Workbook
Name KOL_DB_Header: #REF!

Sheet Cost estimator
B2: Build template for KOL contract negociation.

Sheet Sheet22
B3: dokdoksoda@gmail.com
B5: deenise@deeniseglitz.com
B6: dewyeweat@gmail.com
B12: Aguchi.benson@gmail.com
B13: paulinamikielskaa@gmail.com
B17: stormscape88@gmail.com
B23: hellomegsandalex@gmail.com
B24: Szeyun.low@gmail.com
B25: partners@brenttimm.com
B26: caseycollab@gmail.com
B28: foodtravelexplores@hotmail.com
B29: dhnhatuyen@gmail.com
... B114: zevhu212224@gmail.com

Sheet n8n
A1: Username | B1: Social media type
A2: =IFERROR(__xludf.DUMMYFUNCTION("FILTER('KOL database'!$C$2:$C$869,'KOL database'!$J$2:$J$869<=0)"),"#REF!") -> #REF! | B2: =iferror(XLOOKUP(A2,'KOL database'!$C$2:$C$869,'KOL database'!$F$2:$F$869),"")
B3: =iferror(XLOOKUP(A3,'KOL database'!$C$2:$C$869,'KOL database'!$F$2:$F$869),"")
B4: =iferror(XLOOKUP(A4,'KOL database'!$C$2:$C$869,'KOL database'!$F$2:$F$869),"")
B5: =iferror(XLOOKUP(A5,'KOL database'!$C$2:$C$869,'KOL database'!$F$2:$F$869),"")
B6: =iferror(XLOOKUP(A6,'KOL database'!$C$2:$C$869,'KOL database'!$F$2:$F$869),"")
B7: =iferror(XLOOKUP(A7,'KOL database'!$C$2:$C$869,'KOL database'!$F$2:$F$869),"")
B8: =iferror(XLOOKUP(A8,'KOL database'!$C$2:$C$869,'KOL database'!$F$2:$F$869),"")
B9: =iferror(XLOOKUP(A9,'KOL database'!$C$2:$C$869,'KOL database'!$F$2:$F$869),"")
B10: =iferror(XLOOKUP(A10,'KOL database'!$C$2:$C$869,'KOL database'!$F$2:$F$869),"")
B11: =iferror(XLOOKUP(A11,'KOL database'!$C$2:$C$869,'KOL database'!$F$2:$F$869),"")
B12: =iferror(XLOOKUP(A12,'KOL database'!$C$2:$C$869,'KOL database'!$F$2:$F$869),"")
B13: =iferror(XLOOKUP(A13,'KOL database'!$C$2:$C$869,'KOL database'!$F$2:$F$869),"")
B14: =iferror(XLOOKUP(A14,'KOL database'!$C$2:$C$869,'KOL database'!$F$2:$F$869),"")
... B90: =iferror(XLOOKUP(A90,'KOL database'!$C$2:$C$869,'KOL database'!$F$2:$F$869),"")

Sheet Booking TH
B1: KOL_ID | C1: Username | D1: Followers | E1: Country | F1: Social media URL | G1: Restaurant name | H1: Restaurant ID | I1: Cuisine Type | J1: Package Type | K1: Package price | L1: Package Name | M1: Alergies | N1: Comments | O1: Fee per content | P1: Hotel required | Q1: Validation 1 | R1: Sales in charge | S1: Target Date | T1: Target time | U1: No people | V1: Sales Check | W1: Line_thread_id | X1: Booking ID | Y1: Target post date | Z1: Post details | AA1: Notes | AB1: index
B2: HH-LOIMU | C2: immikeyu | D2: 319003 | E2: Bangkok | G2: Vertigo TOO Banyan Tree | H2: {=XLOOKUP(G2,'Restaurant DB'!B:B,'Restaurant DB'!A:A)} -> 712 | I2: {=XLOOKUP(G2,'Restaurant DB'!B:B,'Restaurant DB'!N:N)} -> Fusion, International | J2: Party Pack | O2: 25000 | Q2: Approved | R2: {=XLOOKUP(G2,'Restaurant DB'!B:B,'Restaurant DB'!I:I)} -> ravi@hungryhub.com, naravadee.sw@banyantree.com, | S2: 45499 | T2: 0.72916667 | U2: 2 | V2: Validated | Z2: Check Later
B3: HH-LOIMU | C3: immikeyu | D3: 319003 | E3: Bangkok | G3: Jim Thompson, A Thai Restaurant | H3: {=XLOOKUP(G3,'Restaurant DB'!B:B,'Restaurant DB'!A:A)} -> 4195 | I3: {=XLOOKUP(G3,'Restaurant DB'!B:B,'Restaurant DB'!N:N)} -> Thai | J3: Party Pack | O3: 25000 | Q3: Approved | R3: {=XLOOKUP(G3,'Restaurant DB'!B:B,'Restaurant DB'!I:I)} -> ravi@hungryhub.com | S3: 45587 | T3: 0.75 | U3: 2 | V3: Validated | Z3: Check Later
B4: HH-LOALZ | C4: ali.al5baz | D4: 94511 | E4: {=XLOOKUP(G4,'Restaurant DB All'!$B$32:$B$5758,'Restaurant DB All'!$I$32:$I$5758)} -> Bangkok | F4: Instagram.com/ali.al5baz | G4: JHOL Coastal Indian Cuisine | H4: {=iferror(XLOOKUP(G4,'Restaurant DB'!B:B,'Restaurant DB'!A:A),".")} -> 4496 | I4: {=XLOOKUP(G4,'Restaurant DB'!B:B,'Restaurant DB'!N:N)} -> Indian | J4: Party Pack | K4: 2990 | L4: Sharing Set for 2 People | O4: 3351.46 | R4: {=XLOOKUP(G4,'Restaurant DB'!B:B,'Restaurant DB'!I:I)} -> ravi@hungryhub.com | S4: 45623 | T4: 0.75 | U4: 2 | V4: Validated | Z4: Check Later
B5: HH-LOALZ | C5: ali.al5baz | D5: 94511 | E5: {=XLOOKUP(G5,'Restaurant DB All'!$B$32:$B$5758,'Restaurant DB All'!$I$32:$I$5758)} -> Bangkok | F5: Instagram.com/ali.al5baz | G5: Jharokha by Indus | H5: {=iferror(XLOOKUP(G5,'Restaurant DB'!B:B,'Restaurant DB'!A:A),".")} -> 4652 | I5: {=XLOOKUP(G5,'Restaurant DB'!B:B,'Restaurant DB'!N:N)} -> Indian | J5: Party Pack | K5: 3000 | L5: Exclusive Dinner Sharing Set for 2 People | O5: 3351.46 | R5: {=XLOOKUP(G5,'Restaurant DB'!B:B,'Restaurant DB'!I:I)} -> ravi@hungryhub.com | S5: 45624 | T5: 0.75 | U5: 2 | V5: Validated | Z5: Check Later
B6: HH-LOALZ | C6: ali.al5baz | D6: 94511 | E6: {=XLOOKUP(G6,'Restaurant DB All'!$B$32:$B$5758,'Restaurant DB All'!$I$32:$I$5758)} -> Bangkok | F6: Instagram.com/ali.al5baz | G6: Florae at Valia Hotel Bangkok | H6: {=iferror(XLOOKUP(G6,'Restaurant DB'!B:B,'Restaurant DB'!A:A),".")} -> 4456 | I6: {=XLOOKUP(G6,'Restaurant DB'!B:B,'Restaurant DB'!N:N)} -> European, Indian, Fusion, Steakhouse | J6: Party Pack | K6: 2599 | L6: Romantic Dinner: 5-Course for 2 People | O6: 3351.46 | R6: {=XLOOKUP(G6,'Restaurant DB'!B:B,'Restaurant DB'!I:I)} -> bond@hungryhub.com | S6: 45641 | T6: 0.83333333 | U6: 2 | V6: Validated | Z6: Check Later
B7: HH-LOALZ | C7: ali.al5baz | D7: 94511 | E7: {=XLOOKUP(G7,'Restaurant DB All'!$B$32:$B$5758,'Restaurant DB All'!$I$32:$I$5758)} -> Bangkok | F7: Instagram.com/ali.al5baz | G7: Nuatair Samyan Mitrtown | H7: {=iferror(XLOOKUP(G7,'Restaurant DB'!B:B,'Restaurant DB'!A:A),".")} -> 4875 | I7: {=XLOOKUP(G7,'Restaurant DB'!B:B,'Restaurant DB'!N:N)} -> Thai, European | J7: All You Can Eat | K7: 999 | L7: Premium: Nuatair Buffet (Jan 1st, 2025 Onwards) | O7: 3351.46 | R7: {=XLOOKUP(G7,'Restaurant DB'!B:B,'Restaurant DB'!I:I)} -> earth@hungryhub.com | S7: 45659 | T7: 0.75 | U7: 2 | V7: Validated | Z7: Check Later
B8: HH-LOBAS | C8: bangkok.rooftops | D8: 182445 | E8: Bangkok | F8: instagram.com/bangkok.rooftops | G8: The Speakeasy Rooftop Bar Bangkok | H8: {=XLOOKUP(G8,'Restaurant DB'!B:B,'Restaurant DB'!A:A)} -> 5140 | I8: {=XLOOKUP(G8,'Restaurant DB'!B:B,'Restaurant DB'!N:N)} -> Fusion, International, American, European | J8: Party Pack | K8: 1190 | L8: 2 Dishes with 1 Alcoholic Beverage (6-8 P.M.) | N8: N/A | O8: 12371 | Q8: Approved | R8: {=XLOOKUP(G8,'Restaurant DB'!B:B,'Restaurant DB'!I:I)} -> ravi@hungryhub.com | S8: 45680 | T8: 0.79166667 | U8: 2 | V8: Booked | X8: 6888788 | Y8: 45699 | Z8: Check Later
B9: HH-LOBAS | C9: bangkok.rooftops | D9: 182445 | E9: Bangkok | F9: instagram.com/bangkok.rooftops | G9: Dark Waters Rooftop Bar & Riverside | H9: {=XLOOKUP(G9,'Restaurant DB'!B:B,'Restaurant DB'!A:A)} -> 4511 | I9: {=XLOOKUP(G9,'Restaurant DB'!B:B,'Restaurant DB'!N:N)} -> International, Fusion, Thai | J9: Party Pack | K9: 1190 | L9: 2 Dishes + Free Flow Alcohol & Soft Drinks | O9: 12371 | Q9: Approved | R9: {=XLOOKUP(G9,'Restaurant DB'!B:B,'Restaurant DB'!I:I)} -> bond@hungryhub.com | S9: 45685 | T9: 0.79166667 | U9: 2 | V9: Booked | X9: 6863186 | Y9: 45701 | Z9: Check Later
B10: HH-LOBAS | C10: bangkok.rooftops | D10: 182445 | E10: Bangkok | F10: instagram.com/bangkok.rooftops | G10: Cielo Sky Bar & Restaurant Rooftop | H10: {=XLOOKUP(G10,'Restaurant DB'!B:B,'Restaurant DB'!A:A)} -> 3934 | I10: {=XLOOKUP(G10,'Restaurant DB'!B:B,'Restaurant DB'!N:N)} -> Fusion, Italian, Thai | J10: Party Pack | K10: 1990 | L10: New: Sharing Set for 2 People | O10: 12371 | Q10: Approved | R10: {=XLOOKUP(G10,'Restaurant DB'!B:B,'Restaurant DB'!I:I)} -> sirirat@hungryhub.com | S10: 45687 | T10: 0.79166667 | U10: 2 | V10: Booked | X10: 6867847 | Y10: 45718 | Z10: Check Later
B11: HH-LOBAS | C11: bangkok.rooftops | D11: 182445 | E11: Bangkok | F11: instagram.com/bangkok.rooftops | G11: LUZ Bangkok Tapas Bar | H11: {=XLOOKUP(G11,'Restaurant DB'!B:B,'Restaurant DB'!A:A)} -> 4897 | I11: {=XLOOKUP(G11,'Restaurant DB'!B:B,'Restaurant DB'!N:N)} -> Spanish | J11: Party Pack | K11: 2390 | L11: LUZ Premium Sharing Set for 2 People | O11: 12371 | Q11: Approved | R11: {=XLOOKUP(G11,'Restaurant DB'!B:B,'Restaurant DB'!I:I)} -> sirirat@hungryhub.com | S11: 45688 | T11: 0.79166667 | U11: 2 | V11: Booked | X11: 6868290 | Y11: 45719 | Z11: Check Later
B12: HH-LOBAS | C12: bangkok.rooftops | D12: 182445 | E12: Bangkok | F12: instagram.com/bangkok.rooftops | G12: ThreeSixty Rooftop Bar at Millennium Hilton Bangkok | H12: {=XLOOKUP(G12,'Restaurant DB'!B:B,'Restaurant DB'!A:A)} -> 4471 | I12: {=XLOOKUP(G12,'Restaurant DB'!B:B,'Restaurant DB'!N:N)} -> International | J12: Party Pack | K12: 1999 | L12: Sharing Set for 2 People with 4 Alcohol Drink | O12: 12371 | Q12: Approved | R12: {=XLOOKUP(G12,'Restaurant DB'!B:B,'Restaurant DB'!I:I)} -> bond@hungryhub.com | S12: 45690 | T12: 0.79166667 | U12: 2 | V12: Booked | X12: 6917649 | Y12: 45700 | Z12: Check Later
B13: =XLOOKUP(C13,'KOL database'!$C$2:$C$869,'KOL database'!$B$2:$B$869) -> #REF! | C13: howtotravelfulltime | D13: 100047 | E13: {=XLOOKUP(G13,'Restaurant DB All'!$B$32:$B$5758,'Restaurant DB All'!$I$32:$I$5758)} -> Bangkok | G13: Butcher Factory by Bangkok Butcher | H13: {=XLOOKUP(G13,'Restaurant DB'!B:B,'Restaurant DB'!A:A)} -> 4178 | I13: {=XLOOKUP(G13,'Restaurant DB'!B:B,'Restaurant DB'!N:N)} -> Steakhouse, Italian, International, American, European | J13: All You Can Eat | K13: 1159 | L13: Dry Aged Buffet Steak | O13: 13500 | Q13: Approved | R13: {=XLOOKUP(G13,'Restaurant DB'!B:B,'Restaurant DB'!I:I)} -> earth@hungryhub.com | S13: 45703 | T13: 0.79166667 | Z13: Check Later
B14: =XLOOKUP(C14,'KOL database'!$C$2:$C$869,'KOL database'!$B$2:$B$869) -> #REF! | C14: eaterries | D14: 26326 | E14: Singapore | G14: Warm Up Cafe @ Mackenzie Road | H14: {=XLOOKUP(G14,'Restaurant DB'!B:B,'Restaurant DB'!A:A)} -> 5318 | I14: {=XLOOKUP(G14,'Restaurant DB'!B:B,'Restaurant DB'!N:N)} -> Thai | J14: Party Pack | K14: 69 | L14: Sharing Set for 2 People | O14: 5062.58 | Q14: Approved | R14: {=XLOOKUP(G14,'Restaurant DB'!B:B,'Restaurant DB'!I:I)} -> fred@hungryhub.com | S14: 45713 | T14: 0.77083333 | U14: 2 | V14: Booked | X14: 7186274 | Z14: Check Later
B15: HH-SGMEY | C15: melicacy | D15: 44191 | E15: {=XLOOKUP(G15,'Restaurant DB All'!$B$32:$B$5758,'Restaurant DB All'!$I$32:$I$5758)} -> Singapore | F15: Instagram.com/melicacy | G15: Forma | H15: {=iferror(XLOOKUP(G15,'Restaurant DB'!B:B,'Restaurant DB'!A:A),".")} -> 5345 | I15: {=XLOOKUP(G15,'Restaurant DB'!B:B,'Restaurant DB'!N:N)} -> Italian | J15: Party Pack | K15: 112 | L15: 3-COURSE WINTER SET DINNER | O15: 5062.58 | R15: {=XLOOKUP(G15,'Restaurant DB'!B:B,'Restaurant DB'!I:I)} -> fred@hungryhub.com | S15: 45713 | T15: 0.79166667 | U15: 2 | V15: Validated | Z15: Check Later
B16: HH-SGMEY | C16: melicacy | D16: 44191 | E16: {=XLOOKUP(G16,'Restaurant DB All'!$B$32:$B$5758,'Restaurant DB All'!$I$32:$I$5758)} -> Singapore | F16: Instagram.com/melicacy | G16: Wild Child Pizzette | H16: {=iferror(XLOOKUP(G16,'Restaurant DB'!B:B,'Restaurant DB'!A:A),".")} -> 5344 | I16: {=XLOOKUP(G16,'Restaurant DB'!B:B,'Restaurant DB'!N:N)} -> Italian | J16: Party Pack | K16: 151 | L16: Sharing Set for 2 People | O16: 5062.58 | R16: {=XLOOKUP(G16,'Restaurant DB'!B:B,'Restaurant DB'!I:I)} -> fred@hungryhub.com | S16: 45714 | T16: 0.79166667 | U16: 2 | V16: Validated | Z16: Check Later
B17: HH-LOALZ | C17: ali.al5baz | D17: 94511 | E17: {=XLOOKUP(G17,'Restaurant DB All'!$B$32:$B$5758,'Restaurant DB All'!$I$32:$I$5758)} -> Bangkok | F17: Instagram.com/ali.al5baz | G17: Copper Beyond Buffet Gaysorn Amarin (Hungry Hub) | H17: {=iferror(XLOOKUP(G17,'Restaurant DB'!B:B,'Restaurant DB'!A:A),".")} -> 4503 | I17: {=XLOOKUP(G17,'Restaurant DB'!B:B,'Restaurant DB'!N:N)} -> European, Fusion, International, Japanese, Thai | J17: All You Can Eat | K17: 2599 | L17: Hungry Hub Pack A - Select 1 Premium Menu | O17: 3351.46 | R17: {=XLOOKUP(G17,'Restaurant DB'!B:B,'Restaurant DB'!I:I)} -> surasit@hungryhub.com | S17: 45717 | T17: 0.8125 | U17: 2 | V17: Validated | Z17: Check Later
B18: HH-LOALZ | C18: ali.al5baz | D18: 94511 | E18: {=XLOOKUP(G18,'Restaurant DB All'!$B$32:$B$5758,'Restaurant DB All'!$I$32:$I$5758)} -> Bangkok | F18: Instagram.com/ali.al5baz | G18: Butcher Factory by Bangkok Butcher | H18: {=iferror(XLOOKUP(G18,'Restaurant DB'!B:B,'Restaurant DB'!A:A),".")} -> 4178 | I18: {=XLOOKUP(G18,'Restaurant DB'!B:B,'Restaurant DB'!N:N)} -> Steakhouse, Italian, International, American, European | J18: All You Can Eat | K18: 1399 | L18: Dry Aged Buffet Steak | O18: 3351.46 | R18: {=XLOOKUP(G18,'Restaurant DB'!B:B,'Restaurant DB'!I:I)} -> earth@hungryhub.com | S18: 45718 | T18: 0.79166667 | U18: 2 | V18: Validated | Z18: Check Later
B19: HH-LOALZ | C19: ali.al5baz | D19: 94511 | E19: {=XLOOKUP(G19,'Restaurant DB All'!$B$32:$B$5758,'Restaurant DB All'!$I$32:$I$5758)} -> Bangkok | F19: Instagram.com/ali.al5baz | G19: Mix Beef Club & Restaurant BKK | H19: {=iferror(XLOOKUP(G19,'Restaurant DB'!B:B,'Restaurant DB'!A:A),".")} -> 4912 | I19: {=XLOOKUP(G19,'Restaurant DB'!B:B,'Restaurant DB'!N:N)} -> Steakhouse, Chinese, Italian, International, Fusion, Thai, European, Thai Southern, Thai Northern | J19: Party Pack | K19: 2190 | L19: Sharing Set for 2 People | O19: 3351.46 | R19: {=XLOOKUP(G19,'Restaurant DB'!B:B,'Restaurant DB'!I:I)} -> bond@hungryhub.com | S19: 45720 | T19: 0.79166667 | U19: 2 | V19: Validated | Z19: Check Later
B20: HH-SGMEY | C20: melicacy | D20: 44191 | E20: {=XLOOKUP(G20,'Restaurant DB All'!$B$32:$B$5758,'Restaurant DB All'!$I$32:$I$5758)} -> Singapore | F20: Instagram.com/melicacy | G20: Mizuya Omakase | H20: {=iferror(XLOOKUP(G20,'Restaurant DB'!B:B,'Restaurant DB'!A:A),".")} -> 5362 | I20: {=XLOOKUP(G20,'Restaurant DB'!B:B,'Restaurant DB'!N:N)} -> Japanese | J20: Party Pack | K20: 155 | L20: Special x2 Omakase 7 Course With Free Flow Green Tea | O20: 5062.58 | R20: {=XLOOKUP(G20,'Restaurant DB'!B:B,'Restaurant DB'!I:I)} -> fred@hungryhub.com | S20: 45720 | T20: 0.79166667 | U20: 2 | V20: Validated | Z20: Check Later
B21: HH-LOALZ | C21: ali.al5baz | D21: 94511 | E21: {=XLOOKUP(G21,'Restaurant DB All'!$B$32:$B$5758,'Restaurant DB All'!$I$32:$I$5758)} -> Bangkok | F21: Instagram.com/ali.al5baz | G21: Mojjo Rooftop Lounge & Bar Skyview Hotel | H21: {=iferror(XLOOKUP(G21,'Restaurant DB'!B:B,'Restaurant DB'!A:A),".")} -> 643 | I21: {=XLOOKUP(G21,'Restaurant DB'!B:B,'Restaurant DB'!N:N)} -> Cuban, Fusion, Mexican, Peruvian | J21: Party Pack | K21: 999 | L21: 3 Dishes & Free Flow Non-Alc. Drinks (90 Mins) | O21: 3351.46 | R21: {=XLOOKUP(G21,'Restaurant DB'!B:B,'Restaurant DB'!I:I)} -> ravi@hungryhub.com | S21: 45721 | T21: 0.79166667 | U21: 2 | V21: Validated | Z21: Check Later
B22: HH-LOALZ | C22: ali.al5baz | D22: 94511 | E22: {=XLOOKUP(G22,'Restaurant DB All'!$B$32:$B$5758,'Restaurant DB All'!$I$32:$I$5758)} -> Bangkok | F22: Instagram.com/ali.al5baz | G22: The Seafood Cafe & Restaurant | H22: {=iferror(XLOOKUP(G22,'Restaurant DB'!B:B,'Restaurant DB'!A:A),".")} -> 1433 | I22: {=XLOOKUP(G22,'Restaurant DB'!B:B,'Restaurant DB'!N:N)} -> Thai, Chinese, International, Fusion | J22: All You Can Eat | K22: 1690 | L22: Premium Seafood Buffet + 1 Premium Jumbo River Prawn | O22: 3351.46 | R22: {=XLOOKUP(G22,'Restaurant DB'!B:B,'Restaurant DB'!I:I)} -> sirirat@hungryhub.com | S22: 45722 | T22: 0.79166667 | U22: 2 | V22: Validated | Z22: Check Later
B23: HH-LODAJ | C23: daddy.xj | D23: 126196 | E23: Bangkok | G23: NAMA Japanese and Seafood Buffet (Hungry Hub) | H23: {=XLOOKUP(G23,'Restaurant DB'!B:B,'Restaurant DB'!A:A)} -> 5149 | I23: {=XLOOKUP(G23,'Restaurant DB'!B:B,'Restaurant DB'!N:N)} -> Japanese | J23: All You Can Eat | K23: 1650 | L23: Premium Box 1 Set + Exclusive Menu + Buffet Line (Sat-Sun) | O23: 5000 | Q23: Approved | R23: {=XLOOKUP(G23,'Restaurant DB'!B:B,'Restaurant DB'!I:I)} -> earth@hungryhub.com | S23: 45724 | T23: 0.54166667 | U23: 2 (1 Adult, 1 kid) | V23: Validated | Z23: Check Later
B24: HH-LOTHI | C24: thara_koiii | D24: 95611 | E24: {=XLOOKUP(G24,'Restaurant DB All'!$B$32:$B$5758,'Restaurant DB All'!$I$32:$I$5758)} -> Singapore | F24: Instagram.com/thara_koiii | G24: Colony At The Ritz-Carlton, Millenia Singapore | H24: {=iferror(XLOOKUP(G24,'Restaurant DB'!B:B,'Restaurant DB'!A:A),".")} -> 5412 | I24: {=XLOOKUP(G24,'Restaurant DB'!B:B,'Restaurant DB'!N:N)} -> International, Singaporean | J24: All You Can Eat | K24: 89 | L24: Lunch Buffet (Mon-Fri) | O24: 1685.8391 | R24: {=XLOOKUP(G24,'Restaurant DB'!B:B,'Restaurant DB'!I:I)} -> fred@hungryhub.com | S24: 45726 | T24: 0.5 | U24: 2 | V24: Validated | Z24: Check Later
B25: =XLOOKUP(C25,'KOL database'!$C$2:$C$869,'KOL database'!$B$2:$B$869) -> #REF! | C25: eaterries | D25: 26326 | E25: Singapore | G25: Wild Child Pizzette | H25: {=XLOOKUP(G25,'Restaurant DB'!B:B,'Restaurant DB'!A:A)} -> 5344 | I25: {=XLOOKUP(G25,'Restaurant DB'!B:B,'Restaurant DB'!N:N)} -> Italian | J25: Party Pack | K25: 151 | L25: Sharing Set for 2 People | O25: 5062.58 | Q25: Approved | R25: {=XLOOKUP(G25,'Restaurant DB'!B:B,'Restaurant DB'!I:I)} -> fred@hungryhub.com | S25: 45731 | T25: 0.54166667 | U25: 2 | V25: Booked | X25: 7175926 | Z25: Check Later
B26: =XLOOKUP(C26,'KOL database'!$C$2:$C$869,'KOL database'!$B$2:$B$869) -> #REF! | C26: eaterries | D26: 26326 | E26: Singapore | G26: Fook Kin 福劲 | H26: {=XLOOKUP(G26,'Restaurant DB'!B:B,'Restaurant DB'!A:A)} -> 5376 | I26: {=XLOOKUP(G26,'Restaurant DB'!B:B,'Restaurant DB'!N:N)} -> Chinese, Singaporean | J26: Party Pack | K26: 76 | L26: Sharing Set for 2 People | O26: 5062.58 | Q26: Approved | R26: {=XLOOKUP(G26,'Restaurant DB'!B:B,'Restaurant DB'!I:I)} -> fred@hungryhub.com | S26: 45734 | T26: 0.79166667 | U26: 2 | V26: Booked | X26: 7344487 | Z26: Check Later
B27: =XLOOKUP(C27,'KOL database'!$C$2:$C$869,'KOL database'!$B$2:$B$869) -> #REF! | C27: sgadventurousduo | D27: 117433 | E27: {=XLOOKUP(G27,'Restaurant DB All'!$B$32:$B$5758,'Restaurant DB All'!$I$32:$I$5758)} -> Bangkok | G27: Kam's Roast Central World | H27: {=XLOOKUP(G27,'Restaurant DB'!B:B,'Restaurant DB'!A:A)} -> 5251 | I27: {=XLOOKUP(G27,'Restaurant DB'!B:B,'Restaurant DB'!N:N)} -> Chinese | J27: Party Pack | K27: 1190 | L27: Premium Set for 2 People | O27: 5905.4996 | Q27: Approved | R27: {=XLOOKUP(G27,'Restaurant DB'!B:B,'Restaurant DB'!I:I)} -> earth@hungryhub.com | S27: 45736 | T27: 0.79166667 | Z27: Check Later
B28: =XLOOKUP(C28,'KOL database'!$C$2:$C$869,'KOL database'!$B$2:$B$869) -> #REF! | C28: sgadventurousduo | D28: 117433 | E28: {=XLOOKUP(G28,'Restaurant DB All'!$B$32:$B$5758,'Restaurant DB All'!$I$32:$I$5758)} -> Bangkok | G28: Oishi Grand Siam Paragon | H28: {=XLOOKUP(G28,'Restaurant DB'!B:B,'Restaurant DB'!A:A)} -> 4039 | I28: {=XLOOKUP(G28,'Restaurant DB'!B:B,'Restaurant DB'!N:N)} -> European, Fusion, International, Japanese | J28: All You Can Eat | K28: 1119 | L28: Oishi Grand: Premium Buffet | O28: 5905.4996 | Q28: Approved | R28: {=XLOOKUP(G28,'Restaurant DB'!B:B,'Restaurant DB'!I:I)} -> bond@hungryhub.com | S28: 45736 | T28: 0.54166667 | Z28: Check Later
B29: =XLOOKUP(C29,'KOL database'!$C$2:$C$869,'KOL database'!$B$2:$B$869) -> #REF! | C29: sgadventurousduo | D29: 117433 | E29: {=XLOOKUP(G29,'Restaurant DB All'!$B$32:$B$5758,'Restaurant DB All'!$I$32:$I$5758)} -> Bangkok | G29: NAMA Japanese and Seafood Buffet (Hungry Hub) | H29: {=XLOOKUP(G29,'Restaurant DB'!B:B,'Restaurant DB'!A:A)} -> 5149 | I29: {=XLOOKUP(G29,'Restaurant DB'!B:B,'Restaurant DB'!N:N)} -> Japanese | J29: All You Can Eat | K29: 1650 | L29: Premium Box 1 Set + Exclusive Menu + Buffet Line (Mon-Fri) | O29: 5905.4996 | Q29: Approved | R29: {=XLOOKUP(G29,'Restaurant DB'!B:B,'Restaurant DB'!I:I)} -> earth@hungryhub.com | S29: 45737 | T29: 0.54166667 | Z29: Check Later
B30: =XLOOKUP(C30,'KOL database'!$C$2:$C$869,'KOL database'!$B$2:$B$869) -> #REF! | C30: howtotravelfulltime | D30: 100047 | E30: {=XLOOKUP(G30,'Restaurant DB All'!$B$32:$B$5758,'Restaurant DB All'!$I$32:$I$5758)} -> Bangkok | G30: About Beef Lava Grill | H30: {=XLOOKUP(G30,'Restaurant DB'!B:B,'Restaurant DB'!A:A)} -> 4751 | I30: {=XLOOKUP(G30,'Restaurant DB'!B:B,'Restaurant DB'!N:N)} -> Japanese, Fusion, Thai | J30: All You Can Eat | K30: 1159 | L30: Premium International Buffet (Only for Hungry Hub) | O30: 13500 | Q30: Approved | R30: {=XLOOKUP(G30,'Restaurant DB'!B:B,'Restaurant DB'!I:I)} -> dew@hungryhub.com | S30: 45738 | T30: 0.70833333 | Z30: Check Later
B31: =XLOOKUP(C31,'KOL database'!$C$2:$C$869,'KOL database'!$B$2:$B$869) -> #REF! | C31: sgadventurousduo | D31: 117433 | E31: {=XLOOKUP(G31,'Restaurant DB All'!$B$32:$B$5758,'Restaurant DB All'!$I$32:$I$5758)} -> Bangkok | G31: Baan Dalaa by Angkana | H31: {=XLOOKUP(G31,'Restaurant DB'!B:B,'Restaurant DB'!A:A)} -> 4778 | I31: {=XLOOKUP(G31,'Restaurant DB'!B:B,'Restaurant DB'!N:N)} -> Thai Southern, Thai | J31: Party Pack | K31: 1350 | L31: Sharing Set for 2 People | O31: 5905.4996 | Q31: Approved | R31: {=XLOOKUP(G31,'Restaurant DB'!B:B,'Restaurant DB'!I:I)} -> dew@hungryhub.com | S31: 45738 | T31: 0.5 | Z31: Check Later
B32: =XLOOKUP(C32,'KOL database'!$C$2:$C$869,'KOL database'!$B$2:$B$869) -> #REF! | C32: sgadventurousduo | D32: 117433 | E32: {=XLOOKUP(G32,'Restaurant DB All'!$B$32:$B$5758,'Restaurant DB All'!$I$32:$I$5758)} -> Bangkok | G32: Butcher Factory by Bangkok Butcher | H32: {=XLOOKUP(G32,'Restaurant DB'!B:B,'Restaurant DB'!A:A)} -> 4178 | I32: {=XLOOKUP(G32,'Restaurant DB'!B:B,'Restaurant DB'!N:N)} -> Steakhouse, Italian, International, American, European | J32: All You Can Eat | K32: 1690 | L32: Premium Dry Aged Gentle Butcher Buffet Steak) | O32: 5905.4996 | Q32: Approved | R32: {=XLOOKUP(G32,'Restaurant DB'!B:B,'Restaurant DB'!I:I)} -> earth@hungryhub.com | S32: 45739 | T32: 0.5 | Z32: Check Later
B33: HH-INJKO | C33: jkonthego | D33: 38900 | E33: Bangkok | G33: Copper Beyond Buffet Gaysorn Amarin (Hungry Hub) | H33: {=XLOOKUP(G33,'Restaurant DB'!B:B,'Restaurant DB'!A:A)} -> 4503 | I33: {=XLOOKUP(G33,'Restaurant DB'!B:B,'Restaurant DB'!N:N)} -> European, Fusion, International, Japanese, Thai | J33: All You Can Eat | K33: 2599 | L33: Hungry Hub Pack A - Select 1 Premium Menu | O33: 1670.6514 | P33: TRUE | Q33: Approved | R33: {=XLOOKUP(G33,'Restaurant DB'!B:B,'Restaurant DB'!I:I)} -> surasit@hungryhub.com | S33: 45740 | T33: 0.8125 | U33: 1 | V33: Booked | X33: 7356179 | Y33: 45741 | Z33: Check Later
B34: =XLOOKUP(C34,'KOL database'!$C$2:$C$869,'KOL database'!$B$2:$B$869) -> #REF! | C34: eaterries | D34: 26326 | E34: Singapore | G34: Bar Cicheti | H34: {=XLOOKUP(G34,'Restaurant DB'!B:B,'Restaurant DB'!A:A)} -> 5343 | I34: {=XLOOKUP(G34,'Restaurant DB'!B:B,'Restaurant DB'!N:N)} -> Italian | J34: Party Pack | K34: 76 | L34: 3-Course Set Dinner Menu | O34: 5062.58 | Q34: Approved | R34: {=XLOOKUP(G34,'Restaurant DB'!B:B,'Restaurant DB'!I:I)} -> fred@hungryhub.com | S34: 45741 | T34: 0.79166667 | U34: 2 | V34: Booked | X34: 7326718 | Z34: Check Later
B35: =XLOOKUP(C35,'KOL database'!$C$2:$C$869,'KOL database'!$B$2:$B$869) -> #REF! | C35: jkonthego | D35: 38900 | E35: {=XLOOKUP(G35,'Restaurant DB All'!$B$32:$B$5758,'Restaurant DB All'!$I$32:$I$5758)} -> Bangkok | G35: Great Harbour International Buffet | H35: {=iferror(XLOOKUP(G35,'Restaurant DB'!B:B,'Restaurant DB'!A:A),".")} -> 3005 | I35: {=XLOOKUP(G35,'Restaurant DB'!B:B,'Restaurant DB'!N:N)} -> Chinese, European, Fusion, International, Japanese, Thai | J35: All You Can Eat | K35: 1493 | L35: Standard Buffet + Durian Buffet | O35: 1670.6514 | P35: TRUE | Q35: Approved | R35: {=XLOOKUP(G35,'Restaurant DB'!B:B,'Restaurant DB'!I:I)} -> bond@hungryhub.com | S35: 45741 | T35: 0.5 | U35: 1 | V35: Booked | X35: 7359498 | Y35: 45747 | Z35: Check Later
B36: =XLOOKUP(C36,'KOL database'!$C$2:$C$869,'KOL database'!$B$2:$B$869) -> #REF! | C36: jkonthego | D36: 38900 | E36: {=XLOOKUP(G36,'Restaurant DB All'!$B$32:$B$5758,'Restaurant DB All'!$I$32:$I$5758)} -> Bangkok | F36: instagram.com/jkonthego | G36: Dark Waters Rooftop Bar & Riverside | H36: {=iferror(XLOOKUP(G36,'Restaurant DB'!B:B,'Restaurant DB'!A:A),".")} -> 4511 | I36: {=XLOOKUP(G36,'Restaurant DB'!B:B,'Restaurant DB'!N:N)} -> International, Fusion, Thai | J36: Party Pack | K36: 1990 | L36: Romantic Set for 2 People (Advance 1 Day) | O36: 1670.6514 | P36: TRUE | Q36: Approved | R36: {=XLOOKUP(G36,'Restaurant DB'!B:B,'Restaurant DB'!I:I)} -> bond@hungryhub.com | S36: 45741 | T36: 0.79166667 | U36: 1 | V36: Booked | X36: 7359514 | Y36: 45743 | Z36: Check Later
B37: =XLOOKUP(C37,'KOL database'!$C$2:$C$869,'KOL database'!$B$2:$B$869) -> #REF! | C37: bangkok.discovery | D37: 199227 | E37: {=XLOOKUP(G37,'Restaurant DB All'!$B$32:$B$5758,'Restaurant DB All'!$I$32:$I$5758)} -> Bangkok | F37: Instagram.com/bangkok.discovery | G37: Oishi Grand Siam Paragon | H37: {=iferror(XLOOKUP(G37,'Restaurant DB'!B:B,'Restaurant DB'!A:A),".")} -> 4039 | I37: {=XLOOKUP(G37,'Restaurant DB'!B:B,'Restaurant DB'!N:N)} -> European, Fusion, International, Japanese | J37: All You Can Eat | K37: 2799 | L37: Oishi Grand: Prestige Buffet | O37: 20250.32 | Q37: Approved | R37: {=XLOOKUP(G37,'Restaurant DB'!B:B,'Restaurant DB'!I:I)} -> bond@hungryhub.com | S37: 45741 | T37: 0.5 | U37: 2 | V37: Validated | Z37: Check Later
B38: =XLOOKUP(C38,'KOL database'!$C$2:$C$869,'KOL database'!$B$2:$B$869) -> #REF! | C38: jkonthego | D38: 38900 | E38: {=XLOOKUP(G38,'Restaurant DB All'!$B$32:$B$5758,'Restaurant DB All'!$I$32:$I$5758)} -> Bangkok | F38: instagram.com/jkonthegoV2 | G38: The Seafood Cafe & Restaurant | H38: {=iferror(XLOOKUP(G38,'Restaurant DB'!B:B,'Restaurant DB'!A:A),".")} -> 1433 | I38: {=XLOOKUP(G38,'Restaurant DB'!B:B,'Restaurant DB'!N:N)} -> Thai, Chinese, International, Fusion | J38: All You Can Eat | K38: 2999 | L38: Lobster Lover Set for 4 People | O38: 1670.6514 | P38: TRUE | Q38: Approved | R38: {=XLOOKUP(G38,'Restaurant DB'!B:B,'Restaurant DB'!I:I)} -> sirirat@hungryhub.com | S38: 45742 | T38: 0.45833333 | U38: 1 | V38: Booked | X38: 7356205 | Y38: 45762 | Z38: Check Later
B39: HH-INJKO | C39: jkonthego | D39: 38900 | E39: Bangkok | G39: Gentle Butcher by Bangkok Butcher | H39: {=XLOOKUP(G39,'Restaurant DB'!B:B,'Restaurant DB'!A:A)} -> 4889 | I39: {=XLOOKUP(G39,'Restaurant DB'!B:B,'Restaurant DB'!N:N)} -> Steakhouse, Fusion, American, Mexican | J39: All You Can Eat | K39: 1690 | L39: Premium Dry Aged Gentle Butcher Buffet Steak | O39: 1670.6514 | P39: TRUE | Q39: Approved | R39: {=XLOOKUP(G39,'Restaurant DB'!B:B,'Restaurant DB'!I:I)} -> earth@hungryhub.com | S39: 45742 | T39: 0.79166667 | U39: 1 | V39: Booked | X39: 7360875 | Y39: 45755 | Z39: Check Later
B40: HH-LOBAE | C40: bangkok.vibe | D40: 33382 | E40: Bangkok | F40: https://www.instagram.com/bangkok.vibe/ | G40: Kam's Roast Central World | H40: {=XLOOKUP(G40,'Restaurant DB'!B:B,'Restaurant DB'!A:A)} -> 5251 | I40: {=XLOOKUP(G40,'Restaurant DB'!B:B,'Restaurant DB'!N:N)} -> Chinese | J40: Party Pack | K40: 1190 | L40: Premium Set for 2 People | O40: 10125.16 | Q40: Approved | R40: {=XLOOKUP(G40,'Restaurant DB'!B:B,'Restaurant DB'!I:I)} -> earth@hungryhub.com | S40: 45742 | T40: 0.5 | U40: 2 | V40: Validated | Z40: Check Later
B41: HH-LOCAW | C41: carmen_wqw | D41: 99495 | E41: Bangkok | G41: RedSquare Rooftop Bar at Novotel Bangkok Sukhumvit 4 | H41: {=XLOOKUP(G41,'Restaurant DB'!B:B,'Restaurant DB'!A:A)} -> 4412 | I41: {=XLOOKUP(G41,'Restaurant DB'!B:B,'Restaurant DB'!N:N)} -> International | J41: Party Pack | O41: 6355.1457 | P41: TRUE | Q41: Approved | R41: {=XLOOKUP(G41,'Restaurant DB'!B:B,'Restaurant DB'!I:I)} -> bond@hungryhub.com | S41: 45743 | T41: 0.75 | U41: 3 | V41: Validated | Y41: 45768 | Z41: Check Later
B42: HH-LOCAW | C42: carmen_wqw | D42: 99495 | E42: Bangkok | G42: Khao Wireless Road | H42: {=XLOOKUP(G42,'Restaurant DB'!B:B,'Restaurant DB'!A:A)} -> 2382 | I42: {=XLOOKUP(G42,'Restaurant DB'!B:B,'Restaurant DB'!N:N)} -> Thai | J42: Party Pack | O42: 6355.1457 | P42: TRUE | Q42: Approved | R42: {=XLOOKUP(G42,'Restaurant DB'!B:B,'Restaurant DB'!I:I)} -> bond@hungryhub.com | S42: 45743 | T42: 0.45833333 | U42: 3 | V42: Validated | Y42: 45787 | Z42: Check Later
B43: HH-LOCAW | C43: carmen_wqw | D43: 99495 | E43: Bangkok | G43: Siam Yacht Club Royal Orchid Sheraton Riverside | H43: {=XLOOKUP(G43,'Restaurant DB'!B:B,'Restaurant DB'!A:A)} -> 3862 | I43: {=XLOOKUP(G43,'Restaurant DB'!B:B,'Restaurant DB'!N:N)} -> International, Italian, Japanese, Thai | J43: Party Pack | O43: 6355.1457 | P43: TRUE | Q43: Approved | R43: {=XLOOKUP(G43,'Restaurant DB'!B:B,'Restaurant DB'!I:I)} -> ravi@hungryhub.com | S43: 45744 | T43: 0.8125 | U43: 3 | V43: Validated | Y43: 45775 | Z43: Check Later
B44: HH-LOCAW | C44: carmen_wqw | D44: 99495 | E44: Bangkok | G44: Copper Beyond Buffet Gaysorn Amarin (Hungry Hub) | H44: {=XLOOKUP(G44,'Restaurant DB'!B:B,'Restaurant DB'!A:A)} -> 4503 | I44: {=XLOOKUP(G44,'Restaurant DB'!B:B,'Restaurant DB'!N:N)} -> European, Fusion, International, Japanese, Thai | J44: All You Can Eat | O44: 6355.1457 | P44: TRUE | Q44: Approved | R44: {=XLOOKUP(G44,'Restaurant DB'!B:B,'Restaurant DB'!I:I)} -> surasit@hungryhub.com | S44: 45745 | T44: 0.52083333 | U44: 3 | V44: Validated | Y44: 45767 | Z44: Check Later
B45: HH-LOCAW | C45: carmen_wqw | D45: 99495 | E45: Bangkok | G45: Saffron Contemporary Thai Signature Rooftop Banyan Tree Bangkok | H45: {=XLOOKUP(G45,'Restaurant DB'!B:B,'Restaurant DB'!A:A)} -> 2506 | I45: {=XLOOKUP(G45,'Restaurant DB'!B:B,'Restaurant DB'!N:N)} -> Thai, Thai Isaan, Thai Southern, Thai Northern | J45: Party Pack | O45: 6355.1457 | P45: TRUE | Q45: Approved | R45: {=XLOOKUP(G45,'Restaurant DB'!B:B,'Restaurant DB'!I:I)} -> ravi@hungryhub.com, naravadee.sw@banyantree.com, | S45: 45745 | T45: 0.79166667 | U45: 3 | V45: Validated | Y45: 45769 | Z45: Check Later
B46: HH-INCHH | C46: chai_shin_yih | D46: 22272 | E46: Bangkok | G46: Siam Yacht Club Royal Orchid Sheraton Riverside | H46: {=XLOOKUP(G46,'Restaurant DB'!B:B,'Restaurant DB'!A:A)} -> 3862 | I46: {=XLOOKUP(G46,'Restaurant DB'!B:B,'Restaurant DB'!N:N)} -> International, Italian, Japanese, Thai | J46: Party Pack | K46: 1990 | L46: The Bar: 3 Dishes & 8 Cocktails or 1 Bottle of Wine for 4 People | O46: 2754 | P46: TRUE | Q46: Approved | R46: {=XLOOKUP(G46,'Restaurant DB'!B:B,'Restaurant DB'!I:I)} -> ravi@hungryhub.com | S46: 45745 | T46: 0.79166667 | U46: 3 | V46: Validated | Z46: Check Later
B47: HH-INCHH | C47: chai_shin_yih | D47: 22272 | E47: Bangkok | G47: NAMA Japanese and Seafood Buffet (Hungry Hub) | H47: {=XLOOKUP(G47,'Restaurant DB'!B:B,'Restaurant DB'!A:A)} -> 5149 | I47: {=XLOOKUP(G47,'Restaurant DB'!B:B,'Restaurant DB'!N:N)} -> Japanese | J47: All You Can Eat | K47: 1650 | L47: Premium Box 1 Set + Exclusive Menu + Buffet Line (Sat-Sun) | O47: 2754 | P47: TRUE | Q47: Approved | R47: {=XLOOKUP(G47,'Restaurant DB'!B:B,'Restaurant DB'!I:I)} -> earth@hungryhub.com | S47: 45746 | T47: 0.45833333 | U47: 3 | V47: Validated | Z47: Check Later
B48: HH-INCHH | C48: chai_shin_yih | D48: 22272 | E48: Bangkok | G48: Vertigo TOO Banyan Tree | H48: {=XLOOKUP(G48,'Restaurant DB'!B:B,'Restaurant DB'!A:A)} -> 712 | I48: {=XLOOKUP(G48,'Restaurant DB'!B:B,'Restaurant DB'!N:N)} -> Fusion, International | J48: Party Pack | K48: 3098 | L48: Romantic Set with 1 Bottle of Wine OR 4 Glasses of Cocktail for 2 People (Book 2 Days in Advance) | O48: 2754 | P48: TRUE | Q48: Approved | R48: {=XLOOKUP(G48,'Restaurant DB'!B:B,'Restaurant DB'!I:I)} -> ravi@hungryhub.com, naravadee.sw@banyantree.com, | S48: 45746 | T48: 0.79166667 | U48: 3 | V48: Asked Guillaume | W48: 574486794880417923 | Z48: Check Later
B49: HH-INCHH | C49: chai_shin_yih | D49: 22272 | E49: Bangkok | G49: Jim Thompson, A Thai Restaurant | H49: {=XLOOKUP(G49,'Restaurant DB'!B:B,'Restaurant DB'!A:A)} -> 4195 | I49: {=XLOOKUP(G49,'Restaurant DB'!B:B,'Restaurant DB'!N:N)} -> Thai | J49: Party Pack | K49: 2590 | L49: Jim's Party A for 2 People inc. 1 drink per person | O49: 2754 | P49: TRUE | Q49: Approved | R49: {=XLOOKUP(G49,'Restaurant DB'!B:B,'Restaurant DB'!I:I)} -> ravi@hungryhub.com | S49: 45747 | T49: 0.47916667 | U49: 3 | V49: Validated | Z49: Check Later
B50: HH-INCHH | C50: chai_shin_yih | D50: 22272 | E50: Bangkok | G50: Copper Beyond Buffet Gaysorn Amarin (Hungry Hub) | H50: {=XLOOKUP(G50,'Restaurant DB'!B:B,'Restaurant DB'!A:A)} -> 4503 | I50: {=XLOOKUP(G50,'Restaurant DB'!B:B,'Restaurant DB'!N:N)} -> European, Fusion, International, Japanese, Thai | J50: All You Can Eat | K50: 2599 | L50: Hungry Hub Pack A - Select 1 Premium Menu | O50: 2754 | P50: TRUE | Q50: Approved | R50: {=XLOOKUP(G50,'Restaurant DB'!B:B,'Restaurant DB'!I:I)} -> surasit@hungryhub.com | S50: 45747 | T50: 0.47916667 | U50: 3 | V50: Validated | Z50: Check Later
B51: HH-LOJEG | C51: jesszhengg | D51: 13331 | E51: Bangkok | G51: Escape Bangkok Emquartier | H51: {=XLOOKUP(G51,'Restaurant DB'!B:B,'Restaurant DB'!A:A)} -> 4750 | I51: {=XLOOKUP(G51,'Restaurant DB'!B:B,'Restaurant DB'!N:N)} -> International, Italian, American, Spanish, European | J51: Party Pack | K51: 1650 | L51: Sharing Set for 2 People (Mon-Fri) | O51: 6000 | Q51: Approved | R51: {=XLOOKUP(G51,'Restaurant DB'!B:B,'Restaurant DB'!I:I)} -> earth@hungryhub.com | S51: 45748 | T51: 0.83333333 | U51: 3 | V51: Validated | Z51: Check Later
B52: HH-LOTHI | C52: thara_koiii | D52: 95611 | E52: {=XLOOKUP(G52,'Restaurant DB All'!$B$32:$B$5758,'Restaurant DB All'!$I$32:$I$5758)} -> Singapore | F52: Instagram.com/thara_koiii | G52: Hai Tien Lo at Pan Pacific Hotel Singapore | H52: {=iferror(XLOOKUP(G52,'Restaurant DB'!B:B,'Restaurant DB'!A:A),".")} -> 5457 | I52: {=XLOOKUP(G52,'Restaurant DB'!B:B,'Restaurant DB'!N:N)} -> Chinese | J52: Party Pack | K52: 110 | L52: Hai Tien Lo l 5-Course Dinner Set | O52: 1685.8391 | R52: {=XLOOKUP(G52,'Restaurant DB'!B:B,'Restaurant DB'!I:I)} -> fred@hungryhub.com | S52: 45749 | T52: 0.75 | U52: 2 | V52: Validated | Z52: Check Later
B53: HH-LOJEG | C53: jesszhengg | D53: 13331 | E53: Bangkok | G53: Siam Yacht Club Royal Orchid Sheraton Riverside | H53: {=XLOOKUP(G53,'Restaurant DB'!B:B,'Restaurant DB'!A:A)} -> 3862 | I53: {=XLOOKUP(G53,'Restaurant DB'!B:B,'Restaurant DB'!N:N)} -> International, Italian, Japanese, Thai | J53: Party Pack | K53: 2790 | L53: utdoor Romantic Set : 4 Dishes & 1 Bottle of Sparkling Wine (Advance 2 Days) | O53: 6000 | Q53: Approved | R53: {=XLOOKUP(G53,'Restaurant DB'!B:B,'Restaurant DB'!I:I)} -> ravi@hungryhub.com | S53: 45753 | T53: 0.79166667 | V53: Validated | Z53: Check Later
B54: HH-LOIMU | C54: immikeyu | D54: 319003 | E54: Bangkok | G54: Copper Beyond Buffet Gaysorn Amarin (Hungry Hub) | H54: {=XLOOKUP(G54,'Restaurant DB'!B:B,'Restaurant DB'!A:A)} -> 4503 | I54: {=XLOOKUP(G54,'Restaurant DB'!B:B,'Restaurant DB'!N:N)} -> European, Fusion, International, Japanese, Thai | J54: All You Can Eat | O54: 25000 | Q54: Approved | R54: {=XLOOKUP(G54,'Restaurant DB'!B:B,'Restaurant DB'!I:I)} -> surasit@hungryhub.com | S54: 45756 | T54: 0.8125 | U54: 3 | V54: Validated | Z54: Check Later
B55: HH-LOJEG | C55: jesszhengg | D55: 13331 | E55: Bangkok | G55: Copper Beyond Buffet Gaysorn Amarin (Hungry Hub) | H55: {=XLOOKUP(G55,'Restaurant DB'!B:B,'Restaurant DB'!A:A)} -> 4503 | I55: {=XLOOKUP(G55,'Restaurant DB'!B:B,'Restaurant DB'!N:N)} -> European, Fusion, International, Japanese, Thai | J55: All You Can Eat | K55: 2599 | L55: Hungry Hub Pack A - Select 1 Premium Menu | O55: 6000 | Q55: Approved | R55: {=XLOOKUP(G55,'Restaurant DB'!B:B,'Restaurant DB'!I:I)} -> surasit@hungryhub.com | S55: 45756 | T55: 0.8125 | V55: Validated | Z55: Check Later
B56: HH-INSTI | C56: stefano_cicchini | D56: 447464 | E56: Bangkok | G56: Copper Beyond Buffet Gaysorn Amarin (Hungry Hub) | H56: {=XLOOKUP(G56,'Restaurant DB'!B:B,'Restaurant DB'!A:A)} -> 4503 | I56: {=XLOOKUP(G56,'Restaurant DB'!B:B,'Restaurant DB'!N:N)} -> European, Fusion, International, Japanese, Thai | J56: All You Can Eat | K56: 2599 | L56: Hungry Hub Pack A - Select 1 Premium Menu | O56: 8780.8252 | Q56: Approved | R56: {=XLOOKUP(G56,'Restaurant DB'!B:B,'Restaurant DB'!I:I)} -> surasit@hungryhub.com | S56: 45758 | T56: 0.5 | V56: Validated | Z56: Check Later
B57: HH-INSTI | C57: stefano_cicchini | D57: 447464 | E57: Bangkok | G57: The St. Regis Bar and The Drawing Room | H57: {=XLOOKUP(G57,'Restaurant DB'!B:B,'Restaurant DB'!A:A)} -> 2634 | I57: {=XLOOKUP(G57,'Restaurant DB'!B:B,'Restaurant DB'!N:N)} -> International | J57: Party Pack | K57: 1200 | L57: 2 cocktails with 1 Dish x 3 packages (new menu) | O57: 8780.8252 | Q57: Approved | R57: {=XLOOKUP(G57,'Restaurant DB'!B:B,'Restaurant DB'!I:I)} -> ravi@hungryhub.com | S57: 45758 | T57: 0.75 | V57: Validated | Z57: Check Later
B58: HH-LOJEG | C58: jesszhengg | D58: 13331 | E58: Bangkok | G58: Nimitr Rooftop by 137 Pillars | H58: {=XLOOKUP(G58,'Restaurant DB'!B:B,'Restaurant DB'!A:A)} -> 2733 | I58: {=XLOOKUP(G58,'Restaurant DB'!B:B,'Restaurant DB'!N:N)} -> Thai | J58: Party Pack | K58: 2590 | L58: 4 Dishes & 4 Mocktail and Cocktail OR 1 Bottle of Wine for 2 People | O58: 6000 | Q58: Approved | R58: {=XLOOKUP(G58,'Restaurant DB'!B:B,'Restaurant DB'!I:I)} -> bond@hungryhub.com | S58: 45759 | T58: 0.83333333 | V58: Validated | Z58: Check Later
B59: HH-INSTI | C59: stefano_cicchini | D59: 447464 | E59: Bangkok | F59: instagram.com/test | G59: Khao Wireless Road | H59: {=XLOOKUP(G59,'Restaurant DB'!B:B,'Restaurant DB'!A:A)} -> 2382 | I59: {=XLOOKUP(G59,'Restaurant DB'!B:B,'Restaurant DB'!N:N)} -> Thai | J59: Party Pack | K59: 4490 | L59: Sharing Set for 3 People | O59: 8780.8252 | Q59: Approved | R59: {=XLOOKUP(G59,'Restaurant DB'!B:B,'Restaurant DB'!I:I)} -> bond@hungryhub.com | S59: 45759 | T59: 0.54166667 | U59: 3 | V59: Validated | Z59: Check Later
B60: HH-INSTI | C60: stefano_cicchini | D60: 447464 | E60: Bangkok | G60: Myste | H60: {=XLOOKUP(G60,'Restaurant DB'!B:B,'Restaurant DB'!A:A)} -> 4747 | I60: {=XLOOKUP(G60,'Restaurant DB'!B:B,'Restaurant DB'!N:N)} -> Fusion | J60: Party Pack | K60: 5990 | L60: Fine Dining 8 Courses | O60: 8780.8252 | Q60: Approved | R60: {=XLOOKUP(G60,'Restaurant DB'!B:B,'Restaurant DB'!I:I)} -> dew@hungryhub.com | S60: 45760 | T60: 0.45833333 | V60: Validated | Z60: Check Later
B61: HH-INSTI | C61: stefano_cicchini | D61: 447464 | E61: Bangkok | G61: Siam Yacht Club Royal Orchid Sheraton Riverside | H61: {=XLOOKUP(G61,'Restaurant DB'!B:B,'Restaurant DB'!A:A)} -> 3862 | I61: {=XLOOKUP(G61,'Restaurant DB'!B:B,'Restaurant DB'!N:N)} -> International, Italian, Japanese, Thai | J61: Party Pack | K61: 1990 | L61: The Bar: 3 Dishes & 8 Cocktails or 1 Bottle of Wine for 4 People | O61: 8780.8252 | Q61: Approved | R61: {=XLOOKUP(G61,'Restaurant DB'!B:B,'Restaurant DB'!I:I)} -> ravi@hungryhub.com | S61: 45760 | T61: 0.77083333 | V61: Validated | Z61: Check Later
B62: HH-INJKO | C62: jkonthego | D62: 38900 | E62: Singapore | G62: Oh Ho Thai BBQ | H62: {=XLOOKUP(G62,'Restaurant DB'!B:B,'Restaurant DB'!A:A)} -> #N/A | I62: {=XLOOKUP(G62,'Restaurant DB'!B:B,'Restaurant DB'!N:N)} -> #N/A | J62: Party Pack | K62: 34 | L62: Sharing Set for 2 People (Book 2 Hours in Advance) | O62: 1670.6514 | P62: FALSE | Q62: Approved | R62: {=XLOOKUP(G62,'Restaurant DB'!B:B,'Restaurant DB'!I:I)} -> #N/A | S62: 45763 | T62: 0.5 | U62: 2 | V62: Booked | X62: 7398610 | Z62: Check Later
B63: HH-LOMAE | C63: ma_vie_nomade | D63: 4663 | E63: Bangkok | G63: Copper Beyond Buffet Gaysorn Amarin (Hungry Hub) | H63: {=XLOOKUP(G63,'Restaurant DB'!B:B,'Restaurant DB'!A:A)} -> 4503 | I63: {=XLOOKUP(G63,'Restaurant DB'!B:B,'Restaurant DB'!N:N)} -> European, Fusion, International, Japanese, Thai | J63: All You Can Eat | K63: 2599 | L63: Hungry Hub Pack A - Select 1 Premium Menu | O63: 0 | Q63: Approved | R63: {=XLOOKUP(G63,'Restaurant DB'!B:B,'Restaurant DB'!I:I)} -> surasit@hungryhub.com | S63: 45763 | T63: 0.8125 | V63: Validated | Z63: Check Later
B64: HH-INJKO | C64: jkonthego | D64: 38900 | E64: Singapore | G64: Home Dusk: Live House | H64: {=XLOOKUP(G64,'Restaurant DB'!B:B,'Restaurant DB'!A:A)} -> 5648 | I64: {=XLOOKUP(G64,'Restaurant DB'!B:B,'Restaurant DB'!N:N)} -> International, Italian, Japanese, Fusion, Korean, American | J64: Party Pack | K64: 130 | L64: Sharing Set for 2 people | O64: 1670.6514 | P64: FALSE | Q64: Approved | R64: {=XLOOKUP(G64,'Restaurant DB'!B:B,'Restaurant DB'!I:I)} -> fred@hungryhub.com | S64: 45764 | T64: 0.77083333 | U64: 2 | V64: Booked | X64: 7398617 | Z64: Check Later
B65: HH-INTAZ | C65: tachichosz | D65: 70870 | E65: Singapore | G65: Bone Apple Tea Bistro | H65: {=XLOOKUP(G65,'Restaurant DB'!B:B,'Restaurant DB'!A:A)} -> 5738 | I65: {=XLOOKUP(G65,'Restaurant DB'!B:B,'Restaurant DB'!N:N)} -> Fusion | J65: Party Pack | K65: 69 | L65: Lunch Set for 2 people | O65: 14152.5 | P65: TRUE | Q65: Approved | R65: {=XLOOKUP(G65,'Restaurant DB'!B:B,'Restaurant DB'!I:I)} -> fred@hungryhub.com | S65: 45764 | T65: 0.66666667 | U65: 2 | V65: Booked | X65: 7419684 | Y65: 45804 | Z65: Check Later
B66: HH-LODID | C66: diaryaroundtheworld | D66: 512171 | E66: Bangkok | G66: The Crystal Grill House at Asiatique The Riverfront | H66: {=XLOOKUP(G66,'Restaurant DB'!B:B,'Restaurant DB'!A:A)} -> 4992 | I66: {=XLOOKUP(G66,'Restaurant DB'!B:B,'Restaurant DB'!N:N)} -> Steakhouse | J66: Party Pack | K66: 2990 | L66: Premium Outside Seating Sharing Set for 2 People | O66: 7000 | Q66: Approved | R66: {=XLOOKUP(G66,'Restaurant DB'!B:B,'Restaurant DB'!I:I)} -> ravi@hungryhub.com | S66: 45764 | T66: 0.79166667 | V66: Validated | Z66: Check Later
B67: HH-LOJEG | C67: jesszhengg | D67: 13331 | E67: Bangkok | G67: Saffron Contemporary Thai Signature Rooftop Banyan Tree Bangkok | H67: {=XLOOKUP(G67,'Restaurant DB'!B:B,'Restaurant DB'!A:A)} -> 2506 | I67: {=XLOOKUP(G67,'Restaurant DB'!B:B,'Restaurant DB'!N:N)} -> Thai, Thai Isaan, Thai Southern, Thai Northern | J67: Party Pack | K67: 1990 | L67: Choose 4 Dishes for 2 Persons [Premium menu] | O67: 6000 | Q67: Approved | R67: {=XLOOKUP(G67,'Restaurant DB'!B:B,'Restaurant DB'!I:I)} -> ravi@hungryhub.com, naravadee.sw@banyantree.com, | S67: 45764 | T67: 0.83333333 | V67: Validated | Z67: Check Later
B68: HH-INTAZ | C68: tachichosz | D68: 70870 | E68: Singapore | G68: Grand Konak Turkish and Lebanese Restaurant | H68: {=XLOOKUP(G68,'Restaurant DB'!B:B,'Restaurant DB'!A:A)} -> 5813 | I68: {=XLOOKUP(G68,'Restaurant DB'!B:B,'Restaurant DB'!N:N)} -> Egyptian, Mediterranean, Lebanese, Turkish, Middle Eastern | J68: Party Pack | K68: 199 | L68: Sharing Set for 2 people | O68: 14152.5 | P68: TRUE | Q68: Approved | R68: {=XLOOKUP(G68,'Restaurant DB'!B:B,'Restaurant DB'!I:I)} -> fred@hungryhub.com | S68: 45765 | T68: 0.47916667 | U68: 2 | V68: Booked | X68: 7421309 | Y68: 45775 | Z68: Check Later
B69: HH-INTAZ | C69: tachichosz | D69: 70870 | E69: Singapore | G69: Waterfall Lounge at Furama Riverfront Hotel | H69: {=XLOOKUP(G69,'Restaurant DB'!B:B,'Restaurant DB'!A:A)} -> 5643 | I69: {=XLOOKUP(G69,'Restaurant DB'!B:B,'Restaurant DB'!N:N)} -> Chinese, European | J69: Party Pack | K69: 50 | L69: Waterfall l Tea Bliss Set for 2 People | O69: 14152.5 | P69: TRUE | Q69: Approved | R69: {=XLOOKUP(G69,'Restaurant DB'!B:B,'Restaurant DB'!I:I)} -> fred@hungryhub.com | S69: 45765 | T69: 0.64583333 | U69: 2 | V69: Booked | X69: 7422629 | Y69: 45777 | Z69: Check Later
B70: HH-LODID | C70: diaryaroundtheworld | D70: 512171 | E70: Bangkok | G70: Vertigo TOO Banyan Tree | H70: {=XLOOKUP(G70,'Restaurant DB'!B:B,'Restaurant DB'!A:A)} -> 712 | I70: {=XLOOKUP(G70,'Restaurant DB'!B:B,'Restaurant DB'!N:N)} -> Fusion, International | J70: Party Pack | K70: 3098 | L70: Romantic Set with 1 Bottle of Wine OR 4 Glasses of Cocktail for 2 People (Book 2 Days in Advance) | O70: 7000 | Q70: Approved | R70: {=XLOOKUP(G70,'Restaurant DB'!B:B,'Restaurant DB'!I:I)} -> ravi@hungryhub.com, naravadee.sw@banyantree.com, | S70: 45765 | T70: 0.79166667 | V70: Validated | Z70: Check Later
B71: HH-LODID | C71: diaryaroundtheworld | D71: 512171 | E71: Bangkok | G71: IGNIV Bangkok at The St.Regis Bangkok (One Michelin Star) | H71: {=XLOOKUP(G71,'Restaurant DB'!B:B,'Restaurant DB'!A:A)} -> 5836 | I71: {=XLOOKUP(G71,'Restaurant DB'!B:B,'Restaurant DB'!N:N)} -> European | J71: Party Pack | K71: 2707 | L71: Lunch Break 4 Course Set | O71: 7000 | Q71: Approved | R71: {=XLOOKUP(G71,'Restaurant DB'!B:B,'Restaurant DB'!I:I)} -> ravi@hungryhub.com | S71: 45765 | T71: 0.5 | V71: Validated | Z71: Check Later
B72: HH-INTAZ | C72: tachichosz | D72: 70870 | E72: Singapore | G72: Taksim Restaurant | H72: {=XLOOKUP(G72,'Restaurant DB'!B:B,'Restaurant DB'!A:A)} -> 5736 | I72: {=XLOOKUP(G72,'Restaurant DB'!B:B,'Restaurant DB'!N:N)} -> Egyptian, Mediterranean, Lebanese, Middle Eastern | J72: Party Pack | K72: 99 | L72: Sharing Set for 2 people | O72: 14152.5 | P72: TRUE | Q72: Approved | R72: {=XLOOKUP(G72,'Restaurant DB'!B:B,'Restaurant DB'!I:I)} -> fred@hungryhub.com | S72: 45766 | T72: 0.83333333 | U72: 2 | V72: Booked | X72: 7419713 | Y72: 45800 | Z72: Check Later
B73: HH-INTAZ | C73: tachichosz | D73: 70870 | E73: Singapore | G73: Tea Lounge at Conrad Singapore Orchard | H73: {=XLOOKUP(G73,'Restaurant DB'!B:B,'Restaurant DB'!A:A)} -> 5597 | I73: {=XLOOKUP(G73,'Restaurant DB'!B:B,'Restaurant DB'!N:N)} -> International | J73: All You Can Eat | K73: 76 | L73: Weekend High Tea Buffet | O73: 14152.5 | P73: TRUE | Q73: Approved | R73: {=XLOOKUP(G73,'Restaurant DB'!B:B,'Restaurant DB'!I:I)} -> fred@hungryhub.com | S73: 45766 | T73: 0.625 | U73: 2 | V73: Booked | X73: 7424025 | Y73: 45772 | Z73: Check Later
B74: HH-LODID | C74: diaryaroundtheworld | D74: 512171 | E74: Bangkok | G74: Siam Yacht Club Royal Orchid Sheraton Riverside | H74: {=XLOOKUP(G74,'Restaurant DB'!B:B,'Restaurant DB'!A:A)} -> 3862 | I74: {=XLOOKUP(G74,'Restaurant DB'!B:B,'Restaurant DB'!N:N)} -> International, Italian, Japanese, Thai | J74: Party Pack | K74: 2790 | L74: Outdoor Romantic Set : 4 Dishes & 1 Bottle of Sparkling Wine (Advance 2 Days) | O74: 7000 | Q74: Approved | R74: {=XLOOKUP(G74,'Restaurant DB'!B:B,'Restaurant DB'!I:I)} -> ravi@hungryhub.com | S74: 45766 | T74: 0.79166667 | V74: Validated | Z74: Check Later
B75: HH-LOBAE | C75: bangkok.vibe | D75: 33382 | E75: Bangkok | F75: https://www.instagram.com/bangkok.vibe/ | G75: Great Harbour International Buffet | H75: {=XLOOKUP(G75,'Restaurant DB'!B:B,'Restaurant DB'!A:A)} -> 3005 | I75: {=XLOOKUP(G75,'Restaurant DB'!B:B,'Restaurant DB'!N:N)} -> Chinese, European, Fusion, International, Japanese, Thai | J75: All You Can Eat | K75: 1100 | L75: Great Harbour: Weekday Buffet (Monday- Friday) | O75: 10125.16 | Q75: Approved | R75: {=XLOOKUP(G75,'Restaurant DB'!B:B,'Restaurant DB'!I:I)} -> bond@hungryhub.com | S75: 45769 | T75: 0.70833333 | U75: 2 | V75: Validated | Z75: Check Later
B76: HH-INJKO | C76: jkonthego | D76: 38900 | E76: Singapore | G76: Fook Kin 福劲 | H76: {=XLOOKUP(G76,'Restaurant DB'!B:B,'Restaurant DB'!A:A)} -> 5376 | I76: {=XLOOKUP(G76,'Restaurant DB'!B:B,'Restaurant DB'!N:N)} -> Chinese, Singaporean | J76: Party Pack | K76: 76 | L76: Sharing Set for 2 People | O76: 1670.6514 | P76: FALSE | Q76: Approved | R76: {=XLOOKUP(G76,'Restaurant DB'!B:B,'Restaurant DB'!I:I)} -> fred@hungryhub.com | S76: 45770 | T76: 0.47916667 | U76: 2 | V76: Booked | X76: 7398622 | Z76: Check Later
B77: HH-LOFOS | C77: foodtravelexplores | D77: 12998 | E77: Phuket | G77: Takieng at Renaissance Resort & Spa (Phuket) | H77: {=XLOOKUP(G77,'Restaurant DB'!B:B,'Restaurant DB'!A:A)} -> 1625 | I77: {=XLOOKUP(G77,'Restaurant DB'!B:B,'Restaurant DB'!N:N)} -> Thai | J77: Party Pack | K77: 2890 | L77: Sharing Set for 3 People | O77: 6233.7156 | Q77: Approved | R77: {=XLOOKUP(G77,'Restaurant DB'!B:B,'Restaurant DB'!I:I)} -> bond@hungryhub.com | S77: 45772 | T77: 0.52083333 | V77: Validated | Z77: Check Later
B78: HH-LODID | C78: diaryaroundtheworld | D78: 512171 | E78: Bangkok | G78: W Omakase Pradit Manutham | H78: {=XLOOKUP(G78,'Restaurant DB'!B:B,'Restaurant DB'!A:A)} -> 3818 | I78: {=XLOOKUP(G78,'Restaurant DB'!B:B,'Restaurant DB'!N:N)} -> Japanese | J78: Party Pack | K78: 4666 | L78: Seasonal Omakase 21 Course | O78: 7000 | Q78: Approved | R78: {=XLOOKUP(G78,'Restaurant DB'!B:B,'Restaurant DB'!I:I)} -> sirirat@hungryhub.com | S78: 45775 | T78: 0.8125 | V78: Validated | Z78: Check Later
B79: HH-LOFOS | C79: foodtravelexplores | D79: 12998 | E79: Bangkok | G79: Copper Beyond Buffet Gaysorn Amarin (Hungry Hub) | H79: {=XLOOKUP(G79,'Restaurant DB'!B:B,'Restaurant DB'!A:A)} -> 4503 | I79: {=XLOOKUP(G79,'Restaurant DB'!B:B,'Restaurant DB'!N:N)} -> European, Fusion, International, Japanese, Thai | J79: All You Can Eat | K79: 2599 | L79: Hungry Hub Pack A - Select 1 Premium Menu | O79: 6233.7156 | Q79: Approved | R79: {=XLOOKUP(G79,'Restaurant DB'!B:B,'Restaurant DB'!I:I)} -> surasit@hungryhub.com | S79: 45776 | T79: 0.8125 | V79: Validated | Z79: Check Later
B80: HH-LOBAY | C80: bangkok.discovery | D80: 199227 | E80: Bangkok | F80: Instagram.com/bangkok.discovery | G80: About Beef Lava Grill | H80: {=XLOOKUP(G80,'Restaurant DB'!B:B,'Restaurant DB'!A:A)} -> 4751 | I80: {=XLOOKUP(G80,'Restaurant DB'!B:B,'Restaurant DB'!N:N)} -> Japanese, Fusion, Thai | J80: All You Can Eat | K80: 1159 | L80: Premium International Buffet (Only for Hungry Hub) | O80: 20250.32 | Q80: Approved | R80: {=XLOOKUP(G80,'Restaurant DB'!B:B,'Restaurant DB'!I:I)} -> dew@hungryhub.com | S80: 45777 | T80: 0.70833333 | U80: 2 | V80: Validated | Z80: Check Later
B81: HH-LOSOY | C81: sovifooddiary | D81: 165096 | E81: Bangkok | G81: The Seafood Cafe & Restaurant | H81: {=XLOOKUP(G81,'Restaurant DB'!B:B,'Restaurant DB'!A:A)} -> 1433 | I81: {=XLOOKUP(G81,'Restaurant DB'!B:B,'Restaurant DB'!N:N)} -> Thai, Chinese, International, Fusion | J81: Party Pack | K81: 1690 | L81: NEW: All You Can Eat with Premium Seafood Buffet + 1 Premium Jumbo River Prawn | O81: 6000 | Q81: Approved | R81: {=XLOOKUP(G81,'Restaurant DB'!B:B,'Restaurant DB'!I:I)} -> sirirat@hungryhub.com | S81: 45777 | T81: 0.47916667 | V81: Validated | Z81: Check Later
B82: HH-LOFOS | C82: foodtravelexplores | D82: 12998 | E82: Bangkok | G82: Khao Wireless Road | H82: {=XLOOKUP(G82,'Restaurant DB'!B:B,'Restaurant DB'!A:A)} -> 2382 | I82: {=XLOOKUP(G82,'Restaurant DB'!B:B,'Restaurant DB'!N:N)} -> Thai | J82: Party Pack | K82: 3880 | L82: Sharing Set for 2 People with 2 Alcohol Drink | O82: 6233.7156 | Q82: Approved | R82: {=XLOOKUP(G82,'Restaurant DB'!B:B,'Restaurant DB'!I:I)} -> bond@hungryhub.com | S82: 45778 | T82: 0.77083333 | V82: Validated | Z82: Check Later
B83: HH-LOSOY | C83: sovifooddiary | D83: 165096 | E83: Bangkok | G83: Khao Jaan-Prod CentralWorld | H83: {=XLOOKUP(G83,'Restaurant DB'!B:B,'Restaurant DB'!A:A)} -> 4311 | I83: {=XLOOKUP(G83,'Restaurant DB'!B:B,'Restaurant DB'!N:N)} -> Thai | J83: Party Pack | K83: 1450 | L83: Sharing Set for 2 People | O83: 6000 | Q83: Approved | R83: {=XLOOKUP(G83,'Restaurant DB'!B:B,'Restaurant DB'!I:I)} -> bond@hungryhub.com | S83: 45778 | T83: 0.47916667 | V83: Validated | Z83: Check Later
B84: HH-LOSOY | C84: sovifooddiary | D84: 165096 | E84: Bangkok | G84: Sirimahannop Asiatique The Riverfront | H84: {=XLOOKUP(G84,'Restaurant DB'!B:B,'Restaurant DB'!A:A)} -> 1893 | I84: {=XLOOKUP(G84,'Restaurant DB'!B:B,'Restaurant DB'!N:N)} -> Thai, International, Fusion, European | J84: Party Pack | K84: 2190 | L84: Premium Sharing Set for 2 People | O84: 6000 | Q84: Approved | R84: {=XLOOKUP(G84,'Restaurant DB'!B:B,'Restaurant DB'!I:I)} -> ravi@hungryhub.com | S84: 45778 | T84: 0.72916667 | V84: Validated | Z84: Check Later
B85: HH-LOMEX | C85: megsandalex | D85: 20381 | E85: Bangkok | G85: Vertigo Rooftop Banyan Tree | H85: {=XLOOKUP(G85,'Restaurant DB'!B:B,'Restaurant DB'!A:A)} -> 280 | I85: {=XLOOKUP(G85,'Restaurant DB'!B:B,'Restaurant DB'!N:N)} -> European, French, Fusion, International, Italian | J85: Party Pack | K85: 6900 | L85: Romantic Dinner w/ 1 bottle of Wine (Book 2 days in advance) | M85: *Allergic to Seafood* | O85: 7000 | Q85: Approved | R85: {=XLOOKUP(G85,'Restaurant DB'!B:B,'Restaurant DB'!I:I)} -> ravi@hungryhub.com, naravadee.sw@banyantree.com, | S85: 45779 | T85: 0.75 | U85: 2 | V85: Validated | Z85: Check Later
B86: HH-LOSOY | C86: sovifooddiary | D86: 165096 | E86: Bangkok | G86: Oishi Grand Siam Paragon | H86: {=XLOOKUP(G86,'Restaurant DB'!B:B,'Restaurant DB'!A:A)} -> 4039 | I86: {=XLOOKUP(G86,'Restaurant DB'!B:B,'Restaurant DB'!N:N)} -> European, Fusion, International, Japanese | J86: All You Can Eat | K86: 1119 | L86: Oishi Grand: Premium Buffet | O86: 6000 | Q86: Approved | R86: {=XLOOKUP(G86,'Restaurant DB'!B:B,'Restaurant DB'!I:I)} -> bond@hungryhub.com | S86: 45779 | T86: 0.47916667 | V86: Validated | Z86: Check Later
B87: HH-LOFOS | C87: foodtravelexplores | D87: 12998 | E87: Bangkok | G87: Neta Grill Seacon Square Srinagarindra | H87: {=XLOOKUP(G87,'Restaurant DB'!B:B,'Restaurant DB'!A:A)} -> 915 | I87: {=XLOOKUP(G87,'Restaurant DB'!B:B,'Restaurant DB'!N:N)} -> Japanese | J87: All You Can Eat | K87: 1662 | L87: Neta Grill Premium Buffet (Discount 10%, 15%) | O87: 6233.7156 | Q87: Approved | R87: {=XLOOKUP(G87,'Restaurant DB'!B:B,'Restaurant DB'!I:I)} -> earth@hungryhub.com | S87: 45780 | T87: 0.52083333 | V87: Validated | Z87: Check Later
B88: HH-LOSOY | C88: sovifooddiary | D88: 165096 | E88: Bangkok | G88: Copper Beyond Buffet Gaysorn Amarin (Hungry Hub) | H88: {=XLOOKUP(G88,'Restaurant DB'!B:B,'Restaurant DB'!A:A)} -> 4503 | I88: {=XLOOKUP(G88,'Restaurant DB'!B:B,'Restaurant DB'!N:N)} -> European, Fusion, International, Japanese, Thai | J88: All You Can Eat | K88: 2599 | L88: Hungry Hub Pack A - Select 1 Premium Menu | O88: 6000 | Q88: Approved | R88: {=XLOOKUP(G88,'Restaurant DB'!B:B,'Restaurant DB'!I:I)} -> surasit@hungryhub.com | S88: 45780 | T88: 0.52083333 | V88: Validated | Z88: Check Later
B89: HH-LOFOS | C89: foodtravelexplores | D89: 12998 | E89: Pattaya | G89: The Sky 32 at Grande CentrePoint Hotel (Pattaya) | H89: {=XLOOKUP(G89,'Restaurant DB'!B:B,'Restaurant DB'!A:A)} -> 2022 | I89: {=XLOOKUP(G89,'Restaurant DB'!B:B,'Restaurant DB'!N:N)} -> International, Fusion, Thai, European | J89: Party Pack | K89: 1290 | L89: Set of 4 Dishes + Free Flow Drink (90 Mins.) for 1 Person | O89: 6233.7156 | Q89: Approved | R89: {=XLOOKUP(G89,'Restaurant DB'!B:B,'Restaurant DB'!I:I)} -> dew@hungryhub.com | S89: 45782 | T89: 0.75 | V89: Validated | Z89: Check Later
B90: HH-LOMEX | C90: megsandalex | D90: 20381 | E90: Bangkok | G90: IGNIV Bangkok at The St.Regis Bangkok (One Michelin Star) | H90: {=XLOOKUP(G90,'Restaurant DB'!B:B,'Restaurant DB'!A:A)} -> 5836 | I90: {=XLOOKUP(G90,'Restaurant DB'!B:B,'Restaurant DB'!N:N)} -> European | J90: Party Pack | K90: 2236 | L90: Dinner: Intro to IGNIV 4 Course | M90: *Allergic to Seafood* | O90: 7000 | Q90: Approved | R90: {=XLOOKUP(G90,'Restaurant DB'!B:B,'Restaurant DB'!I:I)} -> ravi@hungryhub.com | S90: 45784 | T90: 0.8125 | U90: 2 | V90: Validated | Z90: Check Later
B91: HH-LOAJE | C91: aj.some.more | D91: 19521 | E91: Bangkok | G91: Copper Beyond Buffet Gaysorn Amarin (Hungry Hub) | H91: {=XLOOKUP(G91,'Restaurant DB'!B:B,'Restaurant DB'!A:A)} -> 4503 | I91: {=XLOOKUP(G91,'Restaurant DB'!B:B,'Restaurant DB'!N:N)} -> European, Fusion, International, Japanese, Thai | J91: All You Can Eat | K91: 2599 | L91: Hungry Hub Pack A - Select 1 Premium Menu | O91: 10500 | Q91: Approved | R91: {=XLOOKUP(G91,'Restaurant DB'!B:B,'Restaurant DB'!I:I)} -> surasit@hungryhub.com | S91: 45785 | T91: 0.70833333 | U91: 2 | V91: Validated | Z91: Check Later
B92: HH-LOGOE | C92: gooutwithcharlie | D92: 44500 | E92: Bangkok | G92: Siam Yacht Club Royal Orchid Sheraton Riverside | H92: {=XLOOKUP(G92,'Restaurant DB'!B:B,'Restaurant DB'!A:A)} -> 3862 | I92: {=XLOOKUP(G92,'Restaurant DB'!B:B,'Restaurant DB'!N:N)} -> International, Italian, Japanese, Thai | J92: Party Pack | K92: 2290 | L92: Sharing Set for 2 People with Cocktail | O92: 9000 | Q92: Approved | R92: {=XLOOKUP(G92,'Restaurant DB'!B:B,'Restaurant DB'!I:I)} -> ravi@hungryhub.com | S92: 45785 | T92: 0.72916667 | U92: 2 | V92: Validated | Z92: Check Later
B93: HH-INJOR | C93: jocelapar | D93: 78525 | E93: Bangkok | G93: Vertigo TOO Banyan Tree | H93: {=XLOOKUP(G93,'Restaurant DB'!B:B,'Restaurant DB'!A:A)} -> 712 | I93: {=XLOOKUP(G93,'Restaurant DB'!B:B,'Restaurant DB'!N:N)} -> Fusion, International | J93: Party Pack | K93: 2803 | L93: 8 Dishes with Mocktails for 3 People | O93: 6500 | P93: TRUE | Q93: Approved | R93: {=XLOOKUP(G93,'Restaurant DB'!B:B,'Restaurant DB'!I:I)} -> ravi@hungryhub.com, naravadee.sw@banyantree.com, | S93: 45785 | T93: 0.52083333 | U93: 2 | V93: Validated | Z93: Check Later
B94: HH-LOAJE | C94: aj.some.more | D94: 19521 | E94: Bangkok | G94: The Seafood Cafe & Restaurant | H94: {=XLOOKUP(G94,'Restaurant DB'!B:B,'Restaurant DB'!A:A)} -> 1433 | I94: {=XLOOKUP(G94,'Restaurant DB'!B:B,'Restaurant DB'!N:N)} -> Thai, Chinese, International, Fusion | J94: All You Can Eat | K94: 1490 | L94: NEW: All You Can Eat with Premium Seafood Buffet + 1 Premium Menu | O94: 10500 | Q94: Approved | R94: {=XLOOKUP(G94,'Restaurant DB'!B:B,'Restaurant DB'!I:I)} -> sirirat@hungryhub.com | S94: 45786 | T94: 0.5 | U94: 2 | V94: Validated | Z94: Check Later
B95: HH-LOGOE | C95: gooutwithcharlie | D95: 44500 | E95: Bangkok | G95: Great Harbour International Buffet | H95: {=XLOOKUP(G95,'Restaurant DB'!B:B,'Restaurant DB'!A:A)} -> 3005 | I95: {=XLOOKUP(G95,'Restaurant DB'!B:B,'Restaurant DB'!N:N)} -> Chinese, European, Fusion, International, Japanese, Thai | J95: All You Can Eat | K95: 1100 | L95: Great Harbour: Weekday Buffet (Monday- Friday) | O95: 9000 | Q95: Approved | R95: {=XLOOKUP(G95,'Restaurant DB'!B:B,'Restaurant DB'!I:I)} -> bond@hungryhub.com | S95: 45786 | T95: 0.70833333 | U95: 2 | V95: Validated | Z95: {=if(iferror(INDEX(Posts[Username],MATCH(C95&G95,Posts[Username]&Posts[Restaurant Name],0)),"")=C95,"Posted","")} -> Posted
B96: HH-INJOR | C96: jocelapar | D96: 78525 | E96: Bangkok | G96: Kam's Roast Central World | H96: {=XLOOKUP(G96,'Restaurant DB'!B:B,'Restaurant DB'!A:A)} -> 5251 | I96: {=XLOOKUP(G96,'Restaurant DB'!B:B,'Restaurant DB'!N:N)} -> Chinese | J96: Party Pack | K96: 1650 | L96: Premium Set for 3 People | O96: 6500 | P96: TRUE | Q96: Approved | R96: {=XLOOKUP(G96,'Restaurant DB'!B:B,'Restaurant DB'!I:I)} -> earth@hungryhub.com | S96: 45786 | T96: 0.5 | U96: 2 | V96: Validated | Z96: Check Later
B97: HH-INJOR | C97: jocelapar | D97: 78525 | E97: Bangkok | G97: Copper Beyond Buffet Gaysorn Amarin (Hungry Hub) | H97: {=XLOOKUP(G97,'Restaurant DB'!B:B,'Restaurant DB'!A:A)} -> 4503 | I97: {=XLOOKUP(G97,'Restaurant DB'!B:B,'Restaurant DB'!N:N)} -> European, Fusion, International, Japanese, Thai | J97: All You Can Eat | K97: 2599 | L97: Hungry Hub Pack A - Select 1 Premium Menu | O97: 6500 | P97: TRUE | Q97: Approved | R97: {=XLOOKUP(G97,'Restaurant DB'!B:B,'Restaurant DB'!I:I)} -> surasit@hungryhub.com | S97: 45786 | T97: 0.8125 | U97: 2 | V97: Validated | Z97: Check Later
B98: HH-LOGGO | C98: gg_guoguo | D98: 184700 | E98: Bangkok | G98: Copper Beyond Buffet Gaysorn Amarin (Hungry Hub) | H98: {=XLOOKUP(G98,'Restaurant DB'!B:B,'Restaurant DB'!A:A)} -> 4503 | I98: {=XLOOKUP(G98,'Restaurant DB'!B:B,'Restaurant DB'!N:N)} -> European, Fusion, International, Japanese, Thai | J98: All You Can Eat | K98: 2599 | L98: Hungry Hub Pack A - Select 1 Premium Menu | O98: 5000 | Q98: Approved | R98: {=XLOOKUP(G98,'Restaurant DB'!B:B,'Restaurant DB'!I:I)} -> surasit@hungryhub.com | S98: 45787 | T98: 0.70833333 | U98: 1 | V98: Booked | X98: 7475794 | Y98: 45803 | Z98: Check Later
B99: HH-LODAJ | C99: daddy.xj | D99: 126196 | E99: Bangkok | G99: Vantage Point QSNCC | H99: {=XLOOKUP(G99,'Restaurant DB'!B:B,'Restaurant DB'!A:A)} -> 3901 | I99: {=XLOOKUP(G99,'Restaurant DB'!B:B,'Restaurant DB'!N:N)} -> European, French, German, Italian, Mediterranean, Spanish, Steakhouse | J99: All You Can Eat | K99: 990 | L99: Vantage Buffet with Drinks (Lunch) | O99: 5000 | Q99: Approved | R99: {=XLOOKUP(G99,'Restaurant DB'!B:B,'Restaurant DB'!I:I)} -> bond@hungryhub.com | S99: 45787 | T99: 0.45833333 | U99: 2 (1 Adult, 1 kid) | V99: Validated | Z99: Check Later
B100: HH-LOGOE | C100: gooutwithcharlie | D100: 44500 | E100: Bangkok | G100: Copper Beyond Buffet The Sense Pinklao (Hungry Hub) | H100: {=XLOOKUP(G100,'Restaurant DB'!B:B,'Restaurant DB'!A:A)} -> 837 | I100: {=XLOOKUP(G100,'Restaurant DB'!B:B,'Restaurant DB'!N:N)} -> European, Fusion, International, Japanese, Thai | J100: All You Can Eat | K100: 2599 | L100: Hungry Hub Pack A - Select 1 Premium Menu | O100: 9000 | Q100: Approved | R100: {=XLOOKUP(G100,'Restaurant DB'!B:B,'Restaurant DB'!I:I)} -> surasit@hungryhub.com | S100: 45787 | T100: 0.52083333 | U100: 2 | V100: Validated | Z100: Check Later
...

Sheet Booking SG
B1: KOL_ID | C1: Username | D1: Followers | E1: Country | F1: Social media URL | G1: Restaurant name | H1: Restaurant ID | I1: Cuisine Type | J1: Package Type | K1: Package price | L1: Package Name | M1: Allergies | N1: Comments | O1: Fee per content | P1: Column 15 | Q1: Column 16 | R1: Column 17 | S1: Target Date | T1: Target time | U1: No people | V1: Sales Check | W1: Line_thread_id | X1: Booking ID | Y1: Target post date | Z1: Post details | AA1: Notes | AB1: index
B2: HH-TESTING | C2: TESTING | D2: 12345 | E2: Test city | F2: ig.com/testing | G2: tesitng restaurant | H2: {=XLOOKUP(G2,'Restaurant DB All'!B:B,'Restaurant DB All'!A:A)} -> #N/A | I2: {=XLOOKUP(G2,'Restaurant DB'!B:B,'Restaurant DB'!N:N)} -> #N/A | J2: Party Pack | K2: 1234 | L2: Testing menu | M2: Testing alergies | N2: Test comments | O2: 12345 | P2: FALSE | R2: {=XLOOKUP(G2,'Restaurant DB'!B:B,'Restaurant DB'!I:I)} -> #N/A | S2: 33156 | T2: 0.75 | U2: 20 | V2: Asked Guillaume | W2: 588528281180176784 | Z2: TEST | AB2: HH-TESTINGXDE71
B3: HH-TESTING | C3: TESTING | D3: 12345 | E3: Test city | F3: ig.com/testing | G3: test 4 | H3: {=XLOOKUP(G3,'Restaurant DB All'!B:B,'Restaurant DB All'!A:A)} -> #N/A | I3: {=XLOOKUP(G3,'Restaurant DB'!B:B,'Restaurant DB'!N:N)} -> #N/A | J3: Party Pack | K3: 1234 | L3: Testing menu | M3: Testing alergies | N3: Test comments | O3: 12345 | P3: FALSE | R3: {=XLOOKUP(G3,'Restaurant DB'!B:B,'Restaurant DB'!I:I)} -> #N/A | S3: 33177 | T3: 0.79166667 | U3: 100 | V3: Asked Guillaume | W3: 588528294350291663 | Z3: TEST | AB3: HH-TESTINGQHU28
B4: HH-TESTING | C4: TESTING | D4: 12345 | E4: Test city | F4: ig.com/testing | G4: test 3 | H4: {=XLOOKUP(G4,'Restaurant DB All'!B:B,'Restaurant DB All'!A:A)} -> #N/A | I4: {=XLOOKUP(G4,'Restaurant DB'!B:B,'Restaurant DB'!N:N)} -> #N/A | J4: Party Pack | K4: 1234 | L4: Testing menu | M4: Testing alergies | N4: Test comments | O4: 12345 | P4: FALSE | R4: {=XLOOKUP(G4,'Restaurant DB'!B:B,'Restaurant DB'!I:I)} -> #N/A | S4: 33217 | T4: 0.41666667 | U4: 50 | V4: Asked Guillaume | W4: 588528289937883222 | Z4: TEST | AB4: HH-TESTINGYSO07
B5: HH-TESTING | C5: TESTING | D5: 12345 | E5: Test city | F5: ig.com/testing | G5: test 2 | H5: {=XLOOKUP(G5,'Restaurant DB All'!B:B,'Restaurant DB All'!A:A)} -> #N/A | I5: {=XLOOKUP(G5,'Restaurant DB'!B:B,'Restaurant DB'!N:N)} -> #N/A | J5: Party Pack | K5: 1234 | L5: Testing menu | M5: Testing alergies | N5: Test comments | O5: 12345 | P5: FALSE | R5: {=XLOOKUP(G5,'Restaurant DB'!B:B,'Restaurant DB'!I:I)} -> #N/A | S5: 44510 | T5: 0.75 | U5: 10 | V5: Asked Guillaume | W5: 588528285491921411 | Z5: TEST | AB5: HH-TESTINGLNF73
B6: {=XLOOKUP(C6,'KOL database'!$C$2:$C$869,'KOL database'!$B$2:$B$869)} -> #REF! | C6: eaterries | D6: 26326 | E6: Singapore | G6: Warm Up Cafe @ Mackenzie Road | H6: {=XLOOKUP(G6,'Restaurant DB All'!B:B,'Restaurant DB All'!A:A)} -> 5318 | I6: {=XLOOKUP(G6,'Restaurant DB'!B:B,'Restaurant DB'!N:N)} -> Thai | J6: Party Pack | K6: 69 | L6: Sharing Set for 2 People | O6: 5062.58 | Q6: Approved | R6: {=XLOOKUP(G6,'Restaurant DB'!B:B,'Restaurant DB'!I:I)} -> fred@hungryhub.com | S6: 45713 | T6: 0.77083333 | U6: 2 | V6: Booked | X6: 7186274 | Z6: Check Later
B7: HH-SGMEY | C7: melicacy | D7: 44191 | E7: {=XLOOKUP(G7,'Restaurant DB All'!$B$32:$B$5758,'Restaurant DB All'!$I$32:$I$5758)} -> Singapore | F7: Instagram.com/melicacy | G7: Forma | H7: {=XLOOKUP(G7,'Restaurant DB All'!B:B,'Restaurant DB All'!A:A)} -> 5345 | I7: {=XLOOKUP(G7,'Restaurant DB'!B:B,'Restaurant DB'!N:N)} -> Italian | J7: Party Pack | K7: 112 | L7: 3-COURSE WINTER SET DINNER | O7: 5062.58 | R7: {=XLOOKUP(G7,'Restaurant DB'!B:B,'Restaurant DB'!I:I)} -> fred@hungryhub.com | S7: 45713 | T7: 0.79166667 | U7: 2 | V7: Booked | Z7: {=if(iferror(INDEX(Posts[Username],MATCH(C7&G7,Posts[Username]&Posts[Restaurant Name],0)),"")=C7,"Posted","")} -> Posted
B8: HH-SGMEY | C8: melicacy | D8: 44191 | E8: {=XLOOKUP(G8,'Restaurant DB All'!$B$32:$B$5758,'Restaurant DB All'!$I$32:$I$5758)} -> Singapore | F8: Instagram.com/melicacy | G8: Wild Child Pizzette | H8: {=XLOOKUP(G8,'Restaurant DB All'!B:B,'Restaurant DB All'!A:A)} -> 5344 | I8: {=XLOOKUP(G8,'Restaurant DB'!B:B,'Restaurant DB'!N:N)} -> Italian | J8: Party Pack | K8: 151 | L8: Sharing Set for 2 People | O8: 5062.58 | R8: {=XLOOKUP(G8,'Restaurant DB'!B:B,'Restaurant DB'!I:I)} -> fred@hungryhub.com | S8: 45714 | T8: 0.79166667 | U8: 2 | V8: Booked | Z8: Check Later
B9: HH-SGMEY | C9: melicacy | D9: 44191 | E9: {=XLOOKUP(G9,'Restaurant DB All'!$B$32:$B$5758,'Restaurant DB All'!$I$32:$I$5758)} -> Singapore | F9: Instagram.com/melicacy | G9: Mizuya Omakase | H9: {=XLOOKUP(G9,'Restaurant DB All'!B:B,'Restaurant DB All'!A:A)} -> 5362 | I9: {=XLOOKUP(G9,'Restaurant DB'!B:B,'Restaurant DB'!N:N)} -> Japanese | J9: Party Pack | K9: 155 | L9: Special x2 Omakase 7 Course With Free Flow Green Tea | O9: 5062.58 | R9: {=XLOOKUP(G9,'Restaurant DB'!B:B,'Restaurant DB'!I:I)} -> fred@hungryhub.com | S9: 45720 | T9: 0.79166667 | U9: 2 | V9: Booked | Z9: {=if(iferror(INDEX(Posts[Username],MATCH(C9&G9,Posts[Username]&Posts[Restaurant Name],0)),"")=C9,"Posted","")} -> Posted
B10: HH-LOTHI | C10: thara_koiii | D10: 95611 | E10: {=XLOOKUP(G10,'Restaurant DB All'!$B$32:$B$5758,'Restaurant DB All'!$I$32:$I$5758)} -> Singapore | F10: Instagram.com/thara_koiii | G10: Colony At The Ritz-Carlton, Millenia Singapore | H10: {=XLOOKUP(G10,'Restaurant DB All'!B:B,'Restaurant DB All'!A:A)} -> 5412 | I10: {=XLOOKUP(G10,'Restaurant DB'!B:B,'Restaurant DB'!N:N)} -> International, Singaporean | J10: All You Can Eat | K10: 89 | L10: Lunch Buffet (Mon-Fri) | O10: 1685.8391 | R10: {=XLOOKUP(G10,'Restaurant DB'!B:B,'Restaurant DB'!I:I)} -> fred@hungryhub.com | S10: 45726 | T10: 0.5 | U10: 2 | V10: Booked | Z10: {=if(iferror(INDEX(Posts[Username],MATCH(C10&G10,Posts[Username]&Posts[Restaurant Name],0)),"")=C10,"Posted","")} -> Posted
B11: =XLOOKUP(C11,'KOL database'!$C$2:$C$869,'KOL database'!$B$2:$B$869) -> #REF! | C11: eaterries | D11: 26326 | E11: Singapore | G11: Wild Child Pizzette | H11: {=XLOOKUP(G11,'Restaurant DB All'!B:B,'Restaurant DB All'!A:A)} -> 5344 | I11: {=XLOOKUP(G11,'Restaurant DB'!B:B,'Restaurant DB'!N:N)} -> Italian | J11: Party Pack | K11: 151 | L11: Sharing Set for 2 People | O11: 5062.58 | Q11: Approved | R11: {=XLOOKUP(G11,'Restaurant DB'!B:B,'Restaurant DB'!I:I)} -> fred@hungryhub.com | S11: 45731 | T11: 0.54166667 | U11: 2 | V11: Booked | X11: 7175926 | Z11: Check Later
B12: =XLOOKUP(C12,'KOL database'!$C$2:$C$869,'KOL database'!$B$2:$B$869) -> #REF! | C12: eaterries | D12: 26326 | E12: Singapore | G12: Fook Kin 福劲 | H12: {=XLOOKUP(G12,'Restaurant DB All'!B:B,'Restaurant DB All'!A:A)} -> 5376 | I12: {=XLOOKUP(G12,'Restaurant DB'!B:B,'Restaurant DB'!N:N)} -> Chinese, Singaporean | J12: Party Pack | K12: 76 | L12: Sharing Set for 2 People | O12: 5062.58 | Q12: Approved | R12: {=XLOOKUP(G12,'Restaurant DB'!B:B,'Restaurant DB'!I:I)} -> fred@hungryhub.com | S12: 45734 | T12: 0.79166667 | U12: 2 | V12: Booked | X12: 7344487 | Z12: Check Later
B13: =XLOOKUP(C13,'KOL database'!$C$2:$C$869,'KOL database'!$B$2:$B$869) -> #REF! | C13: eaterries | D13: 26326 | E13: Singapore | G13: Bar Cicheti | H13: {=XLOOKUP(G13,'Restaurant DB All'!B:B,'Restaurant DB All'!A:A)} -> 5343 | I13: {=XLOOKUP(G13,'Restaurant DB'!B:B,'Restaurant DB'!N:N)} -> Italian | J13: Party Pack | K13: 76 | L13: 3-Course Set Dinner Menu | O13: 5062.58 | Q13: Approved | R13: {=XLOOKUP(G13,'Restaurant DB'!B:B,'Restaurant DB'!I:I)} -> fred@hungryhub.com | S13: 45741 | T13: 0.79166667 | U13: 2 | V13: Booked | X13: 7326718 | Z13: Check Later
B14: HH-LOTHI | C14: thara_koiii | D14: 95611 | E14: {=XLOOKUP(G14,'Restaurant DB All'!$B$32:$B$5758,'Restaurant DB All'!$I$32:$I$5758)} -> Singapore | F14: Instagram.com/thara_koiii | G14: Hai Tien Lo at Pan Pacific Hotel Singapore | H14: {=XLOOKUP(G14,'Restaurant DB All'!B:B,'Restaurant DB All'!A:A)} -> 5457 | I14: {=XLOOKUP(G14,'Restaurant DB'!B:B,'Restaurant DB'!N:N)} -> Chinese | J14: Party Pack | K14: 110 | L14: Hai Tien Lo l 5-Course Dinner Set | O14: 1685.8391 | R14: {=XLOOKUP(G14,'Restaurant DB'!B:B,'Restaurant DB'!I:I)} -> fred@hungryhub.com | S14: 45749 | T14: 0.75 | U14: 2 | V14: Booked | Z14: {=if(iferror(INDEX(Posts[Username],MATCH(C14&G14,Posts[Username]&Posts[Restaurant Name],0)),"")=C14,"Posted","")} -> Posted
B15: HH-INJKO | C15: jkonthego | D15: 38900 | E15: Singapore | G15: Oh Ho Thai BBQ | H15: {=XLOOKUP(G15,'Restaurant DB All'!B:B,'Restaurant DB All'!A:A)} -> 5474 | I15: {=XLOOKUP(G15,'Restaurant DB'!B:B,'Restaurant DB'!N:N)} -> #N/A | J15: Party Pack | K15: 34 | L15: Sharing Set for 2 People (Book 2 Hours in Advance) | O15: 1670.6514 | P15: FALSE | Q15: Approved | R15: {=XLOOKUP(G15,'Restaurant DB'!B:B,'Restaurant DB'!I:I)} -> #N/A | S15: 45763 | T15: 0.5 | U15: 2 | V15: Booked | X15: 7398610 | Z15: Check Later
B16: HH-INTAZ | C16: tachichosz | D16: 70870 | E16: Singapore | G16: Bone Apple Tea Bistro | H16: {=XLOOKUP(G16,'Restaurant DB All'!B:B,'Restaurant DB All'!A:A)} -> 5738 | I16: {=XLOOKUP(G16,'Restaurant DB'!B:B,'Restaurant DB'!N:N)} -> Fusion | J16: Party Pack | K16: 69 | L16: Lunch Set for 2 people | O16: 14152.5 | P16: TRUE | Q16: Approved | R16: {=XLOOKUP(G16,'Restaurant DB'!B:B,'Restaurant DB'!I:I)} -> fred@hungryhub.com | S16: 45764 | T16: 0.66666667 | U16: 2 | V16: Booked | X16: 7419684 | Y16: 45804 | Z16: {=if(iferror(INDEX(Posts[Username],MATCH(C16&G16,Posts[Username]&Posts[Restaurant Name],0)),"")=C16,"Posted","")} -> Posted
B17: HH-INJKO | C17: jkonthego | D17: 38900 | E17: Singapore | G17: Home Dusk: Live House | H17: {=XLOOKUP(G17,'Restaurant DB All'!B:B,'Restaurant DB All'!A:A)} -> 5648 | I17: {=XLOOKUP(G17,'Restaurant DB'!B:B,'Restaurant DB'!N:N)} -> International, Italian, Japanese, Fusion, Korean, American | J17: Party Pack | K17: 130 | L17: Sharing Set for 2 people | O17: 1670.6514 | P17: FALSE | Q17: Approved | R17: {=XLOOKUP(G17,'Restaurant DB'!B:B,'Restaurant DB'!I:I)} -> fred@hungryhub.com | S17: 45764 | T17: 0.77083333 | U17: 2 | V17: Booked | X17: 7398617 | Z17: Check Later
B18: HH-INTAZ | C18: tachichosz | D18: 70870 | E18: Singapore | G18: Waterfall Lounge at Furama Riverfront Hotel | H18: {=XLOOKUP(G18,'Restaurant DB All'!B:B,'Restaurant DB All'!A:A)} -> 5643 | I18: {=XLOOKUP(G18,'Restaurant DB'!B:B,'Restaurant DB'!N:N)} -> Chinese, European | J18: Party Pack | K18: 50 | L18: Waterfall l Tea Bliss Set for 2 People | O18: 14152.5 | P18: TRUE | Q18: Approved | R18: {=XLOOKUP(G18,'Restaurant DB'!B:B,'Restaurant DB'!I:I)} -> fred@hungryhub.com | S18: 45765 | T18: 0.64583333 | U18: 2 | V18: Booked | X18: 7422629 | Y18: 45777 | Z18: Check Later
B19: HH-INTAZ | C19: tachichosz | D19: 70870 | E19: Singapore | G19: Grand Konak Turkish and Lebanese Restaurant | H19: {=XLOOKUP(G19,'Restaurant DB All'!B:B,'Restaurant DB All'!A:A)} -> 5813 | I19: {=XLOOKUP(G19,'Restaurant DB'!B:B,'Restaurant DB'!N:N)} -> Egyptian, Mediterranean, Lebanese, Turkish, Middle Eastern | J19: Party Pack | K19: 199 | L19: Sharing Set for 2 people | O19: 14152.5 | P19: TRUE | Q19: Approved | R19: {=XLOOKUP(G19,'Restaurant DB'!B:B,'Restaurant DB'!I:I)} -> fred@hungryhub.com | S19: 45765 | T19: 0.47916667 | U19: 2 | V19: Booked | X19: 7421309 | Y19: 45775 | Z19: {=if(iferror(INDEX(Posts[Username],MATCH(C19&G19,Posts[Username]&Posts[Restaurant Name],0)),"")=C19,"Posted","")} -> Posted
B20: HH-INTAZ | C20: tachichosz | D20: 70870 | E20: Singapore | G20: Taksim Restaurant | H20: {=XLOOKUP(G20,'Restaurant DB All'!B:B,'Restaurant DB All'!A:A)} -> 5736 | I20: {=XLOOKUP(G20,'Restaurant DB'!B:B,'Restaurant DB'!N:N)} -> Egyptian, Mediterranean, Lebanese, Middle Eastern | J20: Party Pack | K20: 99 | L20: Sharing Set for 2 people | O20: 14152.5 | P20: TRUE | Q20: Approved | R20: {=XLOOKUP(G20,'Restaurant DB'!B:B,'Restaurant DB'!I:I)} -> fred@hungryhub.com | S20: 45766 | T20: 0.83333333 | U20: 2 | V20: Booked | X20: 7419713 | Y20: 45800 | Z20: {=if(iferror(INDEX(Posts[Username],MATCH(C20&G20,Posts[Username]&Posts[Restaurant Name],0)),"")=C20,"Posted","")} -> Posted
B21: HH-INTAZ | C21: tachichosz | D21: 70870 | E21: Singapore | G21: Tea Lounge at Conrad Singapore Orchard | H21: {=XLOOKUP(G21,'Restaurant DB All'!B:B,'Restaurant DB All'!A:A)} -> 5597 | I21: {=XLOOKUP(G21,'Restaurant DB'!B:B,'Restaurant DB'!N:N)} -> International | J21: All You Can Eat | K21: 76 | L21: Weekend High Tea Buffet | O21: 14152.5 | P21: TRUE | Q21: Approved | R21: {=XLOOKUP(G21,'Restaurant DB'!B:B,'Restaurant DB'!I:I)} -> fred@hungryhub.com | S21: 45766 | T21: 0.625 | U21: 2 | V21: Booked | X21: 7424025 | Y21: 45772 | Z21: {=if(iferror(INDEX(Posts[Username],MATCH(C21&G21,Posts[Username]&Posts[Restaurant Name],0)),"")=C21,"Posted","")} -> Posted
B22: HH-INJKO | C22: jkonthego | D22: 38900 | E22: Singapore | G22: Fook Kin 福劲 | H22: {=XLOOKUP(G22,'Restaurant DB All'!B:B,'Restaurant DB All'!A:A)} -> 5376 | I22: {=XLOOKUP(G22,'Restaurant DB'!B:B,'Restaurant DB'!N:N)} -> Chinese, Singaporean | J22: Party Pack | K22: 76 | L22: Sharing Set for 2 People | O22: 1670.6514 | P22: FALSE | Q22: Approved | R22: {=XLOOKUP(G22,'Restaurant DB'!B:B,'Restaurant DB'!I:I)} -> fred@hungryhub.com | S22: 45770 | T22: 0.47916667 | U22: 2 | V22: Booked | X22: 7398622 | Z22: Check Later
B23: HH-SGLIE | C23: liveloveatwithjie | D23: 20920 | E23: Singapore | G23: Mama Diam 妈妈店 | H23: {=XLOOKUP(G23,'Restaurant DB All'!B:B,'Restaurant DB All'!A:A)} -> 5735 | I23: {=XLOOKUP(G23,'Restaurant DB'!B:B,'Restaurant DB'!N:N)} -> Singaporean, Chinese | J23: Party Pack | K23: 108 | L23: Sharing Set for 2 People | O23: 5062.58 | Q23: Approved | R23: {=XLOOKUP(G23,'Restaurant DB'!B:B,'Restaurant DB'!I:I)} -> fred@hungryhub.com | S23: 45822 | T23: 0.79166667 | U23: 2 | V23: Booked | X23: 7700367 | Z23: {=if(iferror(INDEX(Posts[Username],MATCH(C23&G23,Posts[Username]&Posts[Restaurant Name],0)),"")=C23,"Posted","")} -> Posted
B24: HH-SGMEY | C24: melicacy | D24: 44191 | E24: {=XLOOKUP(G24,'Restaurant DB All'!$B$32:$B$5758,'Restaurant DB All'!$I$32:$I$5758)} -> Singapore | F24: Instagram.com/melicacy | G24: Les Bouchons at Robertson Quay | H24: {=XLOOKUP(G24,'Restaurant DB All'!B:B,'Restaurant DB All'!A:A)} -> 5640 | I24: {=XLOOKUP(G24,'Restaurant DB'!B:B,'Restaurant DB'!N:N)} -> European, French, Steakhouse | J24: Party Pack | K24: 100 | L24: A Taste of France l 3-Course Meal | O24: 5062.58 | R24: {=XLOOKUP(G24,'Restaurant DB'!B:B,'Restaurant DB'!I:I)} -> fred@hungryhub.com | S24: 45828 | T24: 0.79166667 | U24: 2 | V24: Validated | Z24: Check Later
B25: HH-LOMYG | C25: myfoodiegallerysg | D25: 30467 | E25: Singapore | G25: Enjoy Eating House and Bar | H25: {=XLOOKUP(G25,'Restaurant DB All'!B:B,'Restaurant DB All'!A:A)} -> 5462 | I25: {=XLOOKUP(G25,'Restaurant DB'!B:B,'Restaurant DB'!N:N)} -> Chinese, Singaporean | R25: {=XLOOKUP(G25,'Restaurant DB'!B:B,'Restaurant DB'!I:I)} -> fred@hungryhub.com | S25: 45831 | V25: Validated | Z25: Check Later
B26: HH-LOMYG | C26: myfoodiegallerysg | D26: 30467 | E26: Singapore | G26: Hai Tien Lo at Pan Pacific Hotel Singapore | H26: {=XLOOKUP(G26,'Restaurant DB All'!B:B,'Restaurant DB All'!A:A)} -> 5457 | I26: {=XLOOKUP(G26,'Restaurant DB'!B:B,'Restaurant DB'!N:N)} -> Chinese | R26: {=XLOOKUP(G26,'Restaurant DB'!B:B,'Restaurant DB'!I:I)} -> fred@hungryhub.com | S26: 45834 | V26: Validated | Z26: {=if(iferror(INDEX(Posts[Username],MATCH(C26&G26,Posts[Username]&Posts[Restaurant Name],0)),"")=C26,"Posted","")} -> Posted
B27: HH-SGLIE | C27: liveloveatwithjie | D27: 20920 | E27: Singapore | G27: Edge at Pan Pacific Hotel Singapore | H27: {=XLOOKUP(G27,'Restaurant DB All'!B:B,'Restaurant DB All'!A:A)} -> 5465 | I27: {=XLOOKUP(G27,'Restaurant DB'!B:B,'Restaurant DB'!N:N)} -> International | J27: All You Can Eat | K27: 97 | L27: Weekday Dinner Buffet (Sun-Thu) | O27: 5062.58 | Q27: Approved | R27: {=XLOOKUP(G27,'Restaurant DB'!B:B,'Restaurant DB'!I:I)} -> fred@hungryhub.com | S27: 45838 | T27: 0.79166667 | U27: 2 | V27: Booked | X27: 7586879 | Y27: 45861 | Z27: {=if(iferror(INDEX(Posts[Username],MATCH(C27&G27,Posts[Username]&Posts[Restaurant Name],0)),"")=C27,"Posted","")} -> Posted
B28: HH-SGLIE | C28: liveloveatwithjie | D28: 20920 | E28: Singapore | G28: Synthesis 食拿酒稳 Chinese Cuisine | H28: {=XLOOKUP(G28,'Restaurant DB All'!B:B,'Restaurant DB All'!A:A)} -> 5637 | I28: {=XLOOKUP(G28,'Restaurant DB'!B:B,'Restaurant DB'!N:N)} -> Fusion | J28: Party Pack | K28: 248 | L28: Review date:: 30 Jun, 7PM | O28: 5062.58 | Q28: Approved | R28: {=XLOOKUP(G28,'Restaurant DB'!B:B,'Restaurant DB'!I:I)} -> fred@hungryhub.com | S28: 45847 | T28: 0.79166667 | U28: 4 | V28: Booked | X28: 7586898 | Z28: Check Later
B29: HH-INJKO | C29: jkonthego | D29: 38900 | E29: Singapore | G29: Edge at Pan Pacific Hotel Singapore | H29: {=XLOOKUP(G29,'Restaurant DB All'!B:B,'Restaurant DB All'!A:A)} -> 5465 | I29: {=XLOOKUP(G29,'Restaurant DB'!B:B,'Restaurant DB'!N:N)} -> International | J29: All You Can Eat | K29: 97 | L29: Weekday Dinner Buffet (Sun-Thu) | O29: 1670.6514 | P29: FALSE | Q29: Approved | R29: {=XLOOKUP(G29,'Restaurant DB'!B:B,'Restaurant DB'!I:I)} -> fred@hungryhub.com | S29: 45848 | T29: 0.75 | U29: 2 | V29: Booked | X29: 7671275 | Z29: {=if(iferror(INDEX(Posts[Username],MATCH(C29&G29,Posts[Username]&Posts[Restaurant Name],0)),"")=C29,"Posted","")} -> Posted
B30: HH-LOMYG | C30: myfoodiegallerysg | D30: 30467 | E30: {=XLOOKUP(G30,'Restaurant DB All'!$B$32:$B$5758,'Restaurant DB All'!$I$32:$I$5758)} -> Singapore | G30: Crossroads Buffet at Singapore Marriott Tang Plaza Hotel | H30: {=XLOOKUP(G30,'Restaurant DB All'!B:B,'Restaurant DB All'!A:A)} -> 5547 | I30: {=XLOOKUP(G30,'Restaurant DB'!B:B,'Restaurant DB'!N:N)} -> International | P30: FALSE | Q30: Approved | R30: {=XLOOKUP(G30,'Restaurant DB'!B:B,'Restaurant DB'!I:I)} -> fred@hungryhub.com | S30: 45851 | V30: Validated | Z30: {=if(iferror(INDEX(Posts[Username],MATCH(C30&G30,Posts[Username]&Posts[Restaurant Name],0)),"")=C30,"Posted","")} -> Posted
B31: HH-SIGLN | C31: globetrotterkin | D31: 31387 | E31: Singapore | F31: Instagram.com/globetrotterkin | G31: Pacific Emporium at Pan Pacific Hotel Singapore | H31: {=XLOOKUP(G31,'Restaurant DB All'!B:B,'Restaurant DB All'!A:A)} -> 5460 | I31: {=XLOOKUP(G31,'Restaurant DB'!B:B,'Restaurant DB'!N:N)} -> Singaporean | J31: Party Pack | K31: 73.4 | L31: NEW: Local-Inspired Afternoon Tea (Sat-Sun) | O31: 0 | R31: {=XLOOKUP(G31,'Restaurant DB'!B:B,'Restaurant DB'!I:I)} -> fred@hungryhub.com | S31: 45865 | T31: 0.58333333 | U31: 3 | V31: Booked | X31: 7709865 | Z31: Check Later
B32: HH-SIGLN | C32: globetrotterkin | D32: 31387 | E32: Singapore | F32: Instagram.com/globetrotterkin | G32: Shrimp Prawn Seafood | H32: {=XLOOKUP(G32,'Restaurant DB All'!B:B,'Restaurant DB All'!A:A)} -> 5211 | I32: {=XLOOKUP(G32,'Restaurant DB'!B:B,'Restaurant DB'!N:N)} -> Thai | J32: Party Pack | K32: 139 | L32: Premium Set for 3 People | N32: Blogger from KKDAY KOL :globetrotterkin IG : https://www.instagram.com/globetrotterkin/ Follower : 31K | O32: 0 | R32: {=XLOOKUP(G32,'Restaurant DB'!B:B,'Restaurant DB'!I:I)} -> fred@hungryhub.com | S32: 45867 | T32: 0.79166667 | U32: 3 | V32: Booked | X32: 7751400 | Z32: Check Later
B33: HH-SIGLN | C33: globetrotterkin | D33: 31387 | E33: {=XLOOKUP(G33,'Restaurant DB All'!$B$32:$B$5758,'Restaurant DB All'!$I$32:$I$5758)} -> Singapore | F33: Instagram.com/globetrotterkin | G33: The Seafood Market by House of White Bee Hoon | H33: {=XLOOKUP(G33,'Restaurant DB All'!B:B,'Restaurant DB All'!A:A)} -> 5755 | I33: {=XLOOKUP(G33,'Restaurant DB'!B:B,'Restaurant DB'!N:N)} -> Chinese | J33: Party Pack | K33: 255 | L33: Sharing Set for 3 people | O33: 0 | R33: {=XLOOKUP(G33,'Restaurant DB'!B:B,'Restaurant DB'!I:I)} -> fred@hungryhub.com | S33: 45867 | T33: 0.79166667 | U33: 3 | V33: Validated | Z33: Check Later
B34: {=XLOOKUP(C34,'KOL database'!$C$2:$C$299,'KOL database'!$B$2:$B$299)} -> #REF! | C34: eaterries | D34: 26326 | E34: Singapore | G34: Enjoy Eating House and Bar | H34: {=XLOOKUP(G34,'Restaurant DB All'!B:B,'Restaurant DB All'!A:A)} -> 5462 | I34: {=XLOOKUP(G34,'Restaurant DB'!B:B,'Restaurant DB'!N:N)} -> Chinese, Singaporean | J34: Party Pack | K34: 85 | L34: Sharing Set for 2 People | O34: 5062.58 | Q34: Approved | R34: {=XLOOKUP(G34,'Restaurant DB'!B:B,'Restaurant DB'!I:I)} -> fred@hungryhub.com | S34: 45867 | T34: 0.79166667 | U34: 2 | V34: Booked | X34: 7733275 | Z34: Check Later
B35: HH-SGEAG | C35: eatsnapsg | D35: 25100 | E35: {=XLOOKUP(G35,'Restaurant DB All'!$B$32:$B$5758,'Restaurant DB All'!$I$32:$I$5758)} -> Singapore | F35: Tiktok.com/@eatsnapsg | G35: O.BBa Jjajang | H35: {=XLOOKUP(G35,'Restaurant DB All'!B:B,'Restaurant DB All'!A:A)} -> 6153 | I35: {=XLOOKUP(G35,'Restaurant DB'!B:B,'Restaurant DB'!N:N)} -> Korean | K35: 159 | L35: BBQ Set for 3 People | M35: No Dietary restrictions | N35: August Campaign | O35: 1265.645 | R35: {=XLOOKUP(G35,'Restaurant DB'!B:B,'Restaurant DB'!I:I)} -> fred@hungryhub.com | S35: 45881 | T35: 0.8125 | U35: 3 | V35: Booked | X35: 7799247 | Y35: 45897 | Z35: {=if(iferror(INDEX(Posts[Username],MATCH(C35&G35,Posts[Username]&Posts[Restaurant Name],0)),"")=C35,"Posted","")} -> Posted | AA35: Guillaume
B36: HH-INBIK | C36: bigjohnjiak | D36: 48879 | E36: {=XLOOKUP(G36,'Restaurant DB All'!$B$32:$B$5758,'Restaurant DB All'!$I$32:$I$5758)} -> Singapore | G36: Nozomi at Millenia Walk | H36: {=XLOOKUP(G36,'Restaurant DB All'!B:B,'Restaurant DB All'!A:A)} -> 5594 | I36: {=XLOOKUP(G36,'Restaurant DB'!B:B,'Restaurant DB'!N:N)} -> Japanese | J36: All You Can Eat | K36: 139 | L36: Nozomi l Premium Buffet & 1 Special Menu | M36: None | N36: August Campaign, Instagram : https://www.instagram.com/bigjohnjiak/ | O36: 12656.45 | Q36: Approved | R36: {=XLOOKUP(G36,'Restaurant DB'!B:B,'Restaurant DB'!I:I)} -> fred@hungryhub.com | S36: 45881 | T36: 0.47916667 | U36: 2 | V36: Booked | W36: 573865938483937496 | X36: 7826084 | Z36: {=if(iferror(INDEX(Posts[Username],MATCH(C36&G36,Posts[Username]&Posts[Restaurant Name],0)),"")=C36,"Posted","")} -> Posted | AA36: Sirada
B37: HH-SGGIS | C37: girldevours | D37: 2338 | E37: {=XLOOKUP(G37,'Restaurant DB All'!$B$32:$B$5758,'Restaurant DB All'!$I$32:$I$5758)} -> Singapore | F37: Tiktok.com/@girldevours | G37: Wild Child Pizzette | H37: {=XLOOKUP(G37,'Restaurant DB All'!B:B,'Restaurant DB All'!A:A)} -> 5344 | I37: {=XLOOKUP(G37,'Restaurant DB'!B:B,'Restaurant DB'!N:N)} -> Italian | J37: Party Pack | K37: 115 | L37: Sharing set for 2 | M37: None | N37: August Campaign | O37: 1518.774 | R37: {=XLOOKUP(G37,'Restaurant DB'!B:B,'Restaurant DB'!I:I)} -> fred@hungryhub.com | S37: 45885 | T37: 0.75 | U37: 2 | V37: Booked | W37: 573456397380092487 | X37: 7833694 | Y37: 45893 | Z37: {=if(iferror(INDEX(Posts[Username],MATCH(C37&G37,Posts[Username]&Posts[Restaurant Name],0)),"")=C37,"Posted","")} -> Posted | AA37: Guillaume
B38: HH-INPAR | C38: parttimefoodblogger | D38: 16406 | E38: Singapore | F38: Instagram.com/parttimefoodblogger | G38: Baia Rooftop Dining Lounge Bar | H38: {=XLOOKUP(G38,'Restaurant DB All'!B:B,'Restaurant DB All'!A:A)} -> 5647 | I38: {=XLOOKUP(G38,'Restaurant DB'!B:B,'Restaurant DB'!N:N)} -> Fusion | J38: Party Pack | K38: 228 | L38: Sharing Set for 4 People | M38: None | N38: August Campaign, Instagram : https://www.instagram.com/parttimefoodblogger/ (will post on Tiktok too) | O38: 10125.16 | R38: {=XLOOKUP(G38,'Restaurant DB'!B:B,'Restaurant DB'!I:I)} -> fred@hungryhub.com | S38: 45887 | T38: 0.79166667 | U38: 4 | V38: Refused | W38: 574165946647183599 | Z38: {=if(iferror(INDEX(Posts[Username],MATCH(C38&G38,Posts[Username]&Posts[Restaurant Name],0)),"")=C38,"Posted","")} | AA38: Sirada | AB38: HH-INPARXEU
B39: HH-INROA | C39: roadtrippers.asia | D39: 51300 | E39: Singapore | F39: Tiktok.com/@roadtrippers.asia | G39: Riviera | H39: {=XLOOKUP(G39,'Restaurant DB All'!B:B,'Restaurant DB All'!A:A)} -> 6087 | I39: {=XLOOKUP(G39,'Restaurant DB'!B:B,'Restaurant DB'!N:N)} -> Fusion, French, Mediterranean | J39: All You Can Eat | K39: 169.2 | L39: Lunch course 3 meals - 3 pax | M39: None | N39: August Campaign Tiktok https://www.tiktok.com/@roadtrippers.asia IG https://www.instagram.com/eatwithandrewchan Facebook https://www.facebook.com/@roadtrippers.asia Lemon8 https://www.lemon8-app.com/@roadtrippers.asia Xiao Hong Shu https://www.xiaohongshu.com/user/profile/66b9854e000000001d020eb8 Youtube https://youtube.com/@roadtrippers-asia | O39: 7593.87 | R39: {=XLOOKUP(G39,'Restaurant DB'!B:B,'Restaurant DB'!I:I)} -> fred@hungryhub.com | S39: 45888 | T39: 0.52083333 | U39: 3 | V39: Booked | W39: 574749961032826970 | X39: 7850140 | Y39: 45905 | Z39: {=if(iferror(INDEX(Posts[Username],MATCH(C39&G39,Posts[Username]&Posts[Restaurant Name],0)),"")=C39,"Posted","")} -> Posted | AA39: Guillaume
B40: HH-INROA | C40: roadtrippers.asia | D40: 51300 | E40: Singapore | F40: Tiktok.com/@roadtrippers.asia | G40: Bar Cicheti | H40: {=XLOOKUP(G40,'Restaurant DB All'!B:B,'Restaurant DB All'!A:A)} -> 5343 | I40: {=XLOOKUP(G40,'Restaurant DB'!B:B,'Restaurant DB'!N:N)} -> Italian | J40: Party Pack | K40: 76 | L40: 3-course set dinner menu | M40: None | N40: August Campaing Tiktok https://www.tiktok.com/@roadtrippers.asia IG https://www.instagram.com/eatwithandrewchan Facebook https://www.facebook.com/@roadtrippers.asia Lemon8 https://www.lemon8-app.com/@roadtrippers.asia Xiao Hong Shu https://www.xiaohongshu.com/user/profile/66b9854e000000001d020eb8 Youtube https://youtube.com/@roadtrippers-asia | O40: 7593.87 | R40: {=XLOOKUP(G40,'Restaurant DB'!B:B,'Restaurant DB'!I:I)} -> fred@hungryhub.com | S40: 45888 | T40: 0.79166667 | U40: 3 | V40: Booked | X40: 7813043 | Y40: 45898 | Z40: {=if(iferror(INDEX(Posts[Username],MATCH(C40&G40,Posts[Username]&Posts[Restaurant Name],0)),"")=C40,"Posted","")} -> Posted | AA40: Guillaume
B41: HH-SGQIX | C41: qingxiangsqx | D41: 23385 | E41: {=XLOOKUP(G41,'Restaurant DB All'!$B$32:$B$5758,'Restaurant DB All'!$I$32:$I$5758)} -> Singapore | F41: Instagram.com/qingxiangsqx | G41: Mama Diam 妈妈店 | H41: {=XLOOKUP(G41,'Restaurant DB All'!B:B,'Restaurant DB All'!A:A)} -> 5735 | I41: {=XLOOKUP(G41,'Restaurant DB'!B:B,'Restaurant DB'!N:N)} -> Singaporean, Chinese | J41: Party Pack | K41: 180 | L41: Sharing Set for 4 People | M41: Guest does not eat: Lamb or beef | N41: August Campaign | O41: 1265.645 | R41: {=XLOOKUP(G41,'Restaurant DB'!B:B,'Restaurant DB'!I:I)} -> fred@hungryhub.com | S41: 45888 | T41: 0.80208333 | U41: 3 | V41: Booked | X41: 7834272 | Y41: 45897 | Z41: {=if(iferror(INDEX(Posts[Username],MATCH(C41&G41,Posts[Username]&Posts[Restaurant Name],0)),"")=C41,"Posted","")} -> Posted | AA41: Guillaume
B42: HH-INROA | C42: roadtrippers.asia | D42: 51300 | E42: Singapore | F42: Tiktok.com/@roadtrippers.asia | G42: Fu Lin Bar & Kitchen (Clarke Quay) | H42: {=XLOOKUP(G42,'Restaurant DB All'!B:B,'Restaurant DB All'!A:A)} -> 6151 | I42: {=XLOOKUP(G42,'Restaurant DB'!B:B,'Restaurant DB'!N:N)} -> Chinese, Fusion, Singaporean | J42: Party Pack | K42: 159 | L42: Sharing set for 3 people | M42: None | N42: August Campaign Tiktok https://www.tiktok.com/@roadtrippers.asia IG https://www.instagram.com/eatwithandrewchan Facebook https://www.facebook.com/@roadtrippers.asia Lemon8 https://www.lemon8-app.com/@roadtrippers.asia Xiao Hong Shu https://www.xiaohongshu.com/user/profile/66b9854e000000001d020eb8 Youtube https://youtube.com/@roadtrippers-asia | O42: 7593.87 | R42: {=XLOOKUP(G42,'Restaurant DB'!B:B,'Restaurant DB'!I:I)} -> fred@hungryhub.com | S42: 45889 | T42: 0.5 | U42: 3 | V42: Booked | W42: 574190196955283542 | X42: 7835968 | Y42: 45903 | Z42: {=if(iferror(INDEX(Posts[Username],MATCH(C42&G42,Posts[Username]&Posts[Restaurant Name],0)),"")=C42,"Posted","")} -> Posted | AA42: Guillaume
B43: HH-SGGIS | C43: girldevours | D43: 2338 | E43: {=XLOOKUP(G43,'Restaurant DB All'!$B$32:$B$5758,'Restaurant DB All'!$I$32:$I$5758)} -> Singapore | F43: Tiktok.com/@girldevours | G43: Nozomi at Millenia Walk | H43: {=XLOOKUP(G43,'Restaurant DB All'!B:B,'Restaurant DB All'!A:A)} -> 5594 | I43: {=XLOOKUP(G43,'Restaurant DB'!B:B,'Restaurant DB'!N:N)} -> Japanese | J43: All You Can Eat | K43: =69*2 -> 138 | L43: Nozomi l Premium Buffet | M43: None | N43: August Campaign | O43: 1518.774 | R43: {=XLOOKUP(G43,'Restaurant DB'!B:B,'Restaurant DB'!I:I)} -> fred@hungryhub.com | S43: 45892 | T43: 0.75 | U43: 2 | V43: Booked | X43: 7801439 | Y43: 45899 | Z43: {=if(iferror(INDEX(Posts[Username],MATCH(C43&G43,Posts[Username]&Posts[Restaurant Name],0)),"")=C43,"Posted","")} -> Posted | AA43: Guillaume
B44: HH-SGJJ6 | C44: jjloves86 | D44: 14291 | E44: Singapore | F44: Instagram.com/jjloves86 | G44: Edge at Pan Pacific Hotel Singapore | H44: {=XLOOKUP(G44,'Restaurant DB All'!B:B,'Restaurant DB All'!A:A)} -> 5465 | I44: {=XLOOKUP(G44,'Restaurant DB'!B:B,'Restaurant DB'!N:N)} -> International | J44: All You Can Eat | K44: 81 | L44: Saturday Lunch | N44: August Campaign | O44: 3796.935 | R44: {=XLOOKUP(G44,'Restaurant DB'!B:B,'Restaurant DB'!I:I)} -> fred@hungryhub.com | S44: 45892 | T44: 0.5 | U44: 3 | V44: Booked | X44: 7808185 | Y44: 45896 | Z44: {=if(iferror(INDEX(Posts[Username],MATCH(C44&G44,Posts[Username]&Posts[Restaurant Name],0)),"")=C44,"Posted","")} -> Posted | AA44: Guillaume
B45: HH-INGOS | C45: goofytwocooks | D45: 28732 | E45: {=XLOOKUP(G45,'Restaurant DB All'!$B$32:$B$5758,'Restaurant DB All'!$I$32:$I$5758)} -> Singapore | F45: https://www.instagram.com/goofytwocooks/ | G45: Nozomi at Millenia Walk | H45: {=XLOOKUP(G45,'Restaurant DB All'!B:B,'Restaurant DB All'!A:A)} -> 5594 | I45: {=XLOOKUP(G45,'Restaurant DB'!B:B,'Restaurant DB'!N:N)} -> Japanese | J45: All You Can Eat | K45: 69 | L45: Nozomi l Premium Buffet | M45: None | O45: 3796.935 | Q45: Approved | R45: {=XLOOKUP(G45,'Restaurant DB'!B:B,'Restaurant DB'!I:I)} -> fred@hungryhub.com | S45: 45892 | T45: 0.5 | U45: 4 | V45: Booked | X45: 7808162 | Z45: {=if(iferror(INDEX(Posts[Username],MATCH(C45&G45,Posts[Username]&Posts[Restaurant Name],0)),"")=C45,"Posted","")} -> Posted | AA45: Sirada
B46: HH-SGVIN | C46: vincas_kitchen | D46: 20961 | E46: {=XLOOKUP(G46,'Restaurant DB All'!$B$32:$B$5758,'Restaurant DB All'!$I$32:$I$5758)} -> Singapore | F46: Instagram.com/vincas_kitchen | G46: Mama Diam 妈妈店 | H46: {=XLOOKUP(G46,'Restaurant DB All'!B:B,'Restaurant DB All'!A:A)} -> 5735 | I46: {=XLOOKUP(G46,'Restaurant DB'!B:B,'Restaurant DB'!N:N)} -> Singaporean, Chinese | J46: Party Pack | K46: 180 | L46: Sharing set for 4 people | M46: None | N46: August Campaign (updated time) | O46: 5062.58 | R46: {=XLOOKUP(G46,'Restaurant DB'!B:B,'Restaurant DB'!I:I)} -> fred@hungryhub.com | S46: 45893 | T46: 0.79166667 | U46: 4 | V46: Booked | W46: 574457070502281256 | X46: 7860950 | Y46: 45898 | Z46: {=if(iferror(INDEX(Posts[Username],MATCH(C46&G46,Posts[Username]&Posts[Restaurant Name],0)),"")=C46,"Posted","")} -> Posted | AA46: Guillaume
B47: HH-LOTHZ | C47: thesiutwinz | D47: 23792 | E47: {=XLOOKUP(G47,'Restaurant DB All'!$B$32:$B$5758,'Restaurant DB All'!$I$32:$I$5758)} -> Singapore | F47: Instagram.com/thesiutwinz | G47: NOVA | H47: {=XLOOKUP(G47,'Restaurant DB All'!B:B,'Restaurant DB All'!A:A)} -> 6057 | I47: {=XLOOKUP(G47,'Restaurant DB'!B:B,'Restaurant DB'!N:N)} -> Fusion | J47: Party Pack | K47: 129 | L47: Sip & Dine for 2 People | N47: Additional social media : Instagram : https://www.instagram.com/Twinzinbangkok | O47: 7000 | R47: {=XLOOKUP(G47,'Restaurant DB'!B:B,'Restaurant DB'!I:I)} -> fred@hungryhub.com | S47: 45894 | T47: 0.79166667 | U47: 2 | V47: Booked | W47: 573865938416828669 | X47: 7852372 | Y47: 45903 | Z47: posted | AA47: Guillaume
B48: HH-SGVIN | C48: vincas_kitchen | D48: 20961 | E48: {=XLOOKUP(G48,'Restaurant DB All'!$B$32:$B$5758,'Restaurant DB All'!$I$32:$I$5758)} -> Singapore | F48: Instagram.com/vincas_kitchen | G48: Enjoy Eating House and Bar | H48: {=XLOOKUP(G48,'Restaurant DB All'!B:B,'Restaurant DB All'!A:A)} -> 5462 | I48: {=XLOOKUP(G48,'Restaurant DB'!B:B,'Restaurant DB'!N:N)} -> Chinese, Singaporean | J48: Party Pack | K48: 145 | L48: Sharing Set for 3 people | M48: None | N48: August Campaign | O48: 5062.58 | R48: {=XLOOKUP(G48,'Restaurant DB'!B:B,'Restaurant DB'!I:I)} -> fred@hungryhub.com | S48: 45896 | T48: 0.5 | U48: 3 | V48: Booked | W48: 574154487775363232 | X48: 7836071 | Y48: 45903 | Z48: {=if(iferror(INDEX(Posts[Username],MATCH(C48&G48,Posts[Username]&Posts[Restaurant Name],0)),"")=C48,"Posted","")} -> Posted | AA48: Guillaume
B49: HH-SGTHY | C49: the_ace_sisters_and_mummy_fay | D49: 26886 | F49: Instagram.com/the_ace_sisters_and_mummy_fay | G49: Food Exchange at Novotel Singapore On Stevens | H49: {=XLOOKUP(G49,'Restaurant DB All'!B:B,'Restaurant DB All'!A:A)} -> 6310 | I49: {=XLOOKUP(G49,'Restaurant DB'!B:B,'Restaurant DB'!N:N)} | J49: All You Can Eat | K49: 115 | L49: Special Price 50% Off | Lobstermania – Exclusive Saturday Dinner, 7 PM (Only 10 Seats Daily) | M49: can’t take spicy , broad beans and animals organs | N49: Cross post to Tiktok : https://www.tiktok.com/@theacesistersandmummyfay Fb : https://www.facebook.com/ArissaAnya/?ref=pro_upsell_xav_ig_profile_page_web# Lemon8 Youtube Short : https://www.youtube.com/@theacesistersandmummyfay | O49: 8859.515 | S49: 45906 | T49: 0.75 | U49: 3 | V49: Booked | W49: 576483703048897142 | X49: 7887907 | Y49: 45912 | Z49: {=if(iferror(INDEX(Posts[Username],MATCH(C49&G49,Posts[Username]&Posts[Restaurant Name],0)),"")=C49,"Posted","")} -> Posted | AA49: Guillaume
B50: HH-SGCOR | C50: comfortchomper | D50: 16100 | F50: Tiktok.com/@comfortchomper | G50: Fook Kin 福劲 | H50: {=XLOOKUP(G50,'Restaurant DB All'!B:B,'Restaurant DB All'!A:A)} -> 5376 | I50: {=XLOOKUP(G50,'Restaurant DB'!B:B,'Restaurant DB'!N:N)} -> Chinese, Singaporean | J50: Party Pack | K50: 103.7 | L50: Sharing Set for 3 People | M50: none | N50: Cross posted on https://www.instagram.com/comfortchomper | O50: 8859.515 | S50: 45907 | T50: 0.54166667 | U50: 3 | V50: Booked | W50: 577350712661377160 | X50: 7918767 | Y50: 45914 | Z50: {=if(iferror(INDEX(Posts[Username],MATCH(C50&G50,Posts[Username]&Posts[Restaurant Name],0)),"")=C50,"Posted","")} -> Posted | AA50: Guillaume
B51: HH-SGFOS | C51: foody_flyers | D51: 87213 | F51: Instagram.com/foody_flyers | G51: The Butcher's Wife | H51: {=XLOOKUP(G51,'Restaurant DB All'!B:B,'Restaurant DB All'!A:A)} -> 5874 | I51: {=XLOOKUP(G51,'Restaurant DB'!B:B,'Restaurant DB'!N:N)} -> Mediterranean, Latin American | J51: Party Pack | K51: 169 | L51: Sharing Set for 3 People | O51: 6328.225 | S51: 45907 | T51: 0.75 | U51: 3 | V51: Booked | W51: 576921410095022507 | X51: 7906796 | Z51: {=if(iferror(INDEX(Posts[Username],MATCH(C51&G51,Posts[Username]&Posts[Restaurant Name],0)),"")=C51,"Posted","")} -> Posted | AA51: Sirada
B52: HH-LOMYG | C52: myfoodiegallerysg | D52: 30467 | E52: {=XLOOKUP(G52,'Restaurant DB All'!$B$32:$B$5758,'Restaurant DB All'!$I$32:$I$5758)} -> Singapore | F52: https://www.instagram.com/myfoodiegallerysg/ | G52: Nozomi at Millenia Walk | H52: {=XLOOKUP(G52,'Restaurant DB All'!B:B,'Restaurant DB All'!A:A)} -> 5594 | I52: {=XLOOKUP(G52,'Restaurant DB'!B:B,'Restaurant DB'!N:N)} -> Japanese | J52: All You Can Eat | K52: 139 | L52: Nozomi l Premium Buffet & 1 Special Menu | P52: FALSE | Q52: Approved | R52: {=XLOOKUP(G52,'Restaurant DB'!B:B,'Restaurant DB'!I:I)} -> fred@hungryhub.com | S52: 45908 | T52: 0.77083333 | U52: 2 | V52: Booked | W52: 577516820354040137 | X52: 7918703 | Z52: {=if(iferror(INDEX(Posts[Username],MATCH(C52&G52,Posts[Username]&Posts[Restaurant Name],0)),"")=C52,"Posted","")} -> Posted
B53: HH-SGCOR | C53: comfortchomper | D53: 16100 | F53: Tiktok.com/@comfortchomper | G53: Heaven's lotus | H53: {=XLOOKUP(G53,'Restaurant DB All'!B:B,'Restaurant DB All'!A:A)} -> 5896 | I53: {=XLOOKUP(G53,'Restaurant DB'!B:B,'Restaurant DB'!N:N)} -> Thai | J53: Party Pack | K53: 79.2 | L53: Sharing Set for 3 People | M53: none | N53: Cross posted on https://www.instagram.com/comfortchomper | O53: 8859.515 | S53: 45910 | T53: 0.79166667 | U53: 3 | V53: Booked | W53: 577938871422550461 | X53: 7917735 | Y53: 45920 | Z53: {=if(iferror(INDEX(Posts[Username],MATCH(C53&G53,Posts[Username]&Posts[Restaurant Name],0)),"")=C53,"Posted","")} -> Posted | AA53: Guillaume
B54: HH-SGVIN | C54: vincas_kitchen | D54: 20961 | E54: {=XLOOKUP(G54,'Restaurant DB All'!$B$32:$B$5758,'Restaurant DB All'!$I$32:$I$5758)} -> Singapore | F54: Instagram.com/vincas_kitchen | G54: Oscar's At Conrad Singapore Marina Bay | H54: {=XLOOKUP(G54,'Restaurant DB All'!B:B,'Restaurant DB All'!A:A)} -> 5708 | I54: {=XLOOKUP(G54,'Restaurant DB'!B:B,'Restaurant DB'!N:N)} -> International | J54: All You Can Eat | K54: 72 | L54: Oscar's Dinner Buffet l The Sea, Smoke & Spice (Wed-Sun) | M54: None | N54: August Campaign | O54: 5062.58 | R54: {=XLOOKUP(G54,'Restaurant DB'!B:B,'Restaurant DB'!I:I)} -> fred@hungryhub.com | S54: 45912 | T54: 0.75 | U54: 4 | V54: Booked | W54: 577052058084180244 | X54: 7936870 | Y54: 45925 | Z54: {=if(iferror(INDEX(Posts[Username],MATCH(C54&G54,Posts[Username]&Posts[Restaurant Name],0)),"")=C54,"Posted","")} -> Posted | AA54: Guillaume
B55: HH-SGARK | C55: arctheshark | D55: 40934 | F55: Instagram.com/arctheshark | G55: Korat Thai Cafe | H55: {=XLOOKUP(G55,'Restaurant DB All'!B:B,'Restaurant DB All'!A:A)} -> 5650 | I55: {=XLOOKUP(G55,'Restaurant DB'!B:B,'Restaurant DB'!N:N)} -> Thai Isaan, Thai | J55: Party Pack | K55: 65.45 | L55: Sharing set for 3 people | M55: None | O55: 6702.92 | S55: 45912 | T55: 0.60416667 | U55: 3 | V55: Booked | W55: 577970260737786054 | X55: 7928788 | Y55: 45916 | Z55: Posted | AA55: Lars
B56: HH-INGOS | C56: goofytwocooks | D56: 28732 | E56: {=XLOOKUP(G56,'Restaurant DB All'!$B$32:$B$5758,'Restaurant DB All'!$I$32:$I$5758)} -> Singapore | F56: https://www.instagram.com/goofytwocooks/ | G56: Oscar's At Conrad Singapore Marina Bay | H56: {=XLOOKUP(G56,'Restaurant DB All'!B:B,'Restaurant DB All'!A:A)} -> 5708 | I56: {=XLOOKUP(G56,'Restaurant DB'!B:B,'Restaurant DB'!N:N)} -> International | J56: All You Can Eat | K56: 86.33 | L56: (1st-30th September 2025) Oscar's Dinner Buffet l The Sea, Smoke & Spice (Wed-Sun) | M56: None | O56: 3796.935 | Q56: Approved | R56: {=XLOOKUP(G56,'Restaurant DB'!B:B,'Restaurant DB'!I:I)} -> fred@hungryhub.com | S56: 45913 | T56: 0.75 | U56: 4 | V56: Booked | W56: 577514629300224246 | X56: 7936799 | Z56: {=if(iferror(INDEX(Posts[Username],MATCH(C56&G56,Posts[Username]&Posts[Restaurant Name],0)),"")=C56,"Posted","")} -> Posted | AA56: Sirada
B57: HH-SGJJ6 | C57: jjloves86 | D57: 14291 | F57: Instagram.com/jjloves86 | G57: Oscar's At Conrad Singapore Marina Bay | H57: {=XLOOKUP(G57,'Restaurant DB All'!B:B,'Restaurant DB All'!A:A)} -> 5708 | I57: {=XLOOKUP(G57,'Restaurant DB'!B:B,'Restaurant DB'!N:N)} -> International | J57: All You Can Eat | K57: 86.33 | L57: (1st-30th September 2025) Oscar's Dinner Buffet l The Sea, Smoke & Spice (Wed-Sun) | M57: none | O57: 3796.935 | S57: 45914 | T57: 0.5 | U57: 3 | V57: Booked | W57: 577242940540453083 | X57: 7938325 | Y57: 45916 | Z57: {=if(iferror(INDEX(Posts[Username],MATCH(C57&G57,Posts[Username]&Posts[Restaurant Name],0)),"")=C57,"Posted","")} -> Posted | AA57: Guillaume
B58: HH-SGFOS | C58: foody_flyers | D58: 87213 | F58: Instagram.com/foody_flyers | G58: Town Restaurant At The Fullerton Hotel Singapore | H58: {=XLOOKUP(G58,'Restaurant DB All'!B:B,'Restaurant DB All'!A:A)} -> 6141 | I58: {=XLOOKUP(G58,'Restaurant DB'!B:B,'Restaurant DB'!N:N)} -> International | J58: Party Pack | K58: 94 | L58: Sunday Brunch (Unlimited Lobster) | O58: 6328.225 | S58: 45914 | T58: 0.5 | U58: 3 | V58: Booked | W58: 576952617058959857 | X58: 7934597 | Z58: Posted | AA58: Sirada
B59: HH-SGCOR | C59: comfortchomper | D59: 16100 | F59: Tiktok.com/@comfortchomper | G59: 中国好味道 China Taste | H59: {=XLOOKUP(G59,'Restaurant DB All'!B:B,'Restaurant DB All'!A:A)} -> 5899 | I59: {=XLOOKUP(G59,'Restaurant DB'!B:B,'Restaurant DB'!N:N)} -> Chinese | J59: Party Pack | K59: 55.2 | L59: Sharing Set for 3 People | M59: none | N59: Cross posted on https://www.instagram.com/comfortchomper | O59: 8859.515 | S59: 45914 | T59: 0.79166667 | U59: 3 | V59: Booked | W59: 577350715177959886 | X59: 7938164 | Z59: {=if(iferror(INDEX(Posts[Username],MATCH(C59&G59,Posts[Username]&Posts[Restaurant Name],0)),"")=C59,"Posted","")} -> Posted | AA59: Guillaume
B60: HH-LOMYG | C60: myfoodiegallerysg | D60: 30467 | E60: {=XLOOKUP(G60,'Restaurant DB All'!$B$32:$B$5758,'Restaurant DB All'!$I$32:$I$5758)} -> Singapore | F60: https://www.instagram.com/myfoodiegallerysg/ | G60: Oscar's At Conrad Singapore Marina Bay | H60: {=XLOOKUP(G60,'Restaurant DB All'!B:B,'Restaurant DB All'!A:A)} -> 5708 | I60: {=XLOOKUP(G60,'Restaurant DB'!B:B,'Restaurant DB'!N:N)} -> International | J60: All You Can Eat | K60: 86.33 | L60: (1st-30th September 2025) Oscar's Dinner Buffet l The Sea, Smoke & Spice (Wed-Sun) | P60: FALSE | Q60: Approved | R60: {=XLOOKUP(G60,'Restaurant DB'!B:B,'Restaurant DB'!I:I)} -> fred@hungryhub.com | S60: 45914 | T60: 0.75 | U60: 2 | V60: Booked | W60: 577516823223468156 | X60: 7938054 | Z60: {=if(iferror(INDEX(Posts[Username],MATCH(C60&G60,Posts[Username]&Posts[Restaurant Name],0)),"")=C60,"Posted","")} -> Posted
B61: HH-SGSHR | C61: sheen_cher | D61: 23153 | F61: Instagram.com/sheen_cher | G61: Fook Kin 福劲 | H61: {=XLOOKUP(G61,'Restaurant DB All'!B:B,'Restaurant DB All'!A:A)} -> 5376 | I61: {=XLOOKUP(G61,'Restaurant DB'!B:B,'Restaurant DB'!N:N)} -> Chinese, Singaporean | J61: Party Pack | K61: 134.4 | L61: Sharing set for 4 people | M61: None | O61: 0 | S61: 45916 | T61: 0.79166667 | U61: 4 | V61: Booked | W61: 578073728362480217 | X61: 7931373 | Y61: 45923 | Z61: Posted | AA61: Lars
B62: HH-INPAR | C62: parttimefoodblogger | D62: 16406 | E62: Singapore | F62: Instagram.com/parttimefoodblogger | G62: Horses Mouth | H62: {=XLOOKUP(G62,'Restaurant DB All'!B:B,'Restaurant DB All'!A:A)} -> #N/A | I62: {=XLOOKUP(G62,'Restaurant DB'!B:B,'Restaurant DB'!N:N)} -> #N/A | J62: All You Can Eat | K62: 85 | L62: The Horse’s Feast: Limited Edition+ 1 Premium Menu (All You Can Eat) | M62: None | O62: 10125.16 | R62: {=XLOOKUP(G62,'Restaurant DB'!B:B,'Restaurant DB'!I:I)} -> #N/A | S62: 45916 | T62: 0.79166667 | U62: 4 | V62: Booked | W62: 578366144096763924 | X62: 7942715 | Z62: Posted | AA62: Sirada | AB62: HH-INPARQRU
B63: HH-SGARK | C63: arctheshark | D63: 40934 | F63: Instagram.com/arctheshark | G63: Obba.Jjanag | H63: {=XLOOKUP(G63,'Restaurant DB All'!B:B,'Restaurant DB All'!A:A)} -> #N/A | I63: {=XLOOKUP(G63,'Restaurant DB'!B:B,'Restaurant DB'!N:N)} -> #N/A | J63: Party Pack | K63: 143.1 | L63: BBQ Set for 3 people | M63: None | O63: 6702.92 | S63: 45917 | T63: 0.60416667 | U63: 3 | V63: Booked | W63: 577970263203774844 | X63: 7931428 | Y63: 45931 | Z63: Posted | AA63: Lars
B64: HH-SGJJ6 | C64: jjloves86 | D64: 14291 | F64: Instagram.com/jjloves86 | G64: The Horse's Mouth | H64: {=XLOOKUP(G64,'Restaurant DB All'!B:B,'Restaurant DB All'!A:A)} -> 5571 | I64: {=XLOOKUP(G64,'Restaurant DB'!B:B,'Restaurant DB'!N:N)} -> Latin American | J64: Party Pack | K64: 85 | L64: International Buffet + 1 Premium Menu | M64: none | O64: 3796.935 | S64: 45919 | T64: 0.79166667 | U64: 3 | V64: Booked | W64: 577345221730239019 | X64: 7938325 | Y64: 45926 | Z64: Posted | AA64: Guillaume
B65: HH-SGNWL | C65: nwso.ul | D65: 14700 | F65: Tiktok.com/@nwso.ul | G65: ShoSha | H65: {=XLOOKUP(G65,'Restaurant DB All'!B:B,'Restaurant DB All'!A:A)} -> 6104 | I65: {=XLOOKUP(G65,'Restaurant DB'!B:B,'Restaurant DB'!N:N)} -> Fusion, Indian | J65: Party Pack | K65: 99 | L65: Sharing Set for 3 people | N65: Certified Halal | O65: 5063 | S65: 45919 | T65: 0.79166667 | U65: 3 | V65: Booked | W65: 577947313549869108 | X65: 7941266 | Z65: Posted | AA65: Guillaume | AB65: HH-SGNWLLOE
B66: HH-SGJJ6 | C66: jjloves86 | D66: 14291 | F66: Instagram.com/jjloves86 | G66: Nozomi at Millenia Walk | H66: {=XLOOKUP(G66,'Restaurant DB All'!B:B,'Restaurant DB All'!A:A)} -> 5594 | I66: {=XLOOKUP(G66,'Restaurant DB'!B:B,'Restaurant DB'!N:N)} -> Japanese | J66: All You Can Eat | K66: 69 | L66: Nozomi l Premium Buffet | M66: none | O66: 3796.935 | S66: 45920 | T66: 0.5 | U66: 3 | V66: Booked | W66: 577242944466321634 | X66: 7968910 | Y66: 45923 | Z66: Posted | AA66: Guillaume | AB66: HH-SGJJ6RFN
B67: HH-SGEAT | C67: eatwithkeat | D67: 10718 | F67: Instagram.com/eatwithkeat | G67: The Butcher's Wife | H67: {=XLOOKUP(G67,'Restaurant DB All'!B:B,'Restaurant DB All'!A:A)} -> 5874 | I67: {=XLOOKUP(G67,'Restaurant DB'!B:B,'Restaurant DB'!N:N)} -> Mediterranean, Latin American | J67: Party Pack | K67: 169 | L67: Sharing Set for 3 People | M67: allergic to uni and abalone | N67: Tiktok : tiktok.com/eatwithkheat | O67: 0 | S67: 45921 | T67: 0.79166667 | U67: 3 | V67: Booked | W67: 579251341588168875 | X67: 7961505 | Y67: 45929 | Z67: {=if(iferror(INDEX(Posts[Username],MATCH(C67&G67,Posts[Username]&Posts[Restaurant Name],0)),"")=C67,"Posted","")} -> Posted | AA67: Guillaume | AB67: HH-SGEATOXB
B68: HH-SGEAT | C68: eatwithkeat | D68: 10718 | F68: Instagram.com/eatwithkeat | G68: 中国好味道 China Taste | H68: {=XLOOKUP(G68,'Restaurant DB All'!B:B,'Restaurant DB All'!A:A)} -> 5899 | I68: {=XLOOKUP(G68,'Restaurant DB'!B:B,'Restaurant DB'!N:N)} -> Chinese | J68: Party Pack | K68: 68 | L68: Sharing Set for 4 People | M68: allergic to uni and abalone | N68: Tiktok : tiktok.com/eatwithkheat | O68: 0 | S68: 45922 | T68: 0.79166667 | U68: 4 | V68: Booked | W68: 579263674066141408 | X68: 7972694 | Y68: 45930 | Z68: Posted | AA68: Guillaume | AB68: HH-SGEATWEA
B69: HH-SGNWL | C69: nwso.ul | D69: 14700 | F69: Tiktok.com/@nwso.ul | G69: Kintamani at Furama Riverfront Hotel | H69: {=XLOOKUP(G69,'Restaurant DB All'!B:B,'Restaurant DB All'!A:A)} -> 5644 | I69: {=XLOOKUP(G69,'Restaurant DB'!B:B,'Restaurant DB'!N:N)} -> Indonesian | J69: All You Can Eat | K69: 45 | L69: Weekday Dinner Buffet (Mon-Thu) | N69: Certified Halal | O69: 5063 | S69: 45922 | T69: 0.79166667 | U69: 3 | V69: Booked | W69: 577947310177124516 | X69: 7977628 | Z69: Posted | AA69: Guillaume | AB69: HH-SGNWLNIU
B70: HH-SGLUELIP | C70: lucy.rezel | D70: 36490 | F70: Instagram.com/lucy.rezel | G70: Fook Kin 福劲 | H70: {=XLOOKUP(G70,'Restaurant DB All'!B:B,'Restaurant DB All'!A:A)} -> 5376 | I70: {=XLOOKUP(G70,'Restaurant DB'!B:B,'Restaurant DB'!N:N)} -> Chinese, Singaporean | J70: Party Pack | K70: 64.59 | L70: Sharing Set For 2 People | M70: None | O70: 5063 | S70: 45925 | T70: 0.54166667 | U70: 2 | V70: Booked | W70: 579956093946691639 | X70: 7977829 | Y70: 45930 | Z70: Posted | AA70: Lars | AB70: HH-SGLUELIPVWG72
B71: HH-SGNWL | C71: nwso.ul | D71: 14700 | F71: Tiktok.com/@nwso.ul | G71: Taksim Restaurant | H71: {=XLOOKUP(G71,'Restaurant DB All'!B:B,'Restaurant DB All'!A:A)} -> 5736 | I71: {=XLOOKUP(G71,'Restaurant DB'!B:B,'Restaurant DB'!N:N)} -> Egyptian, Mediterranean, Lebanese, Middle Eastern | J71: Party Pack | K71: 149 | L71: Sharing Set for 3 people | N71: Certified Halal | O71: 5063 | S71: 45925 | T71: 0.79166667 | U71: 3 | V71: Booked | W71: 577947316318110006 | X71: 7941579 | Z71: Posted | AA71: Guillaume | AB71: HH-SGNWLMWE
B72: HH-SGGIS | C72: girldevours | D72: 2338 | E72: {=XLOOKUP(G72,'Restaurant DB All'!$B$32:$B$5758,'Restaurant DB All'!$I$32:$I$5758)} -> Singapore | F72: Tiktok.com/@girldevours | G72: The Horse's Mouth | H72: {=XLOOKUP(G72,'Restaurant DB All'!B:B,'Restaurant DB All'!A:A)} -> 5571 | I72: {=XLOOKUP(G72,'Restaurant DB'!B:B,'Restaurant DB'!N:N)} -> Latin American | J72: All You Can Eat | K72: 59 | L72: The Horse’s Feast: Limited Edition (All You Can Eat) | M72: None | O72: 1518.774 | S72: 45927 | T72: 0.75 | U72: 4 | V72: Booked | W72: 580538827828625704 | X72: 7993212 | Z72: {=if(iferror(INDEX(Posts[Username],MATCH(C72&G72,Posts[Username]&Posts[Restaurant Name],0)),"")=C72,"Posted","")} -> Posted | AA72: Guillaume | AB72: HH-SGGISCFU
B73: HH-LOMYG | C73: myfoodiegallerysg | D73: 30604 | F73: Instagram.com/myfoodiegallerysg | G73: Town Restaurant At The Fullerton Hotel Singapore (mail) | H73: {=XLOOKUP(G73,'Restaurant DB All'!B:B,'Restaurant DB All'!A:A)} -> #N/A | I73: {=XLOOKUP(G73,'Restaurant DB'!B:B,'Restaurant DB'!N:N)} -> #N/A | J73: All You Can Eat | K73: 97.12 | L73: Spice Odyssey Dinner Buffet (Fri-Sat & Public Holidays) | O73: 7593.87 | S73: 45927 | T73: 0.75 | U73: 2 | V73: Booked | W73: 1997ad98805dc3b2 | X73: 7992710 | Z73: Posted | AA73: Sirada | AB73: HH-LOMYGAYE37
B74: HH-SGEXN | C74: exploretomakan | D74: 14669 | F74: Instagram.com/exploretomakan | G74: Kintamani at Furama Riverfront Hotel | H74: {=XLOOKUP(G74,'Restaurant DB All'!B:B,'Restaurant DB All'!A:A)} -> 5644 | I74: {=XLOOKUP(G74,'Restaurant DB'!B:B,'Restaurant DB'!N:N)} -> Indonesian | J74: All You Can Eat | K74: 36 | L74: Weekday Lunch Buffet (Mon-Thu) | M74: Halal only, no red meat | N74: Arrives in Singapore 25 Sept | O74: 7593.87 | S74: 45929 | T74: 0.5 | U74: 3 | V74: Booked | W74: 577234971078165096 | X74: 7977637 | Z74: {=if(iferror(INDEX(Posts[Username],MATCH(C74&G74,Posts[Username]&Posts[Restaurant Name],0)),"")=C74,"Posted","")} -> Posted | AA74: Guillaume | AB74: HH-SGEXNPWE
B75: HH-LOTHI | C75: thara_koiii | D75: 95611 | E75: {=XLOOKUP(G75,'Restaurant DB All'!$B$32:$B$5758,'Restaurant DB All'!$I$32:$I$5758)} -> Singapore | F75: Instagram.com/thara_koiii | G75: FIRE | H75: {=XLOOKUP(G75,'Restaurant DB All'!B:B,'Restaurant DB All'!A:A)} -> 6027 | I75: {=XLOOKUP(G75,'Restaurant DB'!B:B,'Restaurant DB'!N:N)} -> Argentinian | J75: Party Pack | K75: 162 | L75: FIRE l 5 Course Dinner | O75: 1685.8391 | R75: {=XLOOKUP(G75,'Restaurant DB'!B:B,'Restaurant DB'!I:I)} -> fred@hungryhub.com | S75: 45929 | T75: 0.75 | U75: 2 | V75: Refused | W75: 577234973460267341 | Z75: {=if(iferror(INDEX(Posts[Username],MATCH(C75&G75,Posts[Username]&Posts[Restaurant Name],0)),"")=C75,"Posted","")} | AB75: HH-LOTHIJWC
B76: HH-SGLUELIP | C76: lucy.rezel | D76: 36490 | F76: Instagram.com/lucy.rezel | G76: Edge at Pan Pacific Hotel Singapore (mail) | H76: {=XLOOKUP(G76,'Restaurant DB All'!B:B,'Restaurant DB All'!A:A)} -> #N/A | I76: {=XLOOKUP(G76,'Restaurant DB'!B:B,'Restaurant DB'!N:N)} -> #N/A | J76: All You Can Eat | K76: 73 | L76: Lunch Buffet (Mon-Fri) | M76: None | N76: She plans to arrive early so the buffet spread still looks full and nice. | O76: 5063 | S76: 45930 | T76: 0.5 | U76: 2 | V76: Booked | W76: 1996f7c5ef2b3c71 | X76: 7978617 | Y76: 45936 | Z76: Posted | AA76: Lars | AB76: HH-SGLUELIPNZE69
B77: HH-SGEAT | C77: eatwithkeat | D77: 10718 | F77: Instagram.com/eatwithkeat | G77: Sakon Thai At E!Hub Downtown East | H77: {=XLOOKUP(G77,'Restaurant DB All'!B:B,'Restaurant DB All'!A:A)} -> 5795 | I77: {=XLOOKUP(G77,'Restaurant DB'!B:B,'Restaurant DB'!N:N)} -> Thai | J77: Party Pack | K77: 66.3 | L77: Sharing Set for 3 people | M77: allergic to uni and abalone | N77: Tiktok : tiktok.com/eatwithkheat | O77: 0 | S77: 45930 | T77: 0.79166667 | U77: 3 | V77: Booked | W77: 579983656076968027 | X77: 7981933 | Y77: 45935 | Z77: Posted | AA77: Guillaume | AB77: HH-SGEATVRP
B78: HH-SGLUELIP | C78: lucy.rezel | D78: 36490 | F78: Instagram.com/lucy.rezel | G78: Nozomi at Millenia Walk | H78: {=XLOOKUP(G78,'Restaurant DB All'!B:B,'Restaurant DB All'!A:A)} -> 5594 | I78: {=XLOOKUP(G78,'Restaurant DB'!B:B,'Restaurant DB'!N:N)} -> Japanese | J78: All You Can Eat | K78: 139 | L78: Nozomi l Premium Buffet & 1 Special Menu | M78: None | O78: 5063 | S78: 45931 | T78: 0.5 | U78: 2 | V78: Booked | W78: 579956096681378228 | X78: 7988886 | Y78: 45949 | Z78: Posted | AA78: Lars | AB78: HH-SGLUELIPKLL95
B79: HH-LOMYG | C79: myfoodiegallerysg | D79: 30604 | F79: Instagram.com/myfoodiegallerysg | G79: The Butcher's Wife | H79: {=XLOOKUP(G79,'Restaurant DB All'!B:B,'Restaurant DB All'!A:A)} -> 5874 | I79: {=XLOOKUP(G79,'Restaurant DB'!B:B,'Restaurant DB'!N:N)} -> Mediterranean, Latin American | J79: Party Pack | K79: 169 | L79: Sharing Set for 3 People | O79: 7593.87 | S79: 45931 | T79: 0.75 | U79: 3 | V79: Booked | W79: 580275936587940335 | X79: 8009511 | Z79: {=if(iferror(INDEX(Posts[Username],MATCH(C79&G79,Posts[Username]&Posts[Restaurant Name],0)),"")=C79,"Posted","")} -> Posted | AA79: Sirada | AB79: HH-LOMYGAKX12
B80: HH-SGFOISPL | C80: foodkakis | D80: 11606 | F80: Instagram.com/foodkakis | G80: Nozomi at Millenia Walk | H80: {=XLOOKUP(G80,'Restaurant DB All'!B:B,'Restaurant DB All'!A:A)} -> 5594 | I80: {=XLOOKUP(G80,'Restaurant DB'!B:B,'Restaurant DB'!N:N)} -> Japanese | J80: All You Can Eat | K80: 69 | L80: Nozomi l Premium Buffet | O80: 3037.548 | S80: 45933 | T80: 0.79166667 | U80: 4 | V80: Booked | W80: 580968047783969442 | X80: 8020322 | Z80: {=if(iferror(INDEX(Posts[Username],MATCH(C80&G80,Posts[Username]&Posts[Restaurant Name],0)),"")=C80,"Posted","")} -> Posted | AA80: Sirada | AB80: HH-SGFOISPLEAU91
B81: HH-SGVIN | C81: vincas_kitchen | D81: 20961 | F81: Instagram.com/vincas_kitchen | G81: Food Exchange at Novotel Singapore On Stevens | H81: {=XLOOKUP(G81,'Restaurant DB All'!B:B,'Restaurant DB All'!A:A)} -> 6310 | I81: {=XLOOKUP(G81,'Restaurant DB'!B:B,'Restaurant DB'!N:N)} | J81: All You Can Eat | K81: 82.5 | L81: Special Price 50% Off | Lobstermania – Exclusive Saturday Dinner, 7 PM (Only 10 Seats Daily) | M81: None | N81: October Campaign | O81: 5062.58 | S81: 45934 | T81: 0.79166667 | U81: 3 | V81: Booked | W81: 581256410025951569 | X81: 8017115 | Y81: 45944 | Z81: Posted | AA81: Guillaume | AB81: HH-SGVINUJG48
B82: HH-TFRTRRNJ | C82: fred.and.chloe | D82: 20181 | F82: Instagram.com/fred.and.chloe | G82: Obba.Jjanag | H82: {=XLOOKUP(G82,'Restaurant DB All'!B:B,'Restaurant DB All'!A:A)} -> #N/A | I82: {=XLOOKUP(G82,'Restaurant DB'!B:B,'Restaurant DB'!N:N)} -> #N/A | J82: Party Pack | K82: 98.1 | L82: BBQ Set for 2 People | M82: None | O82: 5062.58 | S82: 45934 | T82: 0.54166667 | U82: 2 | V82: Booked | W82: 579534187632525942 | X82: 7990567 | Y82: 45939 | Z82: Posted | AA82: Lars | AB82: HH-TFRTRRNJDYL12
B83: HH-TSAAGLUQ | C83: sakshi_reliving | D83: 11627 | F83: Instagram.com/sakshi_reliving | G83: Oscar's At Conrad Singapore Marina Bay (mail) | H83: {=XLOOKUP(G83,'Restaurant DB All'!B:B,'Restaurant DB All'!A:A)} -> #N/A | I83: {=XLOOKUP(G83,'Restaurant DB'!B:B,'Restaurant DB'!N:N)} -> #N/A | J83: All You Can Eat | K83: 96 | L83: Oscar's Dinner Buffet I The Sea, Smoke & Spice (Wed-Sun) | M83: No pork and beef | O83: 0 | S83: 45935 | T83: 0.75 | U83: 2 | V83: Refused | W83: 1999490b28012e0f | Z83: {=if(iferror(INDEX(Posts[Username],MATCH(C83&G83,Posts[Username]&Posts[Restaurant Name],0)),"")=C83,"Posted","")} | AA83: Lars | AB83: HH-TSAAGLUQJSS98
B84: HH-SGARK | C84: arctheshark | D84: 40934 | F84: Instagram.com/arctheshark | G84: Edge at Pan Pacific Hotel Singapore | H84: {=XLOOKUP(G84,'Restaurant DB All'!B:B,'Restaurant DB All'!A:A)} -> 5465 | I84: {=XLOOKUP(G84,'Restaurant DB'!B:B,'Restaurant DB'!N:N)} -> International | J84: All You Can Eat | K84: 73 | L84: Lunch Buffet (Mon-Fri) | M84: None | O84: 6702.92 | S84: 45937 | T84: 0.5 | U84: 3 | V84: Booked | W84: 578214619211104772 | X84: 7938177 | Y84: 45948 | Z84: Posted | AA84: Lars
B85: HH-LOMEX | C85: megsandalex | D85: 20381 | F85: Instagram.com/megsandalex | G85: HIGHHOUSE | H85: {=XLOOKUP(G85,'Restaurant DB All'!B:B,'Restaurant DB All'!A:A)} -> #N/A | I85: {=XLOOKUP(G85,'Restaurant DB'!B:B,'Restaurant DB'!N:N)} -> #N/A | J85: Party Pack | K85: 76.5 | L85: Individual Set (Dinner Only) | O85: 4349 | S85: 45938 | T85: 0.8125 | U85: 3 | V85: Refused | W85: 580137182602199258 | Z85: {=if(iferror(INDEX(Posts[Username],MATCH(C85&G85,Posts[Username]&Posts[Restaurant Name],0)),"")=C85,"Posted","")} | AA85: Sirada | AB85: HH-LOMEXFVG73
B86: HH-SGXCTYWH | C86: xchubbykitty | D86: 24483 | F86: Instagram.com/xchubbykitty | G86: Obba.Jjanag | H86: {=XLOOKUP(G86,'Restaurant DB All'!B:B,'Restaurant DB All'!A:A)} -> #N/A | I86: {=XLOOKUP(G86,'Restaurant DB'!B:B,'Restaurant DB'!N:N)} -> #N/A | J86: Party Pack | K86: 143.1 | L86: BBQ Set for 3 People | M86: No beef and mutton | O86: 0 | S86: 45938 | T86: 0.8125 | U86: 3 | V86: Refused | W86: 581984919023517923 | Z86: {=if(iferror(INDEX(Posts[Username],MATCH(C86&G86,Posts[Username]&Posts[Restaurant Name],0)),"")=C86,"Posted","")} | AA86: Lars | AB86: HH-SGXCTYWHPBP09
B87: HH-INROA | C87: roadtrippers.asia | D87: 51300 | E87: Singapore | F87: Tiktok.com/@roadtrippers.asia | G87: Absurdities Singapore | H87: {=XLOOKUP(G87,'Restaurant DB All'!B:B,'Restaurant DB All'!A:A)} -> 6279 | I87: {=XLOOKUP(G87,'Restaurant DB'!B:B,'Restaurant DB'!N:N)} -> #N/A | J87: Party Pack | K87: 367 | L87: 6 Course Omakase | M87: None | N87: August Campaign Tiktok https://www.tiktok.com/@roadtrippers.asia IG https://www.instagram.com/eatwithandrewchan Facebook https://www.facebook.com/@roadtrippers.asia Lemon8 https://www.lemon8-app.com/@roadtrippers.asia Xiao Hong Shu https://www.xiaohongshu.com/user/profile/66b9854e000000001d020eb8 Youtube https://youtube.com/@roadtrippers-asia | O87: 5062 | S87: 45940 | T87: 0.8125 | U87: 2 | V87: Booked | W87: 580398918346211794 | X87: 8050550 | Y87: 45950 | Z87: Posted | AA87: Guillaume | AB87: HH-INROAXLE37
B88: HH-INROA | C88: roadtrippers.asia | D88: 51300 | E88: Singapore | F88: Tiktok.com/@roadtrippers.asia | G88: Shrimp Prawn Seafood | H88: {=XLOOKUP(G88,'Restaurant DB All'!B:B,'Restaurant DB All'!A:A)} -> 5211 | I88: {=XLOOKUP(G88,'Restaurant DB'!B:B,'Restaurant DB'!N:N)} -> Thai | J88: Party Pack | K88: 139 | L88: FREE LOBSTER worth $88 - Premium Set for 3 People (End October) | M88: None | N88: August Campaign Tiktok https://www.tiktok.com/@roadtrippers.asia IG https://www.instagram.com/eatwithandrewchan Facebook https://www.facebook.com/@roadtrippers.asia Lemon8 https://www.lemon8-app.com/@roadtrippers.asia Xiao Hong Shu https://www.xiaohongshu.com/user/profile/66b9854e000000001d020eb8 Youtube https://youtube.com/@roadtrippers-asia | O88: 5062 | S88: 45940 | T88: 0.5 | U88: 3 | V88: Booked | W88: 580398915930030389 | X88: 8048331 | Y88: 45948 | Z88: Posted | AA88: Guillaume | AB88: HH-INROAMBC10
B89: HH-INROA | C89: roadtrippers.asia | D89: 51300 | E89: Singapore | F89: Tiktok.com/@roadtrippers.asia | G89: The Horse's Mouth | H89: {=XLOOKUP(G89,'Restaurant DB All'!B:B,'Restaurant DB All'!A:A)} -> 5571 | I89: {=XLOOKUP(G89,'Restaurant DB'!B:B,'Restaurant DB'!N:N)} -> Latin American | J89: All You Can Eat | K89: 85 | L89: The Horse’s Feast: Limited Edition+ 1 Premium Menu (All You Can Eat) | M89: None | N89: August Campaign Tiktok https://www.tiktok.com/@roadtrippers.asia IG https://www.instagram.com/eatwithandrewchan Facebook https://www.facebook.com/@roadtrippers.asia Lemon8 https://www.lemon8-app.com/@roadtrippers.asia Xiao Hong Shu https://www.xiaohongshu.com/user/profile/66b9854e000000001d020eb8 Youtube https://youtube.com/@roadtrippers-asia | O89: 5062 | S89: 45941 | T89: 0.79166667 | U89: 3 | V89: Booked | W89: 580398923126931907 | X89: 8043251 | Y89: 45955 | Z89: Posted | AA89: Guillaume | AB89: HH-INROAPII64
B90: HH-INROA | C90: roadtrippers.asia | D90: 51300 | E90: Singapore | F90: Tiktok.com/@roadtrippers.asia | G90: Edge at Pan Pacific Hotel Singapore (mail) | H90: {=XLOOKUP(G90,'Restaurant DB All'!B:B,'Restaurant DB All'!A:A)} -> #N/A | I90: {=XLOOKUP(G90,'Restaurant DB'!B:B,'Restaurant DB'!N:N)} -> #N/A | J90: All You Can Eat | K90: 81 | L90: Saturday Lunch | M90: None | N90: August Campaign Tiktok https://www.tiktok.com/@roadtrippers.asia IG https://www.instagram.com/eatwithandrewchan Facebook https://www.facebook.com/@roadtrippers.asia Lemon8 https://www.lemon8-app.com/@roadtrippers.asia Xiao Hong Shu https://www.xiaohongshu.com/user/profile/66b9854e000000001d020eb8 Youtube https://youtube.com/@roadtrippers-asia | O90: 5062 | S90: 45941 | T90: 0.5 | U90: 3 | V90: Booked | W90: 1997f3809bb175ee | X90: 7990087 | Y90: 45952 | Z90: Posted | AA90: Guillaume | AB90: HH-INROARYL46
B91: HH-TSAAGLUQ | C91: sakshi_reliving | D91: 11627 | F91: Instagram.com/sakshi_reliving | G91: Firangi Super Star | H91: {=XLOOKUP(G91,'Restaurant DB All'!B:B,'Restaurant DB All'!A:A)} -> #N/A | I91: {=XLOOKUP(G91,'Restaurant DB'!B:B,'Restaurant DB'!N:N)} -> #N/A | J91: Party Pack | K91: 203 | L91: Dinner Set for 2 People | M91: No pork and beef | O91: 0 | S91: 45941 | T91: 0.75 | U91: 2 | V91: Refused | W91: 580999760329572423 | Z91: {=if(iferror(INDEX(Posts[Username],MATCH(C91&G91,Posts[Username]&Posts[Restaurant Name],0)),"")=C91,"Posted","")} | AA91: Lars | AB91: HH-TSAAGLUQCZQ77
B92: HH-SGLUELIP | C92: lucy.rezel | D92: 36490 | F92: Instagram.com/lucy.rezel | G92: Beach Road Kitchen at JW Marriott Singapore South Beach (mail) | H92: {=XLOOKUP(G92,'Restaurant DB All'!B:B,'Restaurant DB All'!A:A)} -> #N/A | I92: {=XLOOKUP(G92,'Restaurant DB'!B:B,'Restaurant DB'!N:N)} -> #N/A | J92: All You Can Eat | K92: 108 | L92: Weekend Dinner (Fri-Sat) | M92: None | O92: 5063 | S92: 45941 | T92: 0.75 | U92: 1 + 1 Child | V92: Refused | W92: 1996f7c5ef2b3c71 | Z92: {=if(iferror(INDEX(Posts[Username],MATCH(C92&G92,Posts[Username]&Posts[Restaurant Name],0)),"")=C92,"Posted","")} | AA92: Lars | AB92: HH-SGLUELIPAOB32
B93: HH-SGBAH3AJ | C93: bakencookwith3 | D93: 28698 | F93: Instagram.com/bakencookwith3 | G93: Edge at Pan Pacific Hotel Singapore (mail) | H93: {=XLOOKUP(G93,'Restaurant DB All'!B:B,'Restaurant DB All'!A:A)} -> #N/A | I93: {=XLOOKUP(G93,'Restaurant DB'!B:B,'Restaurant DB'!N:N)} -> #N/A | J93: Party Pack | K93: 81 | L93: Saturday Lunch | O93: 4218.901 | S93: 45941 | T93: 0.5 | U93: 3 | V93: Booked | W93: 199be53ee689e05f | X93: 8037909 | Z93: Posted | AA93: Sirada | AB93: HH-SGBAH3AJCSX25
B94: HH-TXXFOERQ | C94: munchingmomentswithm | D94: 18776 | F94: Instagram.com/munchingmomentswithm | G94: Town Restaurant At The Fullerton Hotel Singapore (mail) | H94: {=XLOOKUP(G94,'Restaurant DB All'!B:B,'Restaurant DB All'!A:A)} -> #N/A | I94: {=XLOOKUP(G94,'Restaurant DB'!B:B,'Restaurant DB'!N:N)} -> #N/A | J94: All You Can Eat | K94: 97.12 | L94: Spice Odyssey Dinner Buffet (Fri-Sat & Public Holidays) | O94: 5062.58 | S94: 45941 | T94: 0.77083333 | U94: 3 | V94: Booked | W94: 199a82edd53f36b6 | X94: 8019975 | Z94: Posted | AA94: Sirada | AB94: HH-TXXFOERQXYY85
B95: HH-INROA | C95: roadtrippers.asia | D95: 51300 | E95: Singapore | F95: Tiktok.com/@roadtrippers.asia | G95: Mama Diam 妈妈店 | H95: {=XLOOKUP(G95,'Restaurant DB All'!B:B,'Restaurant DB All'!A:A)} -> 5735 | I95: {=XLOOKUP(G95,'Restaurant DB'!B:B,'Restaurant DB'!N:N)} -> Singaporean, Chinese | J95: Party Pack | K95: 145 | L95: Sharing Set for 3 People | M95: None | N95: August Campaign Tiktok https://www.tiktok.com/@roadtrippers.asia IG https://www.instagram.com/eatwithandrewchan Facebook https://www.facebook.com/@roadtrippers.asia Lemon8 https://www.lemon8-app.com/@roadtrippers.asia Xiao Hong Shu https://www.xiaohongshu.com/user/profile/66b9854e000000001d020eb8 Youtube https://youtube.com/@roadtrippers-asia | O95: 5062 | S95: 45942 | T95: 0.79166667 | U95: 3 | V95: Booked | W95: 580398920862793883 | X95: 8051688 | Y95: 45961 | Z95: Posted | AA95: Guillaume | AB95: HH-INROAXII71
B96: HH-INROA | C96: roadtrippers.asia | D96: 51300 | E96: Singapore | F96: Tiktok.com/@roadtrippers.asia | G96: Nozomi at The Star Vista | H96: {=XLOOKUP(G96,'Restaurant DB All'!B:B,'Restaurant DB All'!A:A)} -> 5595 | I96: {=XLOOKUP(G96,'Restaurant DB'!B:B,'Restaurant DB'!N:N)} -> Japanese | J96: All You Can Eat | K96: 69 | L96: Nozomi l Premium Buffet | M96: None | N96: August Campaign Tiktok https://www.tiktok.com/@roadtrippers.asia IG https://www.instagram.com/eatwithandrewchan Facebook https://www.facebook.com/@roadtrippers.asia Lemon8 https://www.lemon8-app.com/@roadtrippers.asia Xiao Hong Shu https://www.xiaohongshu.com/user/profile/66b9854e000000001d020eb8 Youtube https://youtube.com/@roadtrippers-asia | O96: 5062 | P96: FALSE | S96: 45942 | T96: 0.5 | U96: 3 | V96: Booked | W96: 580398925794771502 | X96: 8051713 | Y96: 45958 | Z96: Posted | AA96: Guillaume | AB96: HH-INROAQLP90
B97: HH-TLICHGFX | C97: heyyolina616 | D97: 10755 | F97: Instagram.com/heyyolina616 | G97: Nozomi at The Star Vista | H97: {=XLOOKUP(G97,'Restaurant DB All'!B:B,'Restaurant DB All'!A:A)} -> 5595 | I97: {=XLOOKUP(G97,'Restaurant DB'!B:B,'Restaurant DB'!N:N)} -> Japanese | J97: All You Can Eat | K97: 69 | L97: Nozomi I Premium Buffet | M97: None | O97: 1266 | S97: 45942 | T97: 0.54166667 | U97: 3 | V97: Booked | W97: 582012612184375509 | X97: 8043291 | Y97: 45947 | Z97: {=if(iferror(INDEX(Posts[Username],MATCH(C97&G97,Posts[Username]&Posts[Restaurant Name],0)),"")=C97,"Posted","")} -> Posted | AA97: Lars | AB97: HH-TLICHGFXXYO67
B98: HH-SGLUELIP | C98: lucy.rezel | D98: 36490 | F98: Instagram.com/lucy.rezel | G98: Food Exchange at Novotel Singapore On Stevens | H98: {=XLOOKUP(G98,'Restaurant DB All'!B:B,'Restaurant DB All'!A:A)} -> 6310 | I98: {=XLOOKUP(G98,'Restaurant DB'!B:B,'Restaurant DB'!N:N)} | J98: All You Can Eat | K98: 70.5 | L98: Special Price 50% Off I Stevens - Exclusive Sunday Brunch, 1:30 PM (Only 10 Seats Daily) | M98: None | N98: 2 Adults + 1 Child | O98: 5063 | P98: FALSE | S98: 45942 | T98: 0.5625 | U98: 3 | V98: Booked | W98: 582301770656252013 | X98: 8043308 | Y98: 45957 | Z98: Posted | AA98: Lars | AB98: HH-SGLUELIPZKZ56
B99: HH-SGFOISPL | C99: foodkakis | D99: 11606 | F99: Instagram.com/foodkakis | G99: Fook Kin 福劲 | H99: {=XLOOKUP(G99,'Restaurant DB All'!B:B,'Restaurant DB All'!A:A)} -> 5376 | I99: {=XLOOKUP(G99,'Restaurant DB'!B:B,'Restaurant DB'!N:N)} -> Chinese, Singaporean | J99: Party Pack | K99: 134.3 | L99: Sharing Set for 4 People | O99: 3037.548 | S99: 45942 | T99: 0.47916667 | U99: 4 | V99: Booked | W99: 582022343405339126 | X99: 8036903 | Z99: {=if(iferror(INDEX(Posts[Username],MATCH(C99&G99,Posts[Username]&Posts[Restaurant Name],0)),"")=C99,"Posted","")} -> Posted | AA99: Sirada | AB99: HH-SGFOISPLDZI98
B100: HH-CEXXZX | C100: certifiedfabclub | D100: 6567 | F100: Tiktok.com/@certifiedfabclub | G100: Obba.Jjanag | H100: {=XLOOKUP(G100,'Restaurant DB All'!B:B,'Restaurant DB All'!A:A)} -> #N/A | I100: {=XLOOKUP(G100,'Restaurant DB'!B:B,'Restaurant DB'!N:N)} -> #N/A | J100: Party Pack | K100: 143.1 | L100: BBQ Set for 3 People | M100: None | O100: 0 | S100: 45942 | T100: 0.58333333 | U100: 3 | V100: Refused | W100: 580985086305632773 | Z100: {=if(iferror(INDEX(Posts[Username],MATCH(C100&G100,Posts[Username]&Posts[Restaurant Name],0)),"")=C100,"Posted","")} | AA100: Lars | AB100: HH-CEXXZXMCT36
...

Sheet Oct Challenge
B2: KOL username | C2: In Charge | D2: Contacted | E2: Num Reviews | F2: Price per content | G2: Total price | H2: Allergies | I2: Extra Free post
B3: vincas_kitchen | C3: Gui | D3: Contacted/Accepted | E3: 3 | I3: waiting
B4: roadtripper.asia. | C4: Gui | D4: Contacted/Accepted | E4: 4 | I4: 2
B5: 8Foodlab | C5: Gui | D5: Contacted/Accepted | E5: 4
B6: Ieatishootipost | C6: Gui | D6: Contacted
B7: Onebiteonly | C7: Gui | D7: Contacted
B8: seanchankw | C8: Gui | D8: Contacted
B9: dargoyaki | C9: Gui | D9: Contacted
B10: jae7iew | C10: Gui | D10: Contacted
B11: fred.and.chloe | C11: Lars | D11: Contacted/Accepted | E11: 1 | F11: 200
B12: Auntyeats | C12: Lars | D12: Contacted/Refused
B13: Brenda Tan | C13: Lars | D13: Contacted/Refused
B14: certifiedfabclub | C14: Lars | D14: Contacted/Refused
B15: Aikenchia | C15: Lars | D15: Contacted/Refused
B16: Jason.explores | C16: Lars | D16: Contacted/Refused
B17: Lucy.rezel | C17: Lars | D17: Contacted/Accepted | E17: 4 | F17: 200 | G17: 800
B18: Rontreechan | C18: Lars | D18: Contacted/Accepted | E18: 3 | F18: 133 | G18: 400
B19: Amelia_singapore | C19: Lars | D19: Contacted/Ghosted
B20: Fir_foodie | C20: Lars | D20: Contacted/Ghosted
B21: Chiaraang | C21: Lars | D21: Contacted/Ghosted
B22: sakshi_reliving | C22: Lars | D22: Contacted/November
B23: rebeccaeatbook | C23: Lars | D23: Contacted/Accepted | E23: 3 | F23: 100 | G23: 300
B24: VannyTelly | C24: Lars | D24: Contacted/Accepted | E24: 1 | F24: 150 | G24: 150
B25: Lutonikuyalevi | C25: Lars | D25: Contacted/November
B26: Makoeats | C26: Lars | D26: Contacted/Refused
B27: Therantingpanda | C27: Lars | D27: Contacted/Refused
B28: the.sg.nomad | C28: Lars | D28: Contacted/Refused
B29: Myfoodiegallerysg | C29: Tong | D29: Contacted/Accepted | E29: 3 | F29: 300 | G29: 900
B30: eatingjourney | C30: Tong | D30: Contacted/Accepted | F30: 0 | G30: 0
B31: Bigjohnjiak | C31: Tong | D31: Contacted
B32: Goofytwocooks | C32: Tong | D32: Accepted | F32: 250
B33: Foody_flyers | C33: Tong | D33: Refused
B34: Parttimefoodblogger | C34: Tong | D34: ongoing collabs
B35: livewithxiaojie | C35: Tong | D35: Accepted | E35: 2 | F35: 200 | G35: 400
B36: ray_yee | C36: Tong | D36: Accepted
B37: eat_play_lifestyle | C37: Tong | D37: Contacted | F37: 200
B38: Foodkakis | C38: Tong | D38: Accepted | E38: 3 | F38: 120 | G38: 360
B39: eileen_eats_alot | C39: Tong | D39: Contacted | E39: 3 | F39: 200 | G39: 600
B40: Yong Wei Kai | C40: Tong | D40: Contacted
B41: jeethehungrytraveler | C41: Tong | D41: Accepted | F41: 0 | G41: 0
B42: munchingmomentswithm | C42: Tong | D42: Accepted | E42: 3 | F42: 200 | G42: 600
B43: Maggiegiehu | C43: Lars | D43: Contacted/Refused
B44: elma_chin | C44: Lars | D44: Contacted/Ghosted
B45: Arctheshark | C45: Lars | D45: Contacted/Accepted | E45: 3 | G45: 200
B46: Familystaysg | C46: Lars | D46: Contacted/Refused
B47: heyyolina616 | C47: Lars | D47: Contacted/Accepted | E47: 3 | F47: 0 | G47: 0
B48: foodhunterph | C48: Tong | D48: Accepted | E48: 3 | F48: 200 | G48: 600
B49: omgdidwejust | C49: Lars | D49: Contacted/Ghosted
B50: ghibli_ojisan | C50: Lars | D50: Contacted/Ghosted
B51: xchubbykitty | C51: Lars | D51: Contacted/Accepted | E51: 0 | F51: 0 | G51: 0
B52: blessedmomcess | C52: Lars | D52: Contacted/Refused
B53: aikokat | C53: Lars | D53: Contacted/Accepted | E53: 3 | F53: 0 | G53: 0
B54: tomatojen | C54: Lars | D54: Contacted/Accepted | E54: 3 | F54: 0 | G54: 0
B55: jjloves | C55: Guillaume | D55: Accepted | E55: 4
B56: benwhoah | C56: Lars | D56: Contacted/Refused
B57: yongthefoodmonster | C57: Tong | D57: Contacted
B58: puckerandpout | C58: Lars | D58: Contacted/Refused
B59: vivian.sg.5 | C59: Lars | D59: Contacted/Ghosted
B60: foodiekom | C60: Lars | D60: Contacted/Ghosted
B61: qlyx | C61: Lars | D61: Contacted/Refused
B62: chloebutnotreally | C62: Lars | D62: Contacted
B63: hialan1314 | C63: Lars | D63: Contacted/Accepted | E63: 3 | F63: 150 | G63: 450
B64: blackivory | C64: Lars | D64: Contacted
B65: doveria | C65: Lars | D65: Contacted
B66: getfedsg | C66: Lars | D66: Contacted/Refused
B67: goodfomood | C67: Lars | D67: Contacted/Ghosted
B68: anaffairwithfood | C68: Lars | D68: Contacted/Refused
B69: callmepuipuii | C69: Lars | D69: Contacted
B70: seoulcoolsg | C70: Lars | D70: Contacted
B71: keanmono | C71: Lars | D71: Contacted
B72: thatfoodadv | C72: Lars | D72: Contacted/Accepted

Sheet Booking MY
B1: KOL_ID | C1: Username | D1: Followers | E1: Country | F1: Social media URL | G1: Restaurant name | H1: Restaurant ID | I1: Cuisine Type | J1: Package Type | K1: Package price | L1: Package Name | M1: Allergies | N1: Comments | O1: Fee per content | P1: Column 15 | Q1: Column 16 | R1: Column 17 | S1: Target Date | T1: Target time | U1: No people | V1: Sales Check | W1: Line_thread_id | X1: Booking ID | Y1: Target post date | Z1: Post details | AA1: Notes | AB1: index
B2: HH-TESTING | C2: TESTING | D2: 12345 | E2: Test city | F2: ig.com/testing | G2: tesitng restaurant | H2: {=XLOOKUP(G2,'Restaurant DB All'!B:B,'Restaurant DB All'!A:A)} -> #N/A | I2: {=XLOOKUP(G2,'Restaurant DB'!B:B,'Restaurant DB'!N:N)} -> #N/A | J2: Party Pack | K2: 1234 | L2: Testing menu | M2: Testing alergies | N2: Test comments | O2: 12345 | P2: FALSE | R2: {=XLOOKUP(G2,'Restaurant DB'!B:B,'Restaurant DB'!I:I)} -> #N/A | S2: 33156 | T2: 0.75 | U2: 20 | V2: Asked Guillaume | W2: 588528281180176784
B3: HH-TESTING | H3: {=XLOOKUP(G3,'Restaurant DB All'!B:B,'Restaurant DB All'!A:A)} -> #N/A | I3: {=XLOOKUP(G3,'Restaurant DB'!B:B,'Restaurant DB'!N:N)} -> #N/A | P3: FALSE | R3: {=XLOOKUP(G3,'Restaurant DB'!B:B,'Restaurant DB'!I:I)} -> #N/A | W3: 588528294350291663
B4: HH-TESTING | H4: {=XLOOKUP(G4,'Restaurant DB All'!B:B,'Restaurant DB All'!A:A)} -> #N/A | I4: {=XLOOKUP(G4,'Restaurant DB'!B:B,'Restaurant DB'!N:N)} -> #N/A | P4: FALSE | R4: {=XLOOKUP(G4,'Restaurant DB'!B:B,'Restaurant DB'!I:I)} -> #N/A | W4: 588528289937883222
B5: HH-TESTING | H5: {=XLOOKUP(G5,'Restaurant DB All'!B:B,'Restaurant DB All'!A:A)} -> #N/A | I5: {=XLOOKUP(G5,'Restaurant DB'!B:B,'Restaurant DB'!N:N)} -> #N/A | P5: FALSE | R5: {=XLOOKUP(G5,'Restaurant DB'!B:B,'Restaurant DB'!I:I)} -> #N/A | W5: 588528285491921411
B6: {=XLOOKUP(C6,'KOL database'!$C$2:$C$869,'KOL database'!$B$2:$B$869)} -> #REF! | H6: {=XLOOKUP(G6,'Restaurant DB All'!B:B,'Restaurant DB All'!A:A)} -> #N/A | I6: {=XLOOKUP(G6,'Restaurant DB'!B:B,'Restaurant DB'!N:N)} -> #N/A | Q6: Approved | R6: {=XLOOKUP(G6,'Restaurant DB'!B:B,'Restaurant DB'!I:I)} -> #N/A
B7: HH-SGMEY | H7: {=XLOOKUP(G7,'Restaurant DB All'!B:B,'Restaurant DB All'!A:A)} -> #N/A | I7: {=XLOOKUP(G7,'Restaurant DB'!B:B,'Restaurant DB'!N:N)} -> #N/A | R7: {=XLOOKUP(G7,'Restaurant DB'!B:B,'Restaurant DB'!I:I)} -> #N/A

Sheet Posts
B1: KOL_ID | C1: Username | D1: Price per post | E1: Country | F1: Restaurant Code | G1: Restaurant Name | H1: Cuisine Type | I1: Social Media | J1: Social media URL | K1: Booking Date | L1: Booking ID | M1: Boost Code | N1: Post Type | O1: Post Date | P1: Post URL | Q1: D+1 | R1: Views | S1: Comments | T1: Likes | U1: D+5 | V1: Views (+5) | W1: Comments (+5) | X1: Likes (+5) | Y1: D+10 | Z1: Views (+10 | AA1: Comments (+10) | AB1: Likes (+10) | AC1: growth rate | AD1: Conv Rate | AE1: CPM | AF1: Content | AG1: Hook (First 5 Seconds) | AH1: Transcript | AI1: views (latest total)
B2: HH-IN36Y | C2: 365days2play | E2: Bangkok | F2: 1893 | G2: Sirimahannop Asiatique The Riverfront | H2: Thai-European | I2: Instagram | J2: Instagram.com/365days2play | L2: Paid | N2: Video | O2: 45527 | P2: https://www.instagram.com/p/C_AmcP_SZxO/ | Q2: 45839 | R2: 1713 | S2: 18 | T2: -1 | U2: =O2+5 -> 45532 | Y2: 45852 | Z2: 1723 | AA2: 18 | AB2: -1 | AC2: =IFERROR((Z2-R2)/R2,"") -> 0.0058377116 | AD2: =(AA2+AB2)/Z2 -> 0.0098665119 | AE2: =iferror(INDIRECT("D"&ROW()) / INDIRECT("AI"&ROW()) * 1000,0) -> 0 | AG2: Unique things to do aboard a ship, XX cuisines (AI and text) | AI2: =iferror(IFS(Z2>1,Z2,V2>1,V2,R2>1,R2),0) -> 1723
B3: HH-INAAD | C3: aayan_world | D3: 0 | E3: Bangkok | F3: 4503 | G3: Copper Beyond Buffet Gaysorn Amarin (Hungry Hub) | H3: International | I3: Instagram | J3: Instagram.com/aayan_world | L3: Paid | N3: Video | O3: 45905 | P3: https://www.instagram.com/p/DONfTcejOx6/ | Q3: =INDIRECT("o"&ROW())+1 -> 45906 | R3: 279 | S3: 0 | T3: 8 | U3: =INDIRECT("o"&ROW())+5 -> 45910 | V3: 315 | W3: 0 | X3: 8 | Y3: =INDIRECT("o"&ROW())+10 -> 45915 | Z3: 30705 | AA3: 47 | AB3: -1 | AC3: =IFERROR((Z3-R3)/R3,"") -> 109.05376 | AD3: =(AA3+AB3)/Z3 -> 0.0014981273 | AE3: =iferror(INDIRECT("D"&ROW()) / INDIRECT("AI"&ROW()) * 1000,0) -> 0 | AF3: ✨ When in Thailand, food isn’t just a meal — it’s an experience. 🇹🇭 On my recent trip, I discovered @hungryhub_th the app that completely changed the way I dine out here. Instead of walk-ins, I booked an exclusive package through Hungry Hub — knowing the price upfront, no hidden charges, and menus specially curated just for their members. 🍲🥢 From the moment the first dish arrived, I knew this wasn’t your regular dinner. It felt premium, personalized, and effortless — all thanks to Hungry Hub. The best part? These deals aren’t available anywhere else, so it feels like unlocking a secret dining world. 🔑✨ 📲 If you’re visiting or living in Thailand, skip the hassle and book your slots through Hungry Hub. Trust me, your taste buds will thank you! 💯 #hungryhub #Thailandfoodie #luxurydining #exclusivepackages #thaifoodexperience [ Hungry Hub, Thailand dining, Thailand foodie, exclusive dining packages, premium dining, curated food experiences, Thailand restaurants, luxury dining, food reservations app, no hidden charges, easy reservations, Bangkok food, Thai food journey, foodie in Thailand, unique dining deals, premium food experience, Thailand food guide, hidden gems Thailand, dining made easy, travel & food Thailand, baby food blogger, food vlogger, dubai kids] & | AI3: =iferror(IFS(Z3>1,Z3,V3>1,V3,R3>1,R3),0) -> 30705
B4: HH-INBEH | C4: beatricechongyh | E4: Bangkok | F4: #N/A | G4: Copper Beyond Buffet Gaysorn Amarin | H4: #N/A | I4: Instagram | J4: Instagram.com/beatricechongyh | L4: Paid | N4: Video | O4: 45887 | P4: https://www.instagram.com/p/DNfuVImS49G/ | Q4: =INDIRECT("o"&ROW())+1 -> 45888 | R4: 70154 | S4: 15 | U4: =INDIRECT("o"&ROW())+5 -> 45892 | Y4: =INDIRECT("o"&ROW())+10 -> 45897 | Z4: 111112 | AA4: 75 | AB4: 3572 | AC4: =IFERROR((Z4-R4)/R4,"") -> 0.58382986 | AD4: =(AA4+AB4)/Z4 -> 0.032822737 | AE4: =iferror(INDIRECT("D"&ROW()) / INDIRECT("AI"&ROW()) * 1000,0) -> 0 | AF4: Just found my new Bangkok obsession 😍 — Copper Beyond Buffet at Gaysorn Amarin! This award-winning buffet (Best Buffet Restaurants Award 2024 🏆) is next-level luxury: 🦞 Baked & Torched Canadian Lobster Tail with trio cheese velouté — creamy, rich, melt-in-your-mouth goodness 🦀 Korean Crab Paste DIY Rice Bowl — umami bomb & so fun to mix Over 140 dishes — from premium meats, fresh seafood, sushi, Thai favourites, to Michelin-level desserts 🍰✨ 💡 Pro tip: Book through Hungry Hub to get their full Pack A experience for only 2,599 THB/pax, skip the queue & dine stress-free. If you’re coming to Bangkok, SAVE this spot 🥢 — it’s 100% worth it! @hungryhub_th #hungryhubthailand #hungryhub #copperbeyondbuffet #bangkokbuffet & | AI4: =iferror(IFS(Z4>1,Z4,V4>1,V4,R4>1,R4),0) -> 111112
B5: HH-INBEH | C5: beatricechongyh | E5: Bangkok | F5: 4039 | G5: Oishi Grand Siam Paragon | H5: Japanese | I5: Instagram | J5: Instagram.com/beatricechongyh | L5: Paid | N5: Video | O5: 45889 | P5: https://www.instagram.com/p/DNk9UFHSazA/ | Q5: =INDIRECT("o"&ROW())+1 -> 45890 | R5: 91070 | S5: 9 | U5: =INDIRECT("o"&ROW())+5 -> 45894 | V5: 101891 | W5: 70 | X5: -1 | Y5: =INDIRECT("o"&ROW())+10 -> 45899 | Z5: 102159 | AA5: 70 | AB5: -1 | AC5: =IFERROR((Z5-R5)/R5,"") -> 0.12176348 | AD5: =(AA5+AB5)/Z5 -> 0.00067541773 | AE5: =iferror(INDIRECT("D"&ROW()) / INDIRECT("AI"&ROW()) * 1000,0) -> 0 | AF5: If you love Japanese food, this is the buffet to visit in Bangkok. 🍣✨ Oishi Grand at Siam Paragon serves over 140 premium dishes — from thick-cut sashimi and chef’s premium sushi sets, to wagyu udon, sizzling teppanyaki, comforting dobin mushi, Thai favourites, Chinese delicacies, and even Häagen-Dazs with juicy Japanese melon. The best part? It’s only ฿1,119 per person when you book exclusively via Hungry Hub. Premium quality, huge variety, and unbeatable value — this is hands down one of my top buffet picks in Bangkok. 📍 Siam Paragon – Oishi Grand 📲 Book now on Hungry Hub @hungryhub_th #hungryhubthailand #hungryhub #oishigrandsiamparagon #oishigrand #bangkokjapanesebuffet & | AI5: =iferror(IFS(Z5>1,Z5,V5>1,V5,R5>1,R5),0) -> 102159
B6: HH-INBEH | C6: beatricechongyh | E6: Bangkok | F6: 5945 | G6: Kohaku Omakase | H6: Japanese | I6: Instagram | J6: Instagram.com/beatricechongyh | L6: Paid | N6: Video | O6: 45892 | P6: https://www.instagram.com/p/DNse0kWYmjk/ | Q6: =INDIRECT("o"&ROW())+1 -> 45893 | R6: 72590 | S6: 6 | U6: =INDIRECT("o"&ROW())+5 -> 45897 | V6: 102741 | W6: 44 | X6: 0 | Y6: =INDIRECT("o"&ROW())+10 -> 45902 | Z6: 102775 | AA6: 44 | AB6: -1 | AC6: =IFERROR((Z6-R6)/R6,"") -> 0.41582863 | AD6: =(AA6+AB6)/Z6 -> 0.00041838969 | AE6: =iferror(INDIRECT("D"&ROW()) / INDIRECT("AI"&ROW()) * 1000,0) -> 0 | AF6: If you’re in Bangkok and craving an unforgettable sushi experience, Kohaku Omakase is a must. 🌟 Rated 4.9 stars with over 2,000 glowing reviews, it’s not just about the food — the setting is classy, calm, and intimate, perfect for a special night out or even a solo treat. The sushi here is made with premium seasonal seafood flown in directly from Japan, and every bite is a flavour bomb. 🍣 The chef’s passion really shines through — torching, plating, and presenting each dish like a piece of art. I booked via Hungry Hub and got a full 10-course omakase for only 1,165 baht — seriously unbeatable for this quality. Honestly, one of the best omakase experiences I’ve ever had. Highly recommend booking your slot through Hungry Hub to enjoy this deal. 💛 @hungryhub_th #hungryhubthailand #hungryhub & | AI6: =iferror(IFS(Z6>1,Z6,V6>1,V6,R6>1,R6),0) -> 102775
B7: HH-INBEH | C7: beatricechongyh | E7: Bangkok | F7: 5974 | G7: Lamaya Bangkok | H7: Fusion | I7: Instagram | J7: Instagram.com/beatricechongyh | L7: Paid | N7: Video | O7: 45894 | P7: https://www.instagram.com/p/DNyBhp70jHA/ | Q7: =INDIRECT("o"&ROW())+1 -> 45895 | R7: 141498 | S7: 63 | U7: =INDIRECT("o"&ROW())+5 -> 45899 | Y7: =INDIRECT("o"&ROW())+10 -> 45904 | Z7: 141551 | AA7: 63 | AB7: 3963 | AC7: =IFERROR((Z7-R7)/R7,"") -> 0.0003745636 | AD7: =(AA7+AB7)/Z7 -> 0.028442046 | AE7: =iferror(INDIRECT("D"&ROW()) / INDIRECT("AI"&ROW()) * 1000,0) -> 0 | AF7: Just found my new favourite rooftop bar in Bangkok — Lamaya! 🌇✨ Perched on the 30th floor of Staybridge Suites Sukhumvit 24, it’s got stunning city views, tribal-inspired cocktails in the cutest glasses, and that tropical escape vibe right in the middle of the city. Started outside for the views, then moved indoors for dinner — warm lighting, live jazz, and a super cozy atmosphere. 🎶 Booked the Party Pack sharing set for 2 on Hungry Hub for just 1,690 baht and got: 🍣 Hotate Uramaki 🌮 Juicy wagyu beef tacos 🦑 Crispy calamari 🍟 Truffle fries 🍹 Two drinks If you want good food + good vibes + gorgeous views, Lamaya’s where it’s at. 📌 Save this for your next trip & book via Hungry Hub for the best deal! @hungryhub_th #hungryhubthailand #hungryhub #lamayabangkok #lamayarooftopbar & | AI7: =iferror(IFS(Z7>1,Z7,V7>1,V7,R7>1,R7),0) -> 141551
B8: HH-INBEH | C8: beatricechongyh | E8: Bangkok | F8: 4889 | G8: Gentle Butcher by Bangkok Butcher | H8: Steakhouse | I8: Instagram | J8: Instagram.com/beatricechongyh | L8: Paid | N8: Video | O8: 45899 | P8: https://www.instagram.com/p/DN9y149EQ-U/ | Q8: =INDIRECT("o"&ROW())+1 -> 45900 | R8: 71010 | S8: 4 | U8: =INDIRECT("o"&ROW())+5 -> 45904 | V8: 111211 | W8: 36 | X8: -1 | Y8: =INDIRECT("o"&ROW())+10 -> 45909 | Z8: 111275 | AA8: 36 | AB8: -1 | AC8: =IFERROR((Z8-R8)/R8,"") -> 0.56703281 | AD8: =(AA8+AB8)/Z8 -> 0.00031453606 | AE8: =iferror(INDIRECT("D"&ROW()) / INDIRECT("AI"&ROW()) * 1000,0) -> 0 | AF8: If you’re a true meat lover, this is paradise. 🥩✨ At Gentle Butcher in Sathorn, I had unlimited Hataka Wagyu A5, Foie Gras, and Dry Aged Steak — all for just ฿2,390 per person when booking via Hungry Hub. From melt-in-your-mouth wagyu tenderloin to fresh lobster, grilled beef tongue, creamy truffle pasta, and even dry aged sashimi — every bite was pure bliss. 💯 The quality, variety, and flavor here are on another level. Definitely my top steak buffet pick in Bangkok. 🔥 Save this for your next trip! @hungryhub_th #hungryhubthailand #hungryhub #gentlebutcher #bangkok #steakbuffetbangkok & | AI8: =iferror(IFS(Z8>1,Z8,V8>1,V8,R8>1,R8),0) -> 111275
B9: HH-INBIK | C9: bigjohnjiak | D9: 5162 | E9: Bangkok | F9: 4503 | G9: Copper Beyond Buffet Gaysorn Amarin (Hungry Hub) | H9: International | I9: Instagram | J9: Instagram.com/bigjohnjiak | L9: Paid | N9: Video | O9: 45874 | P9: https://www.instagram.com/p/DM-YoM1T99h/ | Q9: =INDIRECT("o"&ROW())+1 -> 45875 | R9: 1910 | S9: 1 | T9: 29 | U9: =INDIRECT("o"&ROW())+5 -> 45879 | Y9: =INDIRECT("o"&ROW())+10 -> 45884 | Z9: 20952 | AA9: 9 | AB9: 154 | AC9: =IFERROR((INDIRECT("Z"&ROW()) - INDIRECT("R"&ROW())) / INDIRECT("R"&ROW()), "") -> 9.9696335 | AD9: =(INDIRECT("AA"&ROW()) + INDIRECT("AB"&ROW())) / INDIRECT("Z"&ROW()) -> 0.0077796869 | AE9: {=INDIRECT("D"&ROW()) / INDIRECT("Z"&ROW()) * 1000} -> 246.37266 | AF9: COPPER BEYOND Possibly the best luxury buffet in Bangkok. Copper beyond not only serve more than 200 all you can eat items, even oysters, sashimi, wagyu beef and lobster are all unlimited. Just download and make your reservation through Hungry Hub app to secure your slots to enjoy the deal at 2599baht ($103sgd). 📍Gaysorn Amarin, Unit 3F-s06, 3F-s07 502, Phloen Chit Rd, Lumphini, Pathum Wan, Bangkok 10330, Thailand @hungryhub_sg @hungryhub_th @copperbeyondbuffet #bangkok #buffet #travel #thailand #hungryhub #wagyu #wheretoeat #foodreview #hojiakbo #sginstagram #foodvlogger #viral #fyp #bigjohnjiak & | AI9: =iferror(IFS(Z9>1,Z9,V9>1,V9,R9>1,R9),0) -> 20952
B10: HH-INBIK | C10: bigjohnjiak | D10: 5162 | E10: Bangkok | F10: 4503 | G10: Copper Beyond Buffet Gaysorn Amarin (Hungry Hub) | H10: International | I10: Tiktok | J10: Tiktok.com/@bigjohnjiak | L10: Paid | N10: Video | O10: 45874 | P10: https://www.tiktok.com/@bigjohnjiak/video/7535086654705487111 | Q10: =INDIRECT("o"&ROW())+1 -> 45875 | U10: =INDIRECT("o"&ROW())+5 -> 45879 | Y10: =INDIRECT("o"&ROW())+10 -> 45884 | Z10: 31600 | AA10: 30 | AB10: 501 | AC10: =IFERROR((INDIRECT("Z"&ROW()) - INDIRECT("R"&ROW())) / INDIRECT("R"&ROW()), "") | AD10: =(INDIRECT("AA"&ROW()) + INDIRECT("AB"&ROW())) / INDIRECT("Z"&ROW()) -> 0.016803797 | AE10: {=iferror(INDIRECT("D"&ROW()) / INDIRECT("AI"&ROW()) * 1000,0)} -> 163.35443 | AI10: =iferror(IFS(Z10>1,Z10,V10>1,V10,R10>1,R10),0) -> 31600
B11: HH-INBIK | C11: bigjohnjiak | D11: 12656.45 | E11: Bangkok | F11: 5149 | G11: NAMA Japanese and Seafood Buffet (Hungry Hub) | H11: Japanese | I11: Tiktok | J11: https://tiktok.com/@bigjohnjiak | L11: Paid | N11: Video | O11: 45936 | P11: https://www.tiktok.com/@bigjohnjiak/video/7558094617837620487 | Q11: =INDIRECT("o"&ROW())+1 -> 45937 | R11: 21079 | S11: 28 | T11: 300 | U11: =INDIRECT("o"&ROW())+5 -> 45941 | V11: 21900 | W11: 29 | X11: 308 | Y11: =INDIRECT("o"&ROW())+10 -> 45946 | Z11: 24500 | AA11: 37 | AB11: 339 | AC11: =IFERROR((INDIRECT("Z"&ROW()) - INDIRECT("R"&ROW())) / INDIRECT("R"&ROW()), "") -> 0.16229423 | AD11: =(INDIRECT("AA"&ROW()) + INDIRECT("AB"&ROW())) / INDIRECT("Z"&ROW()) -> 0.015346939 | AE11: =INDIRECT("D"&ROW()) / INDIRECT("Z"&ROW()) * 1000 -> 516.5898 | AF11: NAMA JAPANESE AND SEAFOOD BUFFET Must try Japanese premium buffet in Bangkok with almost 200 different items from sushi, sashimi, fresh seafood to grilled meats amd more. Remember to make your reservation through the Hungry hub app. 📍24th floor Centara Grand and Bangkok Convention Centre, 999/99 Rama I Rd, Khwaeng Pathum Wan, Pathum Wan, Bangkok 10330, Thailand @hungryhubofficial #buffet #japanesefood #sashimi #wagyu #bangkok & ["buffet","japanesefood","sashimi","wagyu","bangkok"] | AI11: =iferror(IFS(Z11>1,Z11,V11>1,V11,R11>1,R11),0) -> 24500
B12: HH-INBIK | C12: bigjohnjiak | D12: 12656.45 | E12: Bangkok | F12: 5149 | G12: NAMA Japanese and Seafood Buffet (Hungry Hub) | H12: Japanese | I12: Instagram | J12: Instagram.com/bigjohnjiak | L12: Paid | N12: Video | O12: 45936 | P12: https://www.instagram.com/p/DPeBf9lkwYF/ | Q12: =INDIRECT("o"&ROW())+1 -> 45937 | R12: 15549 | S12: 11 | T12: 155 | U12: =INDIRECT("o"&ROW())+5 -> 45941 | V12: 23222 | W12: 6 | X12: 321 | Y12: =INDIRECT("o"&ROW())+10 -> 45946 | Z12: 27473 | AA12: 6 | AB12: 369 | AC12: =IFERROR((INDIRECT("Z"&ROW()) - INDIRECT("R"&ROW())) / INDIRECT("R"&ROW()), "") -> 0.76686604 | AD12: =(INDIRECT("AA"&ROW()) + INDIRECT("AB"&ROW())) / INDIRECT("Z"&ROW()) -> 0.013649765 | AE12: =INDIRECT("D"&ROW()) / INDIRECT("Z"&ROW()) * 1000 -> 460.68686 | AF12: NAMA JAPANESE AND SEAFOOD BUFFET Must try Japanese premium buffet in Bangkok with almost 200 different items from sushi, sashimi, fresh seafood to grilled meats and many more. Remember to make your reservation through the Hungry hub app. 📍24th floor Centara Grand and Bangkok Convention Centre, 999/99 Rama I Rd, Khwaeng Pathum Wan, Pathum Wan, Bangkok 10330, Thailand @hungryhubofficial @hungryhub_th @nama__buffet #buffet #japanesefood #sashimi #wagyu #bangkokfood #bangkok #whattoeat #foodreview #hojiakbo #hungryhub #foodvlogger #sginstagram #viral #fyp #bigjohnjiak & | AI12: =iferror(IFS(Z12>1,Z12,V12>1,V12,R12>1,R12),0) -> 27473
B13: HH-INBRL | C13: brenttimmtravel | E13: Bangkok | F13: #N/A | G13: Copper Beyond Buffet Gaysorn Amarin | H13: #N/A | I13: Instagram | J13: Instagram.com/brenttimmtravel | L13: Paid | N13: Video | O13: 45863 | P13: https://www.instagram.com/p/DMhAg8itih2/ | Q13: =O13+1 -> 45864 | R13: 17810 | S13: 8 | T13: 201 | U13: =O13+5 -> 45868 | V13: 43623 | W13: 10 | X13: 399 | Y13: =O13+10 -> 45873 | Z13: 52120 | AA13: 10 | AB13: 463 | AC13: =IFERROR((Z13-R13)/R13,"") -> 1.9264458 | AD13: =(AA13+AB13)/Z13 -> 0.0090752111 | AE13: =iferror(INDIRECT("D"&ROW()) / INDIRECT("AI"&ROW()) * 1000,0) -> 0 | AF13: Welcome to the BEST buffet in Thailand, and maybe the best on the planet. This is @copperbeyondbuffet , and I’m still dreaming about every sweet, savory, and succulent bite. It’s one of the most popular restaurants in Bangkok, and if you want to feast on 100+ delicious dishes, you need a reservation to avoid the long queue! I booked mine through @hungryhub_th — the app that makes it so easy to discover and reserve the hottest and most unique restaurants in Thailand, while getting the best deals every time. Which food looks the best to you? #hungryhub #buffet #thailand #bangkok #travelfoodie | AI13: =iferror(IFS(Z13>1,Z13,V13>1,V13,R13>1,R13),0) -> 52120
B14: HH-INBRL | C14: brenttimmtravel | E14: Bangkok | F14: 4889 | G14: Gentle Butcher by Bangkok Butcher | H14: Steakhouse | I14: Instagram | J14: Instagram.com/brenttimmtravel | L14: Paid | N14: Video | O14: 45883 | P14: https://www.instagram.com/p/DNU1brwo6y9/ | Q14: =INDIRECT("o"&ROW())+1 -> 45884 | R14: 11205 | S14: 3 | T14: 135 | U14: =INDIRECT("o"&ROW())+5 -> 45888 | Y14: =INDIRECT("o"&ROW())+10 -> 45893 | Z14: 35947 | AA14: 7 | AB14: 283 | AC14: =IFERROR((Z14-R14)/R14,"") -> 2.2081214 | AD14: =(AA14+AB14)/Z14 -> 0.0080674326 | AE14: =iferror(INDIRECT("D"&ROW()) / INDIRECT("AI"&ROW()) * 1000,0) -> 0 | AF14: It’s meat sweats Monday! This is the @gentle.butcher and they’re offering the most protein-packed buffet I’ve ever visited in my life. I’m pretty sure we tried every cut of steak known to man here, along with fish, shrimp, chicken, lamb and more. This restaurant is super popular, so make sure you use the @hungryhub_th app to book your table and find the best deals at Thailand’s most delicious restaurants. Which dish looked best? #hungryhub #thailand #meatsweats #bangkok #bangkokfoodie & | AI14: =iferror(IFS(Z14>1,Z14,V14>1,V14,R14>1,R14),0) -> 35947
B15: HH-INBRL | C15: brenttimmtravel | E15: Bangkok | F15: #N/A | G15: Copper Beyond Buffet Gaysorn Amarin | H15: #N/A | I15: Instagram | J15: Instagram.com/brenttimmtravel | N15: Video | O15: 45899 | P15: https://www.instagram.com/p/DN_wnndDLkd/ | Q15: =INDIRECT("o"&ROW())+1 -> 45900 | R15: 13796 | S15: 7 | T15: 156 | U15: =INDIRECT("o"&ROW())+5 -> 45904 | V15: 23638 | W15: 5 | X15: 200 | Y15: =INDIRECT("o"&ROW())+10 -> 45909 | Z15: 33510 | AA15: 7 | AB15: 229 | AC15: =IFERROR((Z15-R15)/R15,"") -> 1.4289649 | AD15: =(AA15+AB15)/Z15 -> 0.0070426738 | AE15: =iferror(INDIRECT("D"&ROW()) / INDIRECT("AI"&ROW()) * 1000,0) -> 0 | AF15: Date nights in Bangkok just hit different with roses, boats, and view of the incredible Icon Siam. My girlfriend and I celebrated out anniversary at @siamyachtclub and it was one of our most memorable nights in Thailand. We found an amazing deal on this four-course dinner with drinks using the @hungryhub_th app. This is our 3rd time using Hungry Hub in Bangkok, and it’s now our go-to app for finding the best restaurants all around the city. Download it before your next trip to Thailand and treat your partner to a night they’ll never forget! 🇹🇭 #thailand #bangkok #hungryhub #thaifoodstagram #iconsiam & | AI15: =iferror(IFS(Z15>1,Z15,V15>1,V15,R15>1,R15),0) -> 33510
B16: HH-INBRL | C16: brenttimmtravel | D16: 10000 | E16: Bangkok | F16: 4652 | G16: Jharokha by Indus | H16: Indian | I16: Instagram | J16: Instagram.com/brenttimmtravel | L16: Paid | N16: Video | O16: 45904 | P16: https://www.instagram.com/p/DOLQDXJjLaQ/ | Q16: =INDIRECT("o"&ROW())+1 -> 45905 | R16: 14697 | S16: 5 | T16: 116 | U16: =INDIRECT("o"&ROW())+5 -> 45909 | V16: 17538 | W16: 6 | X16: 133 | Y16: =INDIRECT("o"&ROW())+10 -> 45914 | Z16: 32591 | AA16: 6 | AB16: 187 | AC16: =IFERROR((Z16-R16)/R16,"") -> 1.2175274 | AD16: =(AA16+AB16)/Z16 -> 0.0059218803 | AE16: =iferror(INDIRECT("D"&ROW()) / INDIRECT("AI"&ROW()) * 1000,0) -> 306.83317 | AF16: This is the best Indian food I’ve ever had in Thailand! We were both craving Indian food, and found @jharokhabyindus through our favorite food app in Thailand – @hungryhub_th And SHEESH… this place blew us away! The flavors were out of this world——every dish packed with spice, depth, and soul . Combine that with the gorgeous setting and it’s easily one of the most memorable dining experiences we’ve had in Bangkok. Highly recommend if you’re craving authentic Indian cuisine with a touch of elegance. Download Hungry hub to find amazing restaurants like this all over Thailand! What’s the best naan? 🇹🇭 #hungryhub #bangkok #indianfood #desifood #thailand & | AI16: =iferror(IFS(Z16>1,Z16,V16>1,V16,R16>1,R16),0) -> 32591
B17: HH-INBRL | C17: brenttimmtravel | D17: 10000 | E17: Bangkok | F17: 5349 | G17: Samosorn One Bangkok | H17: Thai | I17: Instagram | J17: Instagram.com/brenttimmtravel | L17: Paid | N17: Video | O17: 45915 | P17: https://www.instagram.com/p/DOnv4PiDDlJ/ | Q17: =INDIRECT("o"&ROW())+1 -> 45916 | R17: 17254 | S17: 3 | T17: 113 | U17: =INDIRECT("o"&ROW())+5 -> 45920 | V17: 25102 | W17: 3 | X17: 148 | Y17: =INDIRECT("o"&ROW())+10 -> 45925 | Z17: 33168 | AA17: 3 | AB17: 186 | AC17: =IFERROR((INDIRECT("Z"&ROW()) - INDIRECT("R"&ROW())) / INDIRECT("R"&ROW()), "") -> 0.92233685 | AD17: =(INDIRECT("AA"&ROW()) + INDIRECT("AB"&ROW())) / INDIRECT("Z"&ROW()) -> 0.0056982634 | AE17: =iferror(INDIRECT("D"&ROW()) / INDIRECT("AI"&ROW()) * 1000,0) -> 301.49542 | AF17: For this week’s Thailand Date Night, we headed to @samosorn_restaurant and we were honestly blown away! Every dish was more than just food—it was art on a plate, with super colorful Thai-fusion flavors and mind-blowing presentation. The atmosphere was perfect for a special night out, and booking through @hungryhub_th got us an amazing discount. If you want to experience Bangkok’s most creative and vibrant Thai cuisine, this place is a must-try. Do you like Thai food? 🇹🇭 #hungryhub #thaifood #bangkok #visitthailand #bangkokeats & | AI17: =iferror(IFS(Z17>1,Z17,V17>1,V17,R17>1,R17),0) -> 33168
B18: HH-INBRL | C18: brenttimmtravel | D18: 10000 | E18: Bangkok | F18: 5349 | G18: Samosorn One Bangkok | H18: Thai | I18: Tiktok | J18: Tiktok.com/@brenttimmtravel | L18: Paid | N18: Video | O18: 45915 | P18: https://www.tiktok.com/@brent.timm.travel/video/7550273909384334622 | Q18: =INDIRECT("o"&ROW())+1 -> 45916 | R18: 11096 | S18: 10 | T18: 157 | U18: =INDIRECT("o"&ROW())+5 -> 45920 | V18: 31200 | W18: 13 | X18: 322 | Y18: =INDIRECT("o"&ROW())+10 -> 45925 | Z18: 48800 | AA18: 20 | AB18: 503 | AC18: =IFERROR((INDIRECT("Z"&ROW()) - INDIRECT("R"&ROW())) / INDIRECT("R"&ROW()), "") -> 3.3979813 | AD18: =(INDIRECT("AA"&ROW()) + INDIRECT("AB"&ROW())) / INDIRECT("Z"&ROW()) -> 0.010717213 | AE18: =iferror(INDIRECT("D"&ROW()) / INDIRECT("AI"&ROW()) * 1000,0) -> 204.91803 | AF18: For this week's Thai Date Night, we headed SAMOSORN ONE and we were honestly blown away! Every dish was more than just food—it was art on a plate, with super colorful Thai-fusion flavors and mind-blowing presentation. The atmosphere was perfect for a special night out, and booking through @HungryHub_Official got us an amazing discount. If you want to experience Bangkok’s most creative and vibrant Thai cuisine, this place is a must-try. #SamosornOne #hungryhub #thaifood #bangkok #visitthailand & ["samosornone","hungryhub","thaifood","bangkok","visitthailand"] | AI18: =iferror(IFS(Z18>1,Z18,V18>1,V18,R18>1,R18),0) -> 48800
B19: HH-INBUW | C19: bubufoodshow | E19: Bangkok | F19: #N/A | G19: Saneh Jaan Glasshouse Sindhorn Wireless road | H19: #N/A | I19: Instagram | J19: Instagram.com/bubufoodshow | L19: Paid | N19: Video | O19: 45833 | P19: https://www.instagram.com/p/DLT7WYaxASv/ | Q19: 45839 | R19: 6504 | S19: 1 | T19: 530 | U19: =O19+5 -> 45838 | Y19: =O19+10 -> 45843 | Z19: 6583 | AA19: 1 | AB19: 533 | AC19: =IFERROR((Z19-R19)/R19,"") -> 0.012146371 | AD19: =(AA19+AB19)/Z19 -> 0.081118031 | AE19: =iferror(INDIRECT("D"&ROW()) / INDIRECT("AI"&ROW()) * 1000,0) -> 0 | AG19: changing scenes according to beat (no VO, AI nor text) | AI19: =iferror(IFS(Z19>1,Z19,V19>1,V19,R19>1,R19),0) -> 6583
B20: HH-INBUW | C20: bubufoodshow | E20: Bangkok | F20: 280 | G20: Vertigo Rooftop Banyan Tree | H20: International | I20: Instagram | J20: Instagram.com/bubufoodshow | L20: Paid | N20: Video | O20: 45835 | P20: https://www.instagram.com/p/DLZjL5lRJj1/ | Q20: 45839 | R20: 3541 | S20: 1 | U20: =O20+5 -> 45840 | V20: 3577 | W20: 1 | X20: -1 | Y20: 45852 | Z20: 8976 | AA20: 1 | AB20: -1 | AC20: =IFERROR((Z20-R20)/R20,"") -> 1.5348772 | AD20: =(AA20+AB20)/Z20 -> 0 | AE20: =iferror(INDIRECT("D"&ROW()) / INDIRECT("AI"&ROW()) * 1000,0) -> 0 | AG20: changing scenes according to beat (no VO, AI nor text) | AI20: =iferror(IFS(Z20>1,Z20,V20>1,V20,R20>1,R20),0) -> 8976
B21: HH-INBUW | C21: bubufoodshow | E21: Bangkok | F21: 5836 | G21: IGNIV Bangkok at The St.Regis Bangkok (One Michelin Star) | H21: European | I21: Instagram | J21: Instagram.com/bubufoodshow | L21: Paid | N21: Video | O21: 45836 | P21: https://www.instagram.com/p/DLbcObyxqT6/ | Q21: 45839 | R21: 6951 | S21: 4 | T21: 0 | U21: =O21+5 -> 45841 | V21: 7086 | W21: 5 | X21: -1 | Y21: =O21+10 -> 45846 | Z21: 7242 | AA21: 5 | AB21: -1 | AC21: =IFERROR((Z21-R21)/R21,"") -> 0.04186448 | AD21: =(AA21+AB21)/Z21 -> 0.00055233361 | AE21: =iferror(INDIRECT("D"&ROW()) / INDIRECT("AI"&ROW()) * 1000,0) -> 0 | AG21: changing scenes according to beat (no VO, AI nor text) | AI21: =iferror(IFS(Z21>1,Z21,V21>1,V21,R21>1,R21),0) -> 7242
B22: HH-INCA9 | C22: candychi99 | E22: Bangkok | F22: 2482 | G22: Saffron Sky Garden Rooftop Banyan Tree Bangkok | H22: Thailand | I22: Instagram | J22: Instagram.com/candychi99 | L22: Paid | N22: Video | O22: 45533 | P22: https://www.instagram.com/p/C_P-LyAyQGA/ | Q22: 45839 | R22: 18190 | S22: 139 | T22: -1 | U22: =O22+5 -> 45538 | Y22: 45852 | Z22: 18209 | AA22: 139 | AB22: -1 | AC22: =IFERROR((Z22-R22)/R22,"") -> 0.00104453 | AD22: =(AA22+AB22)/Z22 -> 0.0075786699 | AE22: =iferror(INDIRECT("D"&ROW()) / INDIRECT("AI"&ROW()) * 1000,0) -> 0 | AG22: Bangkok Rooftop Bar @location, $XXX (text only) | AI22: =iferror(IFS(Z22>1,Z22,V22>1,V22,R22>1,R22),0) -> 18209
B23: HH-INCAW | C23: carmen_wqw | D23: 6355.1457 | E23: Bangkok | F23: 3862 | G23: Siam Yacht Club Royal Orchid Sheraton Riverside | H23: International | I23: Instagram | L23: Paid | N23: Video | O23: 45775 | P23: https://www.instagram.com/p/DI_DJGrvZR9/ | Q23: =INDIRECT("o"&ROW())+1 -> 45776 | U23: =INDIRECT("o"&ROW())+5 -> 45780 | Y23: 45940 | Z23: 33395 | AA23: 1 | AB23: 787 | AC23: =IFERROR((INDIRECT("Z"&ROW()) - INDIRECT("R"&ROW())) / INDIRECT("R"&ROW()), "") | AD23: =(INDIRECT("AA"&ROW()) + INDIRECT("AB"&ROW())) / INDIRECT("Z"&ROW()) -> 0.023596347 | AE23: =INDIRECT("D"&ROW()) / INDIRECT("Z"&ROW()) * 1000 -> 190.30231 | AI23: =iferror(IFS(Z23>1,Z23,V23>1,V23,R23>1,R23),0) -> 33395
B24: HH-INCHH | C24: chai_shin_yih | D24: 2754 | E24: Bangkok | F24: 3862 | G24: Siam Yacht Club Royal Orchid Sheraton Riverside | H24: International | I24: Instagram | L24: Paid | N24: Video | O24: 45751 | P24: https://www.instagram.com/p/DIBt5d0zT05/ | Q24: =INDIRECT("o"&ROW())+1 -> 45752 | U24: =INDIRECT("o"&ROW())+5 -> 45756 | Y24: 45940 | Z24: 15438 | AA24: 96 | AB24: 183 | AC24: =IFERROR((INDIRECT("Z"&ROW()) - INDIRECT("R"&ROW())) / INDIRECT("R"&ROW()), "") | AD24: =(INDIRECT("AA"&ROW()) + INDIRECT("AB"&ROW())) / INDIRECT("Z"&ROW()) -> 0.018072289 | AE24: =INDIRECT("D"&ROW()) / INDIRECT("Z"&ROW()) * 1000 -> 178.39098 | AF24: [BANGKOK 🇹🇭] @siamyachtclub Siam Yacht Club – One of the most beautiful riverside restaurants in BANGKOK! 🌊🍷✨ An evening at Siam Yacht Club at Royal Orchid Sheraton Hotel located along Chao Phraya river is pure magic! 💫 With the ICONSIAM skyline twinkling across the river, we indulged in an exclusive dining package via @hungryhub_th - The Bar Package: 3 dishes + 8 cocktails OR 1 bottle of wine for 4 people at just ฿1,990! 🍷🍹 What makes this experience special? HungryHub's exclusive packages unlock premium dining at unbeatable value, giving access to seamless reservation experience. As wine lovers, we had to go for the bottle of wine🥂, the perfect pairing for this dreamy riverside dinner. Plus, with live performances from Thursday to Sunday, the ambiance is on another level! 🎶✨ Here's what we enjoyed: 🍤 Piri-Piri White Prawns – Juicy prawns with feta, wild rocket, and a spicy kick from chili oil & lemon. 🍝 Green Curry Linguine with Wild Salmon – A bold fusion of green curry cream, ikura, anchovies Colatura, and green peas – bursting with flavor! 🔥 Tom Yum Seafood Black Rigatoni – White prawns, baby squid, and salted cod roe tossed in a tom yum-infused foam sauce. For unmatched views, gourmet flavors, and exclusive perks, this is the spot! 🍷🌊 Book on HungryHub and elevate your dining experience. #Hungryhub #SiamYachtClub #BangkokEats #ExclusiveDining #BangkokFoodie | AG24: Hungryhub SiamYachtClub BangkokEats ExclusiveDining BangkokFoodie | AI24: =iferror(IFS(Z24>1,Z24,V24>1,V24,R24>1,R24),0) -> 15438
B25: HH-INCHTSAA | C25: christianandakita | D25: 2275 | E25: Bangkok | F25: 4503 | G25: Copper Beyond Buffet Gaysorn Amarin (Hungry Hub) | H25: International | I25: Instagram | L25: Paid | N25: Video | O25: 45961 | P25: https://www.instagram.com/p/DQdbvEqEU68/ | Q25: =INDIRECT("o"&ROW())+1 -> 45962 | R25: 5526 | S25: 4 | T25: 57 | U25: =INDIRECT("o"&ROW())+5 -> 45966 | V25: 19329 | W25: 9 | X25: 259 | Y25: =INDIRECT("o"&ROW())+10 -> 45971 | Z25: 27349 | AA25: 12 | AB25: 377 | AC25: =IFERROR((INDIRECT("Z"&ROW()) - INDIRECT("R"&ROW())) / INDIRECT("R"&ROW()), "") -> 3.9491495 | AD25: =(INDIRECT("AA"&ROW()) + INDIRECT("AB"&ROW())) / INDIRECT("Z"&ROW()) -> 0.014223555 | AE25: =INDIRECT("D"&ROW()) / INDIRECT("Z"&ROW()) * 1000 -> 83.184029 | AF25: Must-Visit All-You-Can-Eat Buffet in Bangkok! 🇹🇭 Today, we had the pleasure of dining at one of the highest-rated buffets in Thailand, and it truly exceeded our expectations! The buffet featured an impressive array of self-serve stations, along with a dedicated section where you could order over 80 à la carte items, all beautifully presented in fine dining style. We booked our experience through @hungryhub_th ensuring we got the best deal possible, along with exclusive menu items! If you’re in Bangkok and looking for a culinary adventure, this buffet is a must-visit. Indulge in a feast that marries variety with gourmet flair, and savor every moment of your dining experience! - - - - #foryou #fyp #foryoupage #fy #fypシ #hungryhub #bangkok🇹🇭 #thailandfood #thailandtravel & | AI25: =iferror(IFS(Z25>1,Z25,V25>1,V25,R25>1,R25),0) -> 27349
B26: HH-INCHTSAA | C26: christianandakitaeats | D26: 2275 | E26: Bangkok | F26: 4503 | G26: Copper Beyond Buffet Gaysorn Amarin (Hungry Hub) | H26: International | I26: Tiktok | J26: https://tiktok.com/@christianandakitaeats | L26: Paid | N26: video | O26: 45961 | P26: https://www.tiktok.com/@christianandakitaeats/video/7567238129858415879 | Q26: =INDIRECT("o"&ROW())+1 -> 45962 | R26: 1342 | S26: 1 | T26: 43 | U26: =INDIRECT("o"&ROW())+5 -> 45966 | V26: 4039 | W26: 1 | X26: 96 | Y26: =INDIRECT("o"&ROW())+10 -> 45971 | Z26: 6816 | AA26: 2 | AB26: 150 | AC26: =IFERROR((INDIRECT("Z"&ROW()) - INDIRECT("R"&ROW())) / INDIRECT("R"&ROW()), "") -> 4.0789866 | AD26: =(INDIRECT("AA"&ROW()) + INDIRECT("AB"&ROW())) / INDIRECT("Z"&ROW()) -> 0.022300469 | AE26: =INDIRECT("D"&ROW()) / INDIRECT("Z"&ROW()) * 1000 -> 333.77347 | AF26: Must-Visit All-You-Can-Eat Buffet in Bangkok! 🇹🇭 Today, we had the pleasure of dining at one of the highest-rated buffets in Thailand, and it truly exceeded our expectations! The buffet featured an impressive array of self-serve stations, along with a dedicated section where you could order over 80 à la carte items, all beautifully presented in fine dining style. We booked our experience through @HungryHub_Official ensuring we got the best deal possible, along with exclusive menu items! If you’re in Bangkok and looking for a culinary adventure, this buffet is a must-visit. Indulge in a feast that marries variety with gourmet flair, and savor every moment of your dining experience! - - - - #fyp #foryoupage #thailand🇹🇭 #hungryhub & [null,"fyp","foryoupage","thailand🇹🇭","hungryhub"] | AI26: =iferror(IFS(Z26>1,Z26,V26>1,V26,R26>1,R26),0) -> 6816
B27: HH-INCHTSAA | C27: christianandakitaeats | D27: 2275 | E27: Bangkok | F27: 5149 | G27: NAMA Japanese and Seafood Buffet (Hungry Hub) | H27: Japanese | I27: Tiktok | J27: https://tiktok.com/@christianandakitaeats | L27: Paid | N27: video | O27: 45965 | P27: https://www.tiktok.com/@christianandakitaeats/video/7568815515422969095 | Q27: =INDIRECT("o"&ROW())+1 -> 45966 | R27: 1460 | S27: 0 | T27: 48 | U27: =INDIRECT("o"&ROW())+5 -> 45970 | V27: 3865 | W27: 2 | X27: 101 | Y27: =INDIRECT("o"&ROW())+10 -> 45975 | Z27: 5530 | AA27: 2 | AB27: 132 | AC27: =IFERROR((INDIRECT("Z"&ROW()) - INDIRECT("R"&ROW())) / INDIRECT("R"&ROW()), "") -> 2.7876712 | AD27: =(INDIRECT("AA"&ROW()) + INDIRECT("AB"&ROW())) / INDIRECT("Z"&ROW()) -> 0.024231465 | AE27: =INDIRECT("D"&ROW()) / INDIRECT("Z"&ROW()) * 1000 -> 411.39241 | AF27: Best Japanese Buffet in Thailand! 🇹🇭 We visited the best seafood Japanese buffet in Bangkok! If you love seafood and sushi this is a must visit spot and make sure you book through @HungryHub_Official - - - - #foryou #fyp #fy #foryoupage #hungryhub & [null,"foryou","fyp","fy","foryoupage","hungryhub"] | AI27: =iferror(IFS(Z27>1,Z27,V27>1,V27,R27>1,R27),0) -> 5530
B28: HH-INCHTSAA | C28: christianandakitaeats | D28: 4550 | E28: Bangkok | F28: 1594 | G28: Flavors at Renaissance Bangkok | H28: International | I28: Tiktok | J28: https://tiktok.com/@christianandakitaeats | L28: Paid | N28: video | O28: 45977 | P28: https://www.tiktok.com/@christianandakitaeats/video/7573236343678176530 | Q28: =INDIRECT("o"&ROW())+1 -> 45978 | R28: 8408 | S28: 4 | T28: 198 | U28: =INDIRECT("o"&ROW())+5 -> 45982 | V28: 8769 | W28: 4 | X28: 208 | Y28: =INDIRECT("o"&ROW())+10 -> 45987 | AC28: =IFERROR((INDIRECT("Z"&ROW()) - INDIRECT("R"&ROW())) / INDIRECT("R"&ROW()), "") -> -1 | AD28: =(INDIRECT("AA"&ROW()) + INDIRECT("AB"&ROW())) / INDIRECT("Z"&ROW()) -> #DIV/0! | AE28: =INDIRECT("D"&ROW()) / INDIRECT("Z"&ROW()) * 1000 -> #DIV/0! | AF28: Buffets in Bangkok are amazing! 🤩 #foryou #fyp #foryoupage #hungryhub & ["foryou","fyp","foryoupage","hungryhub"]
B29: HH-INDIY | C29: dilanthony | E29: Bangkok | F29: 712 | G29: Vertigo TOO Banyan Tree | H29: International | I29: Instagram | J29: Instagram.com/dilanthony | L29: Paid | N29: Video | O29: 45505 | P29: https://www.instagram.com/p/C-ITWVQPKUs/ | Q29: 45839 | R29: 793890 | S29: 136 | T29: 30271 | U29: =O29+5 -> 45510 | Y29: 45852 | Z29: 793985 | AA29: 136 | AB29: 30256 | AC29: =IFERROR((Z29-R29)/R29,"") -> 0.00011966393 | AD29: =(AA29+AB29)/Z29 -> 0.038277801 | AE29: =iferror(INDIRECT("D"&ROW()) / INDIRECT("AI"&ROW()) * 1000,0) -> 0 | AG29: There's this really nice rooftop spot that I want to take you to... conversation with someone (VO and text) | AI29: =iferror(IFS(Z29>1,Z29,V29>1,V29,R29>1,R29),0) -> 793985
B30: HH-INDRM | C30: drelias_tam | E30: Bangkok | F30: 837 | G30: Copper Beyond Buffet The Sense Pinklao (Hungry Hub) | H30: International | I30: Instagram | J30: Instagram.com/drelias_tam | L30: Paid | N30: Video | O30: 45518 | P30: https://www.instagram.com/p/C-pROhOyD1M/ | Q30: 45839 | R30: 166198 | S30: 40 | T30: 2090 | U30: =O30+5 -> 45523 | Y30: 45852 | Z30: 166281 | AA30: 40 | AB30: 2090 | AC30: =IFERROR((Z30-R30)/R30,"") -> 0.00049940432 | AD30: =(AA30+AB30)/Z30 -> 0.012809642 | AE30: =iferror(INDIRECT("D"&ROW()) / INDIRECT("AI"&ROW()) * 1000,0) -> 0 | AG30: XX and XXX at a buffet in XXX (text only) OMG. There is XXXX in this Buffet?? (VO and text) | AI30: =iferror(IFS(Z30>1,Z30,V30>1,V30,R30>1,R30),0) -> 166281
B31: HH-INFOX | C31: foodtreasurebox | E31: Bangkok | F31: 837 | G31: Copper Beyond Buffet The Sense Pinklao (Hungry Hub) | H31: International | I31: Instagram | J31: Instagram.com/foodtreasurebox | L31: Paid | N31: Video | O31: 45539 | P31: https://www.instagram.com/p/C_fpQxsSAsf/ | Q31: 45839 | R31: 118581 | S31: 8 | T31: 1615 | U31: =O31+5 -> 45544 | Y31: 45852 | Z31: 118703 | AA31: 8 | AB31: 1617 | AC31: =IFERROR((Z31-R31)/R31,"") -> 0.0010288326 | AD31: =(AA31+AB31)/Z31 -> 0.013689629 | AE31: =iferror(INDIRECT("D"&ROW()) / INDIRECT("AI"&ROW()) * 1000,0) -> 0 | AG31: The Best XXX Buffet (text only) I can't believe I just had caviar at a buffet (VO and text) | AI31: =iferror(IFS(Z31>1,Z31,V31>1,V31,R31>1,R31),0) -> 118703
B32: HH-INGIM | C32: giadinhcamcam | E32: Bangkok | F32: 5711 | G32: Apsara Cruise by Banyan Tree | H32: Thai | I32: Tiktok | J32: Tiktok.com/@giadinhcamcam | L32: Paid | N32: Video | O32: 45857 | P32: https://www.tiktok.com/@giadinhcamcam/video/7530268593448340744 | Q32: =O32+1 -> 45858 | R32: 1949 | S32: 1 | T32: 96 | U32: =O32+5 -> 45862 | Y32: =O32+10 -> 45867 | Z32: 19200 | AA32: 6 | AB32: 319 | AC32: =IFERROR((Z32-R32)/R32,"") -> 8.8512057 | AD32: =(AA32+AB32)/Z32 -> 0.016927083 | AE32: =iferror(INDIRECT("D"&ROW()) / INDIRECT("AI"&ROW()) * 1000,0) -> 0 | AF32: Series đi Thái và những điều chưa thử: Trải nghiệm kiểu “fine-dining” trên sông giữa lòng Bangkok @HungryHub_Official #giadinhcamcam #HungryHub #thailand #foodtiktok | AI32: =iferror(IFS(Z32>1,Z32,V32>1,V32,R32>1,R32),0) -> 19200
B33: HH-INGIM | C33: giadinhcamcam | E33: Bangkok | F33: #N/A | G33: Copper Beyond Buffet Gaysorn Amarin | H33: #N/A | I33: Tiktok | J33: Tiktok.com/@giadinhcamcam | L33: Paid | N33: Video | O33: 45864 | P33: https://www.tiktok.com/@giadinhcamcam/video/7531243629118082322 | Q33: =O33+1 -> 45865 | R33: 21477 | S33: 5 | T33: 889 | U33: =O33+5 -> 45869 | Y33: =O33+10 -> 45874 | Z33: 64800 | AA33: 17 | AB33: 1862 | AC33: =IFERROR((Z33-R33)/R33,"") -> 2.0171812 | AD33: =(AA33+AB33)/Z33 -> 0.028996914 | AE33: =iferror(INDIRECT("D"&ROW()) / INDIRECT("AI"&ROW()) * 1000,0) -> 0 | AF33: Series đi Thái và những điều chưa thử p.2: Buffet cao cấp với đầu bếp Michelin ngay trung tâm Bangkok mà có giá hợp lý có thể bạn chưa biết #giadinhcamcam #fyp @HungryHub_Official #HungryHub & ["giadinhcamcam","fyp","hungryhub"] | AI33: =iferror(IFS(Z33>1,Z33,V33>1,V33,R33>1,R33),0) -> 64800
B34: HH-INGIM | C34: giadinhcamcam | E34: Bangkok | F34: 5149 | G34: NAMA Japanese and Seafood Buffet (Hungry Hub) | H34: Japanese | I34: Tiktok | J34: Tiktok.com/@giadinhcamcam | L34: Paid | N34: Video | O34: 45872 | P34: https://www.tiktok.com/@giadinhcamcam/video/7534347870984572168 | Q34: =INDIRECT("o"&ROW())+1 -> 45873 | R34: 6815 | S34: 3 | T34: 205 | U34: =INDIRECT("o"&ROW())+5 -> 45877 | Y34: =INDIRECT("o"&ROW())+10 -> 45882 | Z34: 30900 | AA34: 6 | AB34: 704 | AC34: =IFERROR((Z34-R34)/R34,"") -> 3.5341159 | AD34: =(AA34+AB34)/Z34 -> 0.022977346 | AE34: =iferror(INDIRECT("D"&ROW()) / INDIRECT("AI"&ROW()) * 1000,0) -> 0 | AF34: Series đi Thái và những điều chưa thử p.4: Buffet hải sản Nhật cao cấp ngay CentralWorld mà bọn mình mới tìm được... @HungryHub_Official #giadinhcamcam #foodtiktok #thailand🇹🇭 #HungryHub & ["giadinhcamcam","foodtiktok","thailand🇹🇭","hungryhub"] | AI34: =iferror(IFS(Z34>1,Z34,V34>1,V34,R34>1,R34),0) -> 30900
B35: HH-INGON | C35: gocmengen | D35: 0 | E35: Bangkok | F35: 4503 | G35: Copper Beyond Buffet Gaysorn Amarin (Hungry Hub) | H35: International | I35: Instagram | J35: Instagram.com/gocmengen | L35: Paid | N35: Video | O35: 45915 | P35: https://www.instagram.com/p/DOnsRjljfK4/ | Q35: =INDIRECT("o"&ROW())+1 -> 45916 | R35: 5654 | S35: 5 | T35: 59 | U35: =INDIRECT("o"&ROW())+5 -> 45920 | V35: 7534 | W35: 5 | X35: 65 | Y35: =INDIRECT("o"&ROW())+10 -> 45925 | Z35: 13285 | AA35: 7 | AB35: 84 | AC35: =IFERROR((INDIRECT("Z"&ROW()) - INDIRECT("R"&ROW())) / INDIRECT("R"&ROW()), "") -> 1.349664 | AD35: =(INDIRECT("AA"&ROW()) + INDIRECT("AB"&ROW())) / INDIRECT("Z"&ROW()) -> 0.0068498306 | AE35: =iferror(INDIRECT("D"&ROW()) / INDIRECT("AI"&ROW()) * 1000,0) -> 0 | AF35: Konum için kaydedin❣️ [TR] Tayland’da en özel restoranlarda sıra beklemeden yerinizi ayırtmaya ne dersiniz? Üstelik özel menülere, özel fiyatlarla ulaşma imkanı da var! Ben Copper Beyond Buffet’te Hungry Hub sayesinde hem en iyi fiyatı yakaladım hem de hiç sıra beklemeden direkt masama geçtim🦞 Kişi başı 2.600 Baht’a, 2 saat boyunca sınırsız açık büfe keyfi için rezervasyonunuzu @hungryhub_th üzerinden yapabilirsiniz. Bangkok’a geliyorsanız listenizin başına mutlaka ekleyin!🇹🇭 [EN] How about reserving a table at Thailand’s most exclusive restaurants without waiting in line? ✨ Plus, you get access to special menus at special prices! I experienced Copper Beyond Buffet with Hungry Hub and got the best deal — and the best part, I skipped the line and went straight to my table 🦞 For just 2,600 Baht per person, you can enjoy a 2-hour all-you-can-eat buffet. Simply book your spot through @hungryhub_th If you’re coming to Bangkok, this should definitely be on your list! 🇹🇭 Reklam #işbirliği #collab #thailand #bangkok #dining #copperbeyondbuffet #hungryhub #travel & | AI35: =iferror(IFS(Z35>1,Z35,V35>1,V35,R35>1,R35),0) -> 13285
B36: HH-INGOS | C36: goofytwocooks | D36: 2072 | E36: Bangkok | F36: 4039 | G36: Oishi Grand Siam Paragon | H36: Japanese | I36: Instagram | J36: Instagram.com/goofytwocooks | L36: Paid | N36: Video | O36: 45829 | P36: https://www.instagram.com/p/DLKb_7jzYaQ/ | Q36: =INDIRECT("o"&ROW())+1 -> 45830 | R36: 42502 | S36: 64 | U36: =INDIRECT("o"&ROW())+5 -> 45834 | Y36: =INDIRECT("o"&ROW())+10 -> 45839 | Z36: 42502 | AA36: 64 | AC36: =IFERROR((INDIRECT("Z"&ROW()) - INDIRECT("R"&ROW())) / INDIRECT("R"&ROW()), "") -> 0 | AD36: =(INDIRECT("AA"&ROW()) + INDIRECT("AB"&ROW())) / INDIRECT("Z"&ROW()) -> 0.0015058115 | AE36: {=INDIRECT("D"&ROW()) / INDIRECT("Z"&ROW()) * 1000} -> 48.750647 | AF36: All-You-Can-Eat 🎌🍣Craving quality Japanese cuisine in the heart of Bangkok? Head to Oishi Grand at Siam Paragon for a premium buffet experience. From melt-in-your-mouth sashimi and handcrafted sushi to sizzling grilled meats and crispy tempura, every dish is a celebration of authentic flavors and finesse. 🍣🔥 🌟 Pro tip: Book through the Hungry Hub App to unlock exclusive discounts, enjoy special set menus, and rack up Hungry Points (1 point = 1 Baht!). It’s the smartest way to dine in style and save while you’re at it. #OishiGrand #SiamParagonEats #JapaneseBuffet #BangkokFoodie #HungryHubDeals #AllYouCanEatDelight 🍱 | AI36: =iferror(IFS(Z36>1,Z36,V36>1,V36,R36>1,R36),0) -> 42502
B37: HH-INHAS | C37: happylizzieeats | E37: Bangkok | F37: 5977 | G37: Baan Suriyasai @ One Bangkok | H37: Thai | I37: Instagram | J37: Instagram.com/happylizzieeats | L37: Paid | N37: Video | O37: 45832 | P37: https://www.instagram.com/p/DLSheAuvuVN/ | Q37: 45839 | R37: 4873 | S37: 12 | U37: =O37+5 -> 45837 | Y37: =O37+10 -> 45842 | Z37: 5109 | AA37: 12 | AB37: -1 | AC37: =IFERROR((Z37-R37)/R37,"") -> 0.048430125 | AD37: =(AA37+AB37)/Z37 -> 0.0021530632 | AE37: =iferror(INDIRECT("D"&ROW()) / INDIRECT("AI"&ROW()) * 1000,0) -> 0 | AG37: Experience Authentic Royal Thai Cuisine in an XXX way (VO and text) | AI37: =iferror(IFS(Z37>1,Z37,V37>1,V37,R37>1,R37),0) -> 5109
B38: HH-INHAS | C38: happylizzieeats | E38: Bangkok | F38: 5904 | G38: Restaurant PATT | H38: French | I38: Instagram | J38: Instagram.com/happylizzieeats | L38: Paid | N38: Video | O38: 45838 | P38: https://www.instagram.com/p/DLh4KrFP2W5/ | Q38: 45839 | R38: 3737 | S38: 21 | U38: =O38+5 -> 45843 | V38: 8097 | W38: 29 | X38: -1 | Y38: =O38+10 -> 45848 | Z38: 8869 | AA38: 30 | AB38: -1 | AC38: =IFERROR((Z38-R38)/R38,"") -> 1.3732941 | AD38: =(AA38+AB38)/Z38 -> 0.0032698162 | AE38: =iferror(INDIRECT("D"&ROW()) / INDIRECT("AI"&ROW()) * 1000,0) -> 0 | AG38: This got to be one of XXX's BEST NEW Restaurants... (VO and text) | AI38: =iferror(IFS(Z38>1,Z38,V38>1,V38,R38>1,R38),0) -> 8869
B39: HH-INHOY | C39: hotelbuffet.my | E39: Bangkok | F39: #N/A | G39: Copper Beyond Buffet Gaysorn Amarin | H39: #N/A | I39: Instagram | J39: Instagram.com/hotelbuffet.my | L39: Paid | N39: Video | O39: 45893 | P39: https://www.instagram.com/p/DNuw3dE5ueh/ | Q39: =INDIRECT("o"&ROW())+1 -> 45894 | R39: 562 | S39: 0 | T39: 23 | U39: =INDIRECT("o"&ROW())+5 -> 45898 | V39: 5301 | W39: 4 | X39: 54 | Y39: =INDIRECT("o"&ROW())+10 -> 45903 | Z39: 5305 | AA39: 4 | AB39: 54 | AC39: =IFERROR((Z39-R39)/R39,"") -> 8.4395018 | AD39: =(AA39+AB39)/Z39 -> 0.010933082 | AE39: =iferror(INDIRECT("D"&ROW()) / INDIRECT("AI"&ROW()) * 1000,0) -> 0 | AF39: 没来过 @copperbeyondbuffet , 就不算来过曼谷! Buffet业里的Fine Dine!❤️❤️ 一间高端顶级Buffet, 无人不知晓的【Copper Beyond Buffet】! 这家是曼谷本地人甚至游客也爱去的Buffet餐厅, 水准远超过一般酒店Buffet, 不是只有浮夸, 而是真材实料, 道道精致!😋😋 Copper Beyond Buffet 主打的是“比酒店更有诚意”的自助餐! 每一道菜都讲究质感与摆盘, 而且味道完全对得起价格! 不是那种只是选项多, 而是每一样你吃下去都会觉得：“哇, 做得很好吃,!” 今晚吃的是Hungry Hub Pack A 2599Baht, 这个配套包括了其中一道Special Menu (Baked & Torched Canadian Lobster Tail with Trio Cheese Veloute; Khao-Soi Lobster Truffle Espuma or Korean Crab Paste D.I.Y) ! 这个只有在Hungry Hub 预约与购买才有的哦！❤️❤️ 我们选着了Lobster Tail with Trio Cheese 和 Korean Crab ! 好吃😋 今晚really cincai 叫, cincai 吃, 毕竟第一次来, 有没有😂😂 没来的急做攻略, 但是ho, really beh pai, 每一样都色香味俱全！❤️😋 以下这几样都是a la carte 单点的, 要去到Ordering Counter 然后讲你的桌好, 然后讲你要点什么号码的食物,就搞定了！ 食物然后会送来桌子😘😘 前菜: - Spanish Iberico Ham w Melon❤️❤️ - Crispy Homemade Tofu Foie Gras with White Truffle👍👍 - Hokkaido Scallop A La Plancha Cauliflower, Raisin Purée😋😋 - Cured Wet-aged Seabass, Grapes with Tomato Essence😍😍 - Argentinian Prawn Tartare, Green Pea and Wasabi Foam🥰 主食: - Australian Striploin Steak (YYDS😘) - Australian Wagyu Sushi ❤️❤️❤️ 特别菜肴 : - Abalone Puff Pastry❤️ - Abalone Orzo Pasta❤️❤️ 然后呢, 以下是在Serving Station 拿的: - Truffle Soup with Croissant ❤️ - Wagyu Prime Rib Marble 5/6❤️❤️ - Copper Smokey Pork Rib👍👍 - Sous Vibe Beef Tongue❤️❤️ - Australian Wagyu Beef Boat Noodle❤️❤️❤️ - Grilled River Prawns 😋😋 - Oyster 和 Sashimi 😘😘 甜也有单点, 也有在Serving Station❤️ 感觉上, 好像只是吃了这里的菜单10% 而已, 下次再来盘🤭😂 整体环境高雅, 用餐氛围舒服, 食材补得快, 很多精致的食物都是即点即煮, 而且服务人员训练有素, 收盘, 送餐都非常快!❤️ 重要提醒：Copper Beyond 是曼谷最容易爆满的Buffet之一，几乎每天都有人排长龙, 没有接受walk-in 的! 通过 @hungryhub_th App 提前预订, 不只是方便, 用Hungry Hub Booking, 还可以选着特别菜单, 放心省时又专业 ❤️ 还有记得做攻略, 一进如就立马去Order A La Carte 的menu, 另外一位战友也要去拿其他食物咯.. 不要等哦😂😂 晚餐是两个时段: 5pm-7pm / 7.30pm-9.30pm 预约: Copper Beyond Buffet Gaysorn Amarin https://hhub.ly/7KGVE Menu: https://online.fliphtml5.com/imgdc/warq/#p=1 #HungryHub #CopperBeyondBuffet #CopperAtGaysornAmarin #amazingthailand #bangkokbuffet #hotelbuffet吃到饱吹水站 #hotelbuffet吃到饱分享站 & | AI39: =iferror(IFS(Z39>1,Z39,V39>1,V39,R39>1,R39),0) -> 5305
B40: HH-INITN | C40: itsyourgirl.erin | D40: 5000 | E40: Bangkok | F40: 4503 | G40: Copper Beyond Buffet Gaysorn Amarin (Hungry Hub) | H40: International | I40: Instagram | J40: Instagram.com/itsyourgirl.erin | L40: Paid | N40: Video | O40: 45925 | P40: https://www.instagram.com/p/DPBgKtJgWDT/ | Q40: =INDIRECT("o"&ROW())+1 -> 45926 | R40: 5969 | S40: 8 | T40: -1 | U40: =INDIRECT("o"&ROW())+5 -> 45930 | V40: 8859 | W40: 8 | X40: -1 | Y40: =INDIRECT("o"&ROW())+10 -> 45935 | Z40: 33595 | AA40: 8 | AB40: -1 | AC40: =IFERROR((INDIRECT("Z"&ROW()) - INDIRECT("R"&ROW())) / INDIRECT("R"&ROW()), "") -> 4.6282459 | AD40: =(INDIRECT("AA"&ROW()) + INDIRECT("AB"&ROW())) / INDIRECT("Z"&ROW()) -> 0.00020836434 | AE40: {=INDIRECT("D"&ROW()) / INDIRECT("Z"&ROW()) * 1000} -> 148.83167 | AF40: This is your sign to try one of the most premium buffets in Bangkok! ✨ Unlimited Wagyu, fresh seafood, and over 80 à la carte dishes served straight to your table. Pro tip: Book through HungryHub to score extra dishes like the Lobster, enjoy better deals than walk-ins, and get access to an exclusive menu. 📍 Copper Beyond Buffet 3rd Floor, Gaysorn Amarin @copperbeyondbuffet #copperbeyondbuffet #buffet #bangkok #thailand #bkk #food #seafood #wagyu #unlimited & | AI40: =iferror(IFS(Z40>1,Z40,V40>1,V40,R40>1,R40),0) -> 33595
B41: HH-INITN | C41: itsyourgirl.erin | D41: 5000 | E41: Bangkok | F41: 4503 | G41: Copper Beyond Buffet Gaysorn Amarin (Hungry Hub) | H41: International | I41: Tiktok | J41: Tiktok.com/@itsyourgirl.erin | L41: Paid Thai | N41: Video | O41: 45925 | P41: https://www.tiktok.com/@itsyourgirl.erin/video/7553988136154549525 | Q41: =INDIRECT("o"&ROW())+1 -> 45926 | R41: 215 | S41: 1 | T41: 16 | U41: =INDIRECT("o"&ROW())+5 -> 45930 | V41: 1697 | W41: 1 | X41: 19 | Y41: =INDIRECT("o"&ROW())+10 -> 45935 | Z41: 283 | AA41: 1 | AB41: 21 | AC41: =IFERROR((INDIRECT("Z"&ROW()) - INDIRECT("R"&ROW())) / INDIRECT("R"&ROW()), "") -> 0.31627907 | AD41: =(INDIRECT("AA"&ROW()) + INDIRECT("AB"&ROW())) / INDIRECT("Z"&ROW()) -> 0.077738516 | AE41: {=iferror(INDIRECT("D"&ROW()) / INDIRECT("AI"&ROW()) * 1000,0)} -> 17667.845 | AF41: This is your sign to try one of the most premium buffets in Bangkok! ✨ Unlimited Wagyu, fresh seafood, and over 80 à la carte dishes served straight to your table. Pro tip: Book through HungryHub to score extra dishes like the Lobster, enjoy better deals than walk-ins, and get access to an exclusive menu. 📍 Copper Beyond Buffet 3rd Floor, Gaysorn Amarin @CopperBeyondBuffet #buffet #bangkok #thailand #bkk #food & ["buffet","bangkok","thailand","bkk","food"] | AI41: =iferror(IFS(Z41>1,Z41,V41>1,V41,R41>1,R41),0) -> 283
B42: HH-INITN | C42: itsyourgirl.erin | D42: 5000 | E42: Bangkok | F42: 3005 | G42: Great Harbour International Buffet | H42: International | I42: Instagram | J42: Instagram.com/itsyourgirl.erin | L42: Paid Thai | N42: Video | O42: 45927 | P42: https://www.instagram.com/p/DPF9yJ_gaRI/ | Q42: =INDIRECT("o"&ROW())+1 -> 45928 | R42: 230 | S42: 8 | T42: -1 | U42: =INDIRECT("o"&ROW())+5 -> 45932 | V42: 18174 | W42: 36 | X42: -1 | Y42: =INDIRECT("o"&ROW())+10 -> 45937 | Z42: 173923 | AA42: 49 | AB42: -1 | AC42: =IFERROR((INDIRECT("Z"&ROW()) - INDIRECT("R"&ROW())) / INDIRECT("R"&ROW()), "") -> 755.18696 | AD42: =(INDIRECT("AA"&ROW()) + INDIRECT("AB"&ROW())) / INDIRECT("Z"&ROW()) -> 0.0002759842 | AE42: =INDIRECT("D"&ROW()) / INDIRECT("Z"&ROW()) * 1000 -> 28.748354 | AF42: If variety is your thing, Great Harbour is a food lover’s paradise! 🥢🦐🍝 From classic Asian favorites like dim sum, Peking duck, and fresh seafood to Western delights such as pasta, steak, and indulgent desserts, the selection is so wide you won’t be able to try it all in just one visit ✨ Book through HungryHub to get better prices, easy reservations, and exclusive deals to make your dining experience even more special 🙌🏻 📍 6th Floor, ICONSIAM @great_harbour_th @hungryhub_th #bangkok #thailand #bkk #buffet #iconsiam #greatharbour #foodie #food & | AI42: =iferror(IFS(Z42>1,Z42,V42>1,V42,R42>1,R42),0) -> 173923
B43: HH-INITN | C43: itsyourgirl.erin | D43: 5000 | E43: Bangkok | F43: 5149 | G43: NAMA Japanese and Seafood Buffet (Hungry Hub) | H43: Japanese | I43: Instagram | J43: Instagram.com/itsyourgirl.erin | L43: Paid Thai | N43: Video | O43: 45929 | P43: https://www.instagram.com/p/DPLWBOCAXgo/ | Q43: =INDIRECT("o"&ROW())+1 -> 45930 | R43: 725 | S43: 5 | T43: -1 | U43: =INDIRECT("o"&ROW())+5 -> 45934 | V43: 14117 | W43: 6 | X43: 0 | Y43: =INDIRECT("o"&ROW())+10 -> 45939 | Z43: 14137 | AA43: 6 | AB43: -1 | AC43: =IFERROR((INDIRECT("Z"&ROW()) - INDIRECT("R"&ROW())) / INDIRECT("R"&ROW()), "") -> 18.49931 | AD43: =(INDIRECT("AA"&ROW()) + INDIRECT("AB"&ROW())) / INDIRECT("Z"&ROW()) -> 0.00035368183 | AE43: =INDIRECT("D"&ROW()) / INDIRECT("Z"&ROW()) * 1000 -> 353.68183 | AF43: Craving Japanese flavors with a view? 🍣✨ NAMA takes dining to the next level with fresh sashimi, melt-in-your-mouth Wagyu, premium seafood, and a stunning cityscape to match every bite! Book through HungryHub to unlock an exclusive menu and enjoy unbeatable deals with seamless reservations ❤️ @nama__buffet @hungryhub_th 📍 24th Floor, Centara Grand @ CentralWorld #namajapaneseandseafoodbuffet #centaragrand #centralworld #bangkok #thailand #foodie #food #bkk & | AI43: =iferror(IFS(Z43>1,Z43,V43>1,V43,R43>1,R43),0) -> 14137
B44: HH-INKA_ | C44: kawaiimah_ | E44: Bangkok | F44: 2482 | G44: Saffron Sky Garden Rooftop Banyan Tree Bangkok | H44: Thailand | I44: Instagram | J44: Instagram.com/kawaiimah_ | L44: Paid | N44: Video | O44: 45558 | P44: https://www.instagram.com/p/DAP8JgWPCZg/ | Q44: 45839 | R44: 12885 | S44: 8 | T44: -1 | U44: =O44+5 -> 45563 | Y44: 45852 | Z44: 12906 | AA44: 8 | AB44: -1 | AC44: =IFERROR((Z44-R44)/R44,"") -> 0.0016298021 | AD44: =(AA44+AB44)/Z44 -> 0.00054238339 | AE44: =iferror(INDIRECT("D"&ROW()) / INDIRECT("AI"&ROW()) * 1000,0) -> 0 | AG44: POV: You found XXX's Highly rated and XXXX Restaurant (text only) | AI44: =iferror(IFS(Z44>1,Z44,V44>1,V44,R44>1,R44),0) -> 12906
B45: HH-INKI_ | C45: kivalive_ | D45: 6666.66 | E45: Bangkok | F45: 4195 | G45: Jim Thompson, A Thai Restaurant | H45: Thai | I45: Instagram | J45: Instagram.com/kivalive_ | L45: Paid Thai | N45: Video | O45: 45916 | P45: https://www.instagram.com/p/DOp9i4fEjZ9/ | Q45: =INDIRECT("o"&ROW())+1 -> 45917 | R45: 1135 | S45: 4 | T45: 54 | U45: =INDIRECT("o"&ROW())+5 -> 45921 | V45: 8856 | W45: 6 | X45: 241 | Y45: =INDIRECT("o"&ROW())+10 -> 45926 | Z45: 12126 | AA45: 6 | AB45: 314 | AC45: =IFERROR((INDIRECT("Z"&ROW()) - INDIRECT("R"&ROW())) / INDIRECT("R"&ROW()), "") -> 9.6837004 | AD45: =(INDIRECT("AA"&ROW()) + INDIRECT("AB"&ROW())) / INDIRECT("Z"&ROW()) -> 0.026389576 | AE45: =iferror(INDIRECT("D"&ROW()) / INDIRECT("AI"&ROW()) * 1000,0) -> 549.78229 | AF45: ✨ Save this unique Thai dining experience in a heritage house or beside the koi pond! ✨ We found this amazing dining spot via @hungryhub_th — @jimthompsonathairestaurant is a relaxing luxury spot with refined Thai cuisine🍴 We booked Jim’s Party A for 2 (2,590 THB), which comes with 4 dishes + 2 drinks. Must-try: the melt-in-your-mouth Grilled Wagyu in Panang Curry & the bold Tom Yum Goong 🦐🔥 Walking distance from BTS National Stadium with a free shuttle bus available! 📍 @hungryhub_th @jimthompsonathairestaurant #bangkok #thailand #bangkoktravel #bangkokfood #thaicuisine & | AI45: =iferror(IFS(Z45>1,Z45,V45>1,V45,R45>1,R45),0) -> 12126
B46: HH-INKI_ | C46: kivalive_ | D46: 6666.66 | E46: Bangkok | F46: 5945 | G46: Kohaku Omakase | H46: Japanese | I46: Instagram | J46: Instagram.com/kivalive_ | L46: Paid Thai | N46: Video | O46: 45922 | P46: https://www.instagram.com/p/DO5nIu_krN9/ | Q46: =INDIRECT("o"&ROW())+1 -> 45923 | R46: 2024 | S46: 12 | T46: 69 | U46: =INDIRECT("o"&ROW())+5 -> 45927 | V46: 7674 | W46: 12 | X46: 184 | Y46: =INDIRECT("o"&ROW())+10 -> 45932 | Z46: 12895 | AA46: 13 | AB46: 259 | AC46: =IFERROR((INDIRECT("Z"&ROW()) - INDIRECT("R"&ROW())) / INDIRECT("R"&ROW()), "") -> 5.3710474 | AD46: =(INDIRECT("AA"&ROW()) + INDIRECT("AB"&ROW())) / INDIRECT("Z"&ROW()) -> 0.021093447 | AE46: =iferror(INDIRECT("D"&ROW()) / INDIRECT("AI"&ROW()) * 1000,0) -> 516.99573 | AF46: Just had an amazing omakase at one of the best-rated spots in Bangkok (4.9 stars on Google!) ✨🙌 The sushi was super fresh and delicate, and the best part? It was super affordable! I booked through Hungry Hub for a 10-course Hiru omakase for only 1,165 baht – seriously can’t believe the value for this quality! 📍 @kohaku.th @hungryhub_th #bangkok #thailand #bangkokthailand #sushi #omakase #dining & | AI46: =iferror(IFS(Z46>1,Z46,V46>1,V46,R46>1,R46),0) -> 12895
B47: HH-INKI_ | C47: kivalive_ | D47: 6666.66 | E47: Bangkok | F47: 4503 | G47: Copper Beyond Buffet Gaysorn Amarin (Hungry Hub) | H47: International | I47: Instagram | J47: Instagram.com/kivalive_ | L47: Paid Thai | N47: Video | O47: 45937 | P47: https://www.instagram.com/p/DPgTMqaAEMx/ | Q47: =INDIRECT("o"&ROW())+1 -> 45938 | R47: 948 | S47: 6 | T47: 45 | U47: =INDIRECT("o"&ROW())+5 -> 45942 | V47: 10491 | W47: 9 | X47: 227 | Y47: =INDIRECT("o"&ROW())+10 -> 45947 | Z47: 15157 | AA47: 9 | AB47: 334 | AC47: =IFERROR((INDIRECT("Z"&ROW()) - INDIRECT("R"&ROW())) / INDIRECT("R"&ROW()), "") -> 14.988397 | AD47: =(INDIRECT("AA"&ROW()) + INDIRECT("AB"&ROW())) / INDIRECT("Z"&ROW()) -> 0.022629808 | AE47: {=INDIRECT("D"&ROW()) / INDIRECT("Z"&ROW()) * 1000} -> 439.84034 | AF47: Save this must try buffet spot, you don’t wanna miss it! Copper Beyond Buffet the award-winning buffet in bangkok. Why you should try it? - Best Buffet Restaurants in Bangkok - Over 140 dishes - Premium meats, fresh seafood, sushi - Michelin-level desserts. Pro tip: Book through Hungry Hub to get their full Pack A (Lobster Meal) for only 2,599 THB/pax, skip the queue secured your seat in a minute 😉 @hungryhub_th #hungryhubthailand #hungryhub #copperbeyondbuffet #bangkok #bangkokthailand & | AI47: =iferror(IFS(Z47>1,Z47,V47>1,V47,R47>1,R47),0) -> 15157
B48: HH-INLAY | C48: lastminuteguy | E48: Bangkok | F48: 837 | G48: Copper Beyond Buffet The Sense Pinklao (Hungry Hub) | H48: International | I48: Instagram | J48: Instagram.com/lastminuteguy | L48: Paid | N48: Video | O48: 45835 | P48: https://www.instagram.com/p/DLaGzFmyfCx/ | Q48: 45839 | R48: 133867 | S48: 77 | T48: 15650 | U48: =O48+5 -> 45840 | V48: 133876 | W48: 77 | X48: 15650 | Y48: 45852 | Z48: 133925 | AA48: 77 | AB48: 15652 | AC48: =IFERROR((Z48-R48)/R48,"") -> 0.00043326585 | AD48: =(AA48+AB48)/Z48 -> 0.11744633 | AE48: =iferror(INDIRECT("D"&ROW()) / INDIRECT("AI"&ROW()) * 1000,0) -> 0 | AG48: To all the hungry souls out there, I found the best app for you if you are visiting XXX (VO only) | AI48: =iferror(IFS(Z48>1,Z48,V48>1,V48,R48>1,R48),0) -> 133925
B49: HH-INLEH | C49: leslie.koh | E49: Bangkok | F49: 3166 | G49: Koko Japanese Omakase | H49: Japanese | I49: Instagram | J49: Instagram.com/leslie.koh | L49: Paid | N49: Video | O49: 45521 | P49: https://www.instagram.com/p/C-xWpscy8BJ/ | Q49: 45839 | R49: 11466 | S49: 10 | T49: 142 | U49: =O49+5 -> 45526 | Y49: 45852 | Z49: 11474 | AA49: 10 | AB49: 142 | AC49: =IFERROR((Z49-R49)/R49,"") -> 0.00069771498 | AD49: =(AA49+AB49)/Z49 -> 0.013247342 | AE49: =iferror(INDIRECT("D"&ROW()) / INDIRECT("AI"&ROW()) * 1000,0) -> 0 | AG49: This might be the CHEAPEST Omakase in Bangkok (text only) Less than $XX for a 12 Course OMAKASE (voiceover and text) | AI49: =iferror(IFS(Z49>1,Z49,V49>1,V49,R49>1,R49),0) -> 11474
B50: HH-INLEH | C50: leslie.koh | D50: 7593.87 | E50: Bangkok | F50: 4503 | G50: Copper Beyond Buffet Gaysorn Amarin (Hungry Hub) | H50: International | I50: Instagram | J50: Instagram.com/leslie.koh | L50: Paid | N50: Video | O50: 45925 | P50: https://www.instagram.com/p/DPBTEkBEbh7/ | Q50: {=INDIRECT("o"&ROW())+1} -> 45926 | R50: 8736 | S50: 18 | T50: 182 | U50: {=INDIRECT("o"&ROW())+5} -> 45930 | V50: 17243 | W50: 26 | X50: 267 | Y50: {=INDIRECT("o"&ROW())+10} -> 45935 | Z50: 20248 | AA50: 26 | AB50: 288 | AC50: {=IFERROR((INDIRECT("Z"&ROW()) - INDIRECT("R"&ROW())) / INDIRECT("R"&ROW()), "")} -> 1.3177656 | AD50: {=(INDIRECT("AA"&ROW()) + INDIRECT("AB"&ROW())) / INDIRECT("Z"&ROW())} -> 0.015507704 | AE50: =iferror(INDIRECT("D"&ROW()) / INDIRECT("AI"&ROW()) * 1000,0) -> 375.04297 | AF50: This is said to be Bangkok’s BEST buffet and the hype is real. @copperbeyondbuffet at Gaysorn Amarin gives you 2 hours to feast on over 80 à la carte dishes, all made-to-order. Portions are bite-sized so you can try everything and there’s even ChaTraMue milk tea on tap! Pro tip: book via @hungryhub_th for great deals like weekday lunch from ฿1,999! Follow @leslie.koh for more food recommendations! #BangkokEats #HungryHub #CopperBuffet #ThailandFoodie #BangkokFood & | AI50: =iferror(IFS(Z50>1,Z50,V50>1,V50,R50>1,R50),0) -> 20248
B51: HH-INLIY | C51: littlepuffy_diary | E51: Bangkok | F51: 643 | G51: Mojjo Rooftop Lounge & Bar Skyview Hotel | H51: Mexican | I51: Instagram | J51: Instagram.com/littlepuffy_diary | L51: Paid | N51: Video | O51: 45576 | P51: https://www.instagram.com/p/DA-tn0wvnIA/ | Q51: 45839 | R51: 17138 | S51: 17 | T51: 222 | U51: =O51+5 -> 45581 | Y51: 45852 | Z51: 17147 | AA51: 17 | AB51: 222 | AC51: =IFERROR((Z51-R51)/R51,"") -> 0.00052514879 | AD51: =(AA51+AB51)/Z51 -> 0.013938298 | AE51: =iferror(INDIRECT("D"&ROW()) / INDIRECT("AI"&ROW()) * 1000,0) -> 0 | AG51: This rooftop bar is so pretty right? I am XXX and I am at XXX Restaurant (VO and text) | AI51: =iferror(IFS(Z51>1,Z51,V51>1,V51,R51>1,R51),0) -> 17147
B52: HH-INMRN | C52: mrf00dporn | E52: Bangkok | F52: 837 | G52: Copper Beyond Buffet The Sense Pinklao (Hungry Hub) | H52: International | I52: Instagram | J52: Instagram.com/mrf00dporn | L52: Paid | N52: Video | O52: 45499 | P52: https://www.instagram.com/p/C94jS6qh3vi/ | Q52: 45839 | R52: 369214 | S52: 71 | T52: 3272 | U52: =O52+5 -> 45504 | Y52: 45852 | Z52: 369538 | AA52: 71 | AB52: 3276 | AC52: =IFERROR((Z52-R52)/R52,"") -> 0.00087753985 | AD52: =(AA52+AB52)/Z52 -> 0.0090572553 | AE52: =iferror(INDIRECT("D"&ROW()) / INDIRECT("AI"&ROW()) * 1000,0) -> 0 | AG52: Behind me is my favourite buffet spot in the whole of XXX (VO and text) | AI52: =iferror(IFS(Z52>1,Z52,V52>1,V52,R52>1,R52),0) -> 369538
B53: HH-INNAI | C53: namrata_pardasani | E53: Bangkok | F53: #N/A | G53: Copper Beyond Buffet Gaysorn Amarin | H53: #N/A | I53: Instagram | J53: Instagram.com/namrata_pardasani | L53: Paid | N53: Video | O53: 45843 | P53: https://www.instagram.com/p/DLtqh-qRxsP/ | Q53: =O53+1 -> 45844 | R53: 36690 | S53: 35 | U53: =O53+5 -> 45848 | V53: 37165 | W53: 41 | X53: 1672 | Y53: =O53+10 -> 45853 | Z53: 37321 | AA53: 41 | AB53: 1675 | AC53: =IFERROR((Z53-R53)/R53,"") -> 0.017198147 | AD53: =(AA53+AB53)/Z53 -> 0.045979475 | AE53: =iferror(INDIRECT("D"&ROW()) / INDIRECT("AI"&ROW()) * 1000,0) -> 0 | AG53: Hi guys, today I am at XXX Restaurant (VO only) | AI53: =iferror(IFS(Z53>1,Z53,V53>1,V53,R53>1,R53),0) -> 37321
B54: HH-INRAL | C54: randomtravelll | D54: 0 | E54: Bangkok | F54: 1198 | G54: Red Sky Rooftop & Bar 56th Floor | H54: International | I54: Instagram | J54: Instagram.com/randomtravelll | L54: Paid | N54: Video | O54: 45910 | P54: https://www.instagram.com/p/DOazT-YExgx/ | Q54: =INDIRECT("o"&ROW())+1 -> 45911 | R54: 1343 | S54: 16 | T54: 29 | U54: =INDIRECT("o"&ROW())+5 -> 45915 | V54: 1753 | W54: 16 | X54: 36 | Y54: =INDIRECT("o"&ROW())+10 -> 45920 | AC54: =IFERROR((INDIRECT("Z"&ROW()) - INDIRECT("R"&ROW())) / INDIRECT("R"&ROW()), "") -> -1 | AD54: =(INDIRECT("AA"&ROW()) + INDIRECT("AB"&ROW())) / INDIRECT("Z"&ROW()) -> #DIV/0! | AE54: =iferror(INDIRECT("D"&ROW()) / INDIRECT("AI"&ROW()) * 1000,0) -> 0 | AF54: 🚨 What if I told you luxury dining in Bangkok doesn’t have to be crazy expensive? 👀✨ From sipping cocktails 56 floors above the city at Red Sky Rooftop 🌇🍸 … to soaking in views that feel unreal 🤯—we got it all at Only 1,099 baht to enjoy a stunning view in Bangkok , thanks to Hungry Hub. 💸 Why just dream luxury… when you can actually live it? 🥂 👉 Book smart. Dine smarter. Download Hungry Hub NOW !!! . Available on both Apple and Android. Do follow us on Instagram @randomtravelll #randomtravelll #bangkok #thailand #bar #rooftop #hungryhub [ bangkok nightlife, bangkok rooftop bars, bangkok city views, best rooftop bar bangkok, food deals, bangkok travel guide, dining in bangkok, bangkok rooftop restaurants, rooftop bar thailand , luxury dining bangkok, cheap eats bangkok, bangkok cocktail bars, bangkok dinner deals, bangkok foodie, bangkok travel tips, rooftop dining bangkok, bangkok sky bar, bangkok city lights, thailand travel, bangkok restaurants, rooftop bar experience, bangkok trip, food in bangkok, bangkok travel blog, hidden gems bangkok, rooftop cocktails bangkok, bangkok travel deals, bangkok night views , red sky 56th floor , red sky rooftop bar , bangkok best rooftop bars , restaurants in bangkok , food reel , food video , randomtravelll , bangkok , thailand ] & | AI54: =iferror(IFS(Z54>1,Z54,V54>1,V54,R54>1,R54),0) -> 1753
B55: HH-INRAL | C55: randomtravelll | D55: 0 | E55: Bangkok | F55: 1198 | G55: Red Sky Rooftop & Bar 56th Floor | H55: International | I55: Instagram | J55: Instagram.com/randomtravelll | L55: Paid Thai | N55: Video | O55: 45918 | P55: https://www.instagram.com/p/DOv_UoZk3Cs/ | Q55: =INDIRECT("o"&ROW())+1 -> 45919 | R55: 27276 | S55: 20 | T55: 109 | U55: =INDIRECT("o"&ROW())+5 -> 45923 | Y55: =INDIRECT("o"&ROW())+10 -> 45928 | Z55: 27464 | AA55: 20 | AB55: 110 | AC55: =IFERROR((INDIRECT("Z"&ROW()) - INDIRECT("R"&ROW())) / INDIRECT("R"&ROW()), "") -> 0.0068925062 | AD55: =(INDIRECT("AA"&ROW()) + INDIRECT("AB"&ROW())) / INDIRECT("Z"&ROW()) -> 0.0047334693 | AE55: =iferror(INDIRECT("D"&ROW()) / INDIRECT("AI"&ROW()) * 1000,0) -> 0 | AF55: 🚨 What if I told you luxury dining in Bangkok doesn’t have to be crazy expensive? 👀✨ From sipping cocktails 56 floors above the city at Red Sky Rooftop 🌇🍸 … to soaking in views that feel unreal 🤯—we got it all at Only 1,099 baht to enjoy a stunning view in Bangkok , thanks to Hungry Hub. 💸 Why just dream luxury… when you can actually live it? 🥂 👉 Book smart. Dine smarter. Download Hungry Hub NOW !!! . Available on both Apple and Android. Do follow us on Instagram @randomtravelll #randomtravelll #bangkok #thailand #bar #rooftop #hungryhub [ bangkok nightlife, bangkok rooftop bars, bangkok city views, best rooftop bar bangkok, food deals, bangkok travel guide, dining in bangkok, bangkok rooftop restaurants, rooftop bar thailand , luxury dining bangkok, cheap eats bangkok, bangkok cocktail bars, bangkok dinner deals, bangkok foodie, bangkok travel tips, rooftop dining bangkok, bangkok sky bar, bangkok city lights, thailand travel, bangkok restaurants, rooftop bar experience, bangkok trip, food in bangkok, bangkok travel blog, hidden gems bangkok, rooftop cocktails bangkok, bangkok travel deals, bangkok night views , red sky 56th floor , red sky rooftop bar , bangkok best rooftop bars , restaurants in bangkok , food reel , food video , randomtravelll , bangkok , thailand ] & | AI55: =iferror(IFS(Z55>1,Z55,V55>1,V55,R55>1,R55),0) -> 27464
B56: HH-INSGO | C56: sgadventurousduo | D56: 5063 | E56: Bangkok | F56: 3005 | G56: Great Harbour International Buffet | H56: International | I56: Tiktok | J56: https://tiktok.com/@sgadventurousduo | L56: Paid | N56: Video | O56: 45601 | P56: https://www.tiktok.com/@sgadventurousduo/video/7433737671043747073 | Q56: =INDIRECT("o"&ROW())+1 -> 45602 | R56: 187151 | S56: 62 | T56: 2083 | U56: =INDIRECT("o"&ROW())+5 -> 45606 | Y56: =INDIRECT("o"&ROW())+10 -> 45611 | AC56: =IFERROR((INDIRECT("Z"&ROW()) - INDIRECT("R"&ROW())) / INDIRECT("R"&ROW()), "") -> -1 | AD56: =(INDIRECT("AA"&ROW()) + INDIRECT("AB"&ROW())) / INDIRECT("Z"&ROW()) -> #DIV/0! | AE56: {=INDIRECT("D"&ROW()) / INDIRECT("Z"&ROW()) * 1000} -> #DIV/0! | AF56: Omg this buffet has a DIY bubble tea station and a chocolate fountain?! Check out @HungryHub_Official for the best food deals 📍Great Harbour International Buffet 6th Floor, ICONSIAM, Charoen Nakhon Rd, Khlong Ton Sai, Khlong San, Bangkok 10600, Thailand Opening hours as per Google: Daily: 12–2:30 pm 5–9 pm & [null] | AI56: =iferror(IFS(Z56>1,Z56,V56>1,V56,R56>1,R56),0) -> 187151
